Workbook
Name ACTION: #REF!
Name ACTION: #REF!

Sheet Cover
B2: TEST REPORT DOCUMENT
A4: Project Name | B4: BrandHub - AI-Powered Multi-Channel Content Platform | E4: Creator | F4: Trung
A5: Project Code | B5: BRANDHUB | E5: Issue Date | F5: 46300
A6: Document Code | B6: =B5&"_"&"Test Report"&"_"&"v1.0" -> BRANDHUB_Test Report_v1.0 | E6: Version | F6: v1.0
A9: Record of change
A10: Effective Date | B10: Version | C10: Change Item | D10: *A,D,M | E10: Change description | F10: Reference
A11: 46300 | B11: v1.0 | C11: All Document | D11: A | E11: Create document - test report for all FRs | F11: Report5_Unit Test.xls

Sheet Test Cases
D1: TEST CASE LIST
B3: Project Name | D3: BrandHub - AI-Powered Multi-Channel Content Platform
B4: Project Code | D4: BRANDHUB
B5: Test Environment Setup Description | D5: 1. Server: Spring Boot 3 business-service (8081), api-gateway (8080), publisher-service (8083), FastAPI ai-service (8082) 2. Database: PostgreSQL 17, MongoDB Atlas, Redis, ChromaDB, Neo4j 3. Message broker: RabbitMQ 4. Web browser: Chrome (latest)
B8: No | C8: Function Name | D8: Sheet Name | E8: Description | F8: Pre-Condition
B9: 1 | C9: 3.2.1 Sign Up (Email + OTP) | D9: Authentication | E9: Register a new account with email/password/fullName, store hashed password, assign USER role, email a 6-digit OTP | F9: Can connect with server; Email not registered
B10: 2 | C10: 3.2.2 Sign In with Email | D10: Authentication | E10: Authenticate by email/phone identifier + password, check account status, issue JWT access + refresh tokens or 2FA challenge | F10: Can connect with server; Account ACTIVE and email verified
B11: 3 | C11: 3.2.3 Sign In with Google OAuth | D11: Authentication | E11: Handle Google callback: verify state, exchange code, login/create/link user and issue JWT or 2FA token | F11: Can connect with server; OAuth state valid in Redis for GOOGLE
B12: 4 | C12: 3.2.4 Reset Password | D12: Authentication | E12: Consume a one-time reset token and set a new bcrypt password, invalidating older sessions via lastPasswordChange | F12: Can connect with server; Reset token valid in Redis
B13: 5 | C13: 3.2.5 Change Password | D13: Authentication | E13: Change password for the logged-in user after verifying current password and rejecting a same-as-current password | F13: Can connect with server; User has password hash
B14: 6 | C14: 3.2.6 OTP Verification | D14: Authentication | E14: Verify the 6-digit email OTP with expiry check, attempt counter (max lockout) and idempotent already-verified handling | F14: Can connect with server; User registered, email not verified, OTP valid
B15: 7 | C15: 3.2.7 Two-Factor Authentication (TOTP) | D15: Authentication | E15: Verify the 2FA challenge token and TOTP code after password login, with 5-attempt lockout, then issue JWT tokens | F15: Can connect with server; User has 2FA enabled with TOTP secret
B16: 8 | C16: 3.2.8 Sign Out | D16: Authentication | E16: Blacklist access and refresh tokens, write LOGOUT audit log; idempotent for invalid/expired tokens | F16: Can connect with server; User logged in with valid tokens
B17: 9 | C17: 3.2.9 Deactivate Account | D17: Authentication | E17: Deactivate own account after password (or OTP for OAuth-only) re-auth, block if owning active agency, revoke tokens | F17: Can connect with server; User has password, owns no active agency
B18: 10 | C18: 3.3.1 View User Profile | D18: Profile | E18: Return the authenticated user's profile (identity, extended fields, preferences) for the current user | F18: Can connect with server; User exists
B19: 11 | C19: 3.3.2 Update Profile | D19: Profile | E19: Update own profile fields (fullName required, optional fields partial), merging preferences without overwriting other keys | F19: Can connect with server; User exists
B20: 12 | C20: 3.3.3 View Client Profile | D20: Profile | E20: List all client profiles owned by the current user (and fetch one by id with ownership check) | F20: Can connect with server; User owns 1 client profile
... B134: 126 | C134: 3.10.12 Export Report File PDF | D134: Admin | E134: Admin exports a user or revenue report to PDF for a date range; empty data still yields a PDF | F134: Can connect with server; Caller has ADMIN system role

Sheet Test Statistics
B1: TEST STATISTICS
B3: Project Name | C3: BrandHub - AI-Powered Multi-Channel Content Platform | E3: Creator | G3: Trung
B4: Project Code | C4: BRANDHUB | E4: Reviewer/Approver
B5: Document Code | C5: =C4&"_"&"Test Report"&"_"&"v1.0" -> BRANDHUB_Test Report_v1.0 | E5: Issue Date | H5: 46300
B6: Notes | C6: Release 1 includes 9 modules: Authentication, Profile, Agency & Workspace, Media Package, Content & Task, AI Features, Publishing, Billing, Admin
B10: No | C10: Module code | D10: Passed | E10: Failed | F10: Pending | G10: N/A | H10: Number of test cases
B11: 1 | C11: =Authentication!B2 -> Authentication | D11: =Authentication!B6 -> 160 | E11: =Authentication!C6 -> 0 | F11: =Authentication!D6 -> 0 | G11: =Authentication!E6 -> 0 | H11: =Authentication!B4 -> 160
B12: 2 | C12: =Profile!B2 -> Profile | D12: =Profile!B6 -> 71 | E12: =Profile!C6 -> 0 | F12: =Profile!D6 -> 0 | G12: =Profile!E6 -> 0 | H12: =Profile!B4 -> 71
B13: 3 | C13: ='Agency & Workspace'!B2 -> Agency & Workspace | D13: ='Agency & Workspace'!B6 -> 394 | E13: ='Agency & Workspace'!C6 -> 0 | F13: ='Agency & Workspace'!D6 -> 0 | G13: ='Agency & Workspace'!E6 -> 0 | H13: ='Agency & Workspace'!B4 -> 394
B14: 4 | C14: ='Media Package'!B2 -> Media Package | D14: ='Media Package'!B6 -> 73 | E14: ='Media Package'!C6 -> 0 | F14: ='Media Package'!D6 -> 126 | G14: ='Media Package'!E6 -> 0 | H14: ='Media Package'!B4 -> 199
B15: 5 | C15: ='Content & Task'!B2 -> Content & Task | D15: ='Content & Task'!B6 -> 151 | E15: ='Content & Task'!C6 -> 0 | F15: ='Content & Task'!D6 -> 511 | G15: ='Content & Task'!E6 -> 0 | H15: ='Content & Task'!B4 -> 662
B16: 6 | C16: ='AI Features'!B2 -> AI Features | D16: ='AI Features'!B6 -> 122 | E16: ='AI Features'!C6 -> 0 | F16: ='AI Features'!D6 -> 84 | G16: ='AI Features'!E6 -> 0 | H16: ='AI Features'!B4 -> 206
B17: 7 | C17: =Publishing!B2 -> Publishing | D17: =Publishing!B6 -> 81 | E17: =Publishing!C6 -> 0 | F17: =Publishing!D6 -> 215 | G17: =Publishing!E6 -> 0 | H17: =Publishing!B4 -> 296
B18: 8 | C18: =Billing!B2 -> Billing | D18: =Billing!B6 -> 32 | E18: =Billing!C6 -> 0 | F18: =Billing!D6 -> 82 | G18: =Billing!E6 -> 0 | H18: =Billing!B4 -> 114
B19: 9 | C19: =Admin!B2 -> Admin | D19: =Admin!B6 -> 33 | E19: =Admin!C6 -> 0 | F19: =Admin!D6 -> 152 | G19: =Admin!E6 -> 0 | H19: =Admin!B4 -> 185
C21: Sub total | D21: =SUM(D11:D19) -> 1117 | E21: =SUM(E11:E19) -> 0 | F21: =SUM(F11:F19) -> 1170 | G21: =SUM(G11:G19) -> 0 | H21: =SUM(H11:H19) -> 2287
C23: Test coverage | E23: =(D21+E21)*100/(H21-G21) -> 48.841277 | F23: %
C24: Test successful coverage | E24: =D21*100/(H21-G21) -> 48.841277 | F24: %

Sheet Authentication
A2: Feature | B2: Authentication | R2: Passed
A3: Test requirement | B3: Functional test of 3.2.1 Sign Up (Email + OTP); 3.2.2 Sign In with Email; 3.2.3 Sign In with Google OAuth; 3.2.4 Reset Password and 5 more | R3: Failed
A4: Number of TCs | B4: =COUNTA(F12:F1000) -> 160 | R4: Pending
A5: Testing Round | B5: Passed | C5: Failed | D5: Pending | E5: N/A | R5: N/A
A6: Round 1 | B6: =COUNTIF($F$10:$F$998,B$5) -> 160 | C6: =COUNTIF($F$10:$F$998,C$5) -> 0 | D6: =COUNTIF($F$10:$F$998,D$5) -> 0 | E6: =COUNTIF($F$10:$F$998,E$5) -> 0
A7: Round 2 | B7: =COUNTIF($I$10:$I$998,B$5) -> 0 | C7: =COUNTIF($I$10:$I$998,C$5) -> 0 | D7: =COUNTIF($I$10:$I$998,D$5) -> 160 | E7: =COUNTIF($I$10:$I$998,E$5) -> 0
A8: Round 3 | B8: =COUNTIF($L$10:$L$998,B$5) -> 0 | C8: =COUNTIF($L$10:$L$998,C$5) -> 0 | D8: =COUNTIF($L$10:$L$998,D$5) -> 160 | E8: =COUNTIF($L$10:$L$998,E$5) -> 0
A10: Test Case ID | B10: Test Case Description | C10: Test Case Procedure | D10: Expected Results | E10: Pre-conditions | F10: Round 1 | G10: Test date | H10: Tester | I10: Round 2 | J10: Test date | K10: Tester | L10: Round 3 | M10: Test date | N10: Tester | O10: Note
A11: 3.2.1 Sign Up (Email + OTP)
A12: FR3.2.1-01 | B12: [Normal] Sign Up (Email + OTP) with email = new@brandhub.vn, password = Abc@12345, fullName = Nguyen Van A | C12: 1. Prepare the state listed in Pre-conditions. 2. Call AuthServiceImpl.register with: email = new@brandhub.vn; password = Abc@12345; fullName = Nguyen Van A. 3. Check the response / error and the log. | D12: 201 Created - RegisterResponse(userId) Log: OTP email sent to new@brandhub.vn | E12: - Can connect with server - Email not registered | F12: Passed | G12: 46300 | H12: Trung | I12: Pending | L12: Pending
A13: FR3.2.1-02 | B13: [Normal] Sign Up (Email + OTP) with email = Mixed@BrandHub.VN , password = Abc@12345, fullName = Nguyen Van A | C13: 1. Prepare the state listed in Pre-conditions. 2. Call AuthServiceImpl.register with: email = Mixed@BrandHub.VN ; password = Abc@12345; fullName = Nguyen Van A. 3. Check the response / error and the log. | D13: 201 Created - email stored lowercase and trimmed Log: OTP email sent | E13: - Can connect with server - Email not registered | F13: Passed | G13: 46300 | H13: Trung | I13: Pending | L13: Pending
A14: FR3.2.1-03 | B14: [Normal] Sign Up (Email + OTP) with email = new@brandhub.vn, password = Abc@12345, fullName = Tran B | C14: 1. Prepare the state listed in Pre-conditions. 2. Call AuthServiceImpl.register with: email = new@brandhub.vn; password = Abc@12345; fullName = Tran B . 3. Check the response / error and the log. | D14: 201 Created - fullName stored trimmed Log: OTP email sent | E14: - Can connect with server - Email not registered | F14: Passed | G14: 46300 | H14: Trung | I14: Pending | L14: Pending
A15: FR3.2.1-04 | B15: [Normal] Sign Up (Email + OTP) with email = new@brandhub.vn, password = Abc@12345, fullName = Nguyen Van A | C15: 1. Prepare the state listed in Pre-conditions. 2. Call AuthServiceImpl.register with: email = new@brandhub.vn; password = Abc@12345; fullName = Nguyen Van A. 3. Check the response / error and the log. | D15: 201 Created - password saved as bcrypt hash, not plaintext | E15: - Can connect with server - Email not registered | F15: Passed | G15: 46300 | H15: Trung | I15: Pending | L15: Pending
A16: FR3.2.1-05 | B16: [Normal] Sign Up (Email + OTP) with email = new@brandhub.vn, password = Abc@12345, fullName = Nguyen Van A | C16: 1. Prepare the state listed in Pre-conditions. 2. Call AuthServiceImpl.register with: email = new@brandhub.vn; password = Abc@12345; fullName = Nguyen Van A. 3. Check the response / error and the log. | D16: 201 Created - UserSystemRole USER saved, emailVerifiedAt null | E16: - Can connect with server - Email not registered | F16: Passed | G16: 46300 | H16: Trung | I16: Pending | L16: Pending
A17: FR3.2.1-06 | B17: [Normal] Sign Up (Email + OTP) with email = new@brandhub.vn, password = Abc@12345, fullName = Nguyen Van A | C17: 1. Prepare the state listed in Pre-conditions. 2. Call AuthServiceImpl.register with: email = new@brandhub.vn; password = Abc@12345; fullName = Nguyen Van A. 3. Check the response / error and the log. | D17: 201 Created - OTP expiry set to now + 10 minutes | E17: - Can connect with server - Email not registered | F17: Passed | G17: 46300 | H17: Trung | I17: Pending | L17: Pending
A18: FR3.2.1-07 | B18: [Normal] Sign Up (Email + OTP) with email = new@brandhub.vn, password = Abc@12345, fullName = Nguyen Van A | C18: 1. Prepare the state listed in Pre-conditions. 2. Call AuthServiceImpl.register with: email = new@brandhub.vn; password = Abc@12345; fullName = Nguyen Van A. 3. Check the response / error and the log. | D18: 201 Created - unverified user cannot login until OTP verified Log: OTP email sent | E18: - Can connect with server - Email not registered | F18: Passed | G18: 46300 | H18: Trung | I18: Pending | L18: Pending
A19: FR3.2.1-08 | B19: [Boundary] Sign Up (Email + OTP) with email = new@brandhub.vn, password = Abcdef12, fullName = Nguyen Van A | C19: 1. Prepare the state listed in Pre-conditions. 2. Call AuthServiceImpl.register with: email = new@brandhub.vn; password = Abcdef12; fullName = Nguyen Van A. 3. Check the response / error and the log. | D19: 201 Created - password exactly 8 chars with 1 digit accepted Log: OTP email sent | E19: - Can connect with server - Email not registered | F19: Passed | G19: 46300 | H19: Trung | I19: Pending | L19: Pending
A20: FR3.2.1-09 | B20: [Boundary] Sign Up (Email + OTP) with email = new@brandhub.vn, password = Abcdefg1, fullName = N | C20: 1. Prepare the state listed in Pre-conditions. 2. Call AuthServiceImpl.register with: email = new@brandhub.vn; password = Abcdefg1; fullName = N. 3. Check the response / error and the log. | D20: 201 Created - fullName 1 char accepted Log: OTP email sent | E20: - Can connect with server - Email not registered | F20: Passed | G20: 46300 | H20: Trung | I20: Pending | L20: Pending
A21: FR3.2.1-10 | B21: [Boundary] Sign Up (Email + OTP) with email = new@brandhub.vn, password = Abcdef1, fullName = Nguyen Van A | C21: 1. Prepare the state listed in Pre-conditions. 2. Call AuthServiceImpl.register with: email = new@brandhub.vn; password = Abcdef1; fullName = Nguyen Van A. 3. Check the response / error and the log. | D21: Error: VALIDATION_ERROR - Password must be at least 8 characters (7 chars) | E21: - Can connect with server - Email not registered | F21: Passed | G21: 46300 | H21: Trung | I21: Pending | L21: Pending
A22: FR3.2.1-11 | B22: [Abnormal] Sign Up (Email + OTP) with email = new@brandhub.vn, password = Abc@12345, fullName = Nguyen Van A | C22: 1. Prepare the state listed in Pre-conditions. 2. Call AuthServiceImpl.register with: email = new@brandhub.vn; password = Abc@12345; fullName = Nguyen Van A. 3. Check the response / error and the log. | D22: Error: EMAIL_ALREADY_EXISTS - 409 This email is already associated with another account | E22: - Can connect with server - Email already registered | F22: Passed | G22: 46300 | H22: Trung | I22: Pending | L22: Pending
A23: FR3.2.1-12 | B23: [Abnormal] Sign Up (Email + OTP) with email = NEW@BrandHub.vn, password = Abc@12345, fullName = Nguyen Van A | C23: 1. Prepare the state listed in Pre-conditions. 2. Call AuthServiceImpl.register with: email = NEW@BrandHub.vn; password = Abc@12345; fullName = Nguyen Van A. 3. Check the response / error and the log. | D23: Error: EMAIL_ALREADY_EXISTS - case-insensitive duplicate, no new account, no OTP resend | E23: - Can connect with server - Email already registered | F23: Passed | G23: 46300 | H23: Trung | I23: Pending | L23: Pending
... A29: FR3.2.1-18 | B29: [Abnormal] Sign Up (Email + OTP) with email = new@brandhub.vn, password = Abc@12345, fullName = empty | C29: 1. Prepare the state listed in Pre-conditions. 2. Call AuthServiceImpl.register with: email = new@brandhub.vn; password = Abc@12345; fullName = empty. 3. Check the response / error and the log. | D29: Error: VALIDATION_ERROR - fullName must not be blank | E29: - Can connect with server | F29: Passed | G29: 46300 | H29: Trung | I29: Pending | L29: Pending
A30: 3.2.2 Sign In with Email
A31: FR3.2.2-01 | B31: [Normal] Sign In with Email with identifier = user@brandhub.vn, password = Abc@12345 | C31: 1. Prepare the state listed in Pre-conditions. 2. Call AuthServiceImpl.login with: identifier = user@brandhub.vn; password = Abc@12345. 3. Check the response / error and the log. | D31: 200 OK - LoginResponse(accessToken, expiresIn) + refresh token Log: Audit LOGIN saved | E31: - Can connect with server - Account ACTIVE and email verified | F31: Passed | G31: 46300 | H31: Trung | I31: Pending | L31: Pending
A32: FR3.2.2-02 | B32: [Normal] Sign In with Email with identifier = USER@BrandHub.VN, password = Abc@12345 | C32: 1. Prepare the state listed in Pre-conditions. 2. Call AuthServiceImpl.login with: identifier = USER@BrandHub.VN; password = Abc@12345. 3. Check the response / error and the log. | D32: 200 OK - identifier matched case-insensitively Log: Audit LOGIN saved | E32: - Can connect with server - Account ACTIVE and email verified | F32: Passed | G32: 46300 | H32: Trung | I32: Pending | L32: Pending
A33: FR3.2.2-03 | B33: [Normal] Sign In with Email with identifier = +84901234567, password = Abc@12345 | C33: 1. Prepare the state listed in Pre-conditions. 2. Call AuthServiceImpl.login with: identifier = +84901234567; password = Abc@12345. 3. Check the response / error and the log. | D33: 200 OK - login by phone identifier Log: Audit LOGIN saved | E33: - Can connect with server - Account ACTIVE and email verified - Identifier is a linked phone number | F33: Passed | G33: 46300 | H33: Trung | I33: Pending | L33: Pending
A34: FR3.2.2-04 | B34: [Normal] Sign In with Email with identifier = user@brandhub.vn, password = Abc@12345 | C34: 1. Prepare the state listed in Pre-conditions. 2. Call AuthServiceImpl.login with: identifier = user@brandhub.vn; password = Abc@12345. 3. Check the response / error and the log. | D34: 200 OK - lastLoginAt updated | E34: - Can connect with server - Account ACTIVE and email verified | F34: Passed | G34: 46300 | H34: Trung | I34: Pending | L34: Pending
A35: FR3.2.2-05 | B35: [Normal] Sign In with Email with identifier = user@brandhub.vn, password = Abc@12345 | C35: 1. Prepare the state listed in Pre-conditions. 2. Call AuthServiceImpl.login with: identifier = user@brandhub.vn; password = Abc@12345. 3. Check the response / error and the log. | D35: 200 OK - access token contains workspaceId claim | E35: - Can connect with server - Account ACTIVE and email verified - User has active workspace | F35: Passed | G35: 46300 | H35: Trung | I35: Pending | L35: Pending
A36: FR3.2.2-06 | B36: [Normal] Sign In with Email with identifier = admin@brandhub.vn, password = Abc@12345 | C36: 1. Prepare the state listed in Pre-conditions. 2. Call AuthServiceImpl.login with: identifier = admin@brandhub.vn; password = Abc@12345. 3. Check the response / error and the log. | D36: 200 OK - access token role=ADMIN | E36: - Can connect with server - Account ACTIVE and email verified - User has role ADMIN | F36: Passed | G36: 46300 | H36: Trung | I36: Pending | L36: Pending
A37: FR3.2.2-07 | B37: [Normal] Sign In with Email with identifier = user@brandhub.vn, password = Abc@12345 | C37: 1. Prepare the state listed in Pre-conditions. 2. Call AuthServiceImpl.login with: identifier = user@brandhub.vn; password = Abc@12345. 3. Check the response / error and the log. | D37: 200 OK - workspaceId claim null | E37: - Can connect with server - Account ACTIVE and email verified - User has no workspace | F37: Passed | G37: 46300 | H37: Trung | I37: Pending | L37: Pending
A38: FR3.2.2-08 | B38: [Normal] Sign In with Email with identifier = user@brandhub.vn, password = Abc@12345 | C38: 1. Prepare the state listed in Pre-conditions. 2. Call AuthServiceImpl.login with: identifier = user@brandhub.vn; password = Abc@12345. 3. Check the response / error and the log. | D38: 200 OK - LoginResponse.twoFactorChallenge(twoFactorToken), no access token | E38: - Can connect with server - Account ACTIVE and email verified - 2FA enabled for user | F38: Passed | G38: 46300 | H38: Trung | I38: Pending | L38: Pending
A39: FR3.2.2-09 | B39: [Normal] Sign In with Email with identifier = user@brandhub.vn, password = Abc@12345 | C39: 1. Prepare the state listed in Pre-conditions. 2. Call AuthServiceImpl.login with: identifier = user@brandhub.vn; password = Abc@12345. 3. Check the response / error and the log. | D39: 200 OK - refresh token returned with refreshExpirationMs | E39: - Can connect with server - Account ACTIVE and email verified | F39: Passed | G39: 46300 | H39: Trung | I39: Pending | L39: Pending
A40: FR3.2.2-10 | B40: [Boundary] Sign In with Email with identifier = user@brandhub.vn, password = A1234567 | C40: 1. Prepare the state listed in Pre-conditions. 2. Call AuthServiceImpl.login with: identifier = user@brandhub.vn; password = A1234567. 3. Check the response / error and the log. | D40: 200 OK - 8-char password matches | E40: - Can connect with server - Account ACTIVE and email verified | F40: Passed | G40: 46300 | H40: Trung | I40: Pending | L40: Pending
A41: FR3.2.2-11 | B41: [Abnormal] Sign In with Email with identifier = ghost@brandhub.vn, password = Abc@12345 | C41: 1. Prepare the state listed in Pre-conditions. 2. Call AuthServiceImpl.login with: identifier = ghost@brandhub.vn; password = Abc@12345. 3. Check the response / error and the log. | D41: Error: INVALID_CREDENTIALS - 401 Invalid email or password | E41: - Can connect with server - Email not registered | F41: Passed | G41: 46300 | H41: Trung | I41: Pending | L41: Pending
A42: FR3.2.2-12 | B42: [Abnormal] Sign In with Email with identifier = user@brandhub.vn, password = WrongPass1 | C42: 1. Prepare the state listed in Pre-conditions. 2. Call AuthServiceImpl.login with: identifier = user@brandhub.vn; password = WrongPass1. 3. Check the response / error and the log. | D42: Error: INVALID_CREDENTIALS - 401 Invalid email or password | E42: - Can connect with server - Account ACTIVE and email verified | F42: Passed | G42: 46300 | H42: Trung | I42: Pending | L42: Pending
... A48: FR3.2.2-18 | B48: [Abnormal] Sign In with Email with identifier = user@brandhub.vn, password = null | C48: 1. Prepare the state listed in Pre-conditions. 2. Call AuthServiceImpl.login with: identifier = user@brandhub.vn; password = null. 3. Check the response / error and the log. | D48: Error: VALIDATION_ERROR - password must not be blank | E48: - Can connect with server | F48: Passed | G48: 46300 | H48: Trung | I48: Pending | L48: Pending
A49: 3.2.3 Sign In with Google OAuth
A50: FR3.2.3-01 | B50: [Normal] Sign In with Google OAuth with code = valid code, state = valid state | C50: 1. Prepare the state listed in Pre-conditions. 2. Call OAuthService (GoogleOAuthService).handleCallback with: code = valid code; state = valid state. 3. Check the response / error and the log. | D50: 200 OK - CallbackResult(loginResult), access + refresh token issued Log: Audit LOGIN saved | E50: - Can connect with server - OAuth state valid in Redis for GOOGLE - Google account already linked to a user | F50: Passed | G50: 46300 | H50: Trung | I50: Pending | L50: Pending
A51: FR3.2.3-02 | B51: [Normal] Sign In with Google OAuth with code = valid code, state = valid state | C51: 1. Prepare the state listed in Pre-conditions. 2. Call OAuthService (GoogleOAuthService).handleCallback with: code = valid code; state = valid state. 3. Check the response / error and the log. | D51: 200 OK - new OAuth-only user created (emailVerifiedAt set, role USER) and logged in Log: Audit LOGIN saved | E51: - Can connect with server - OAuth state valid in Redis for GOOGLE - No user with Google email | F51: Passed | G51: 46300 | H51: Trung | I51: Pending | L51: Pending
A52: FR3.2.3-03 | B52: [Normal] Sign In with Google OAuth with code = valid code, state = valid state | C52: 1. Prepare the state listed in Pre-conditions. 2. Call OAuthService (GoogleOAuthService).handleCallback with: code = valid code; state = valid state. 3. Check the response / error and the log. | D52: 200 OK - Google provider linked to existing account, logged in Log: Audit LOGIN saved | E52: - Can connect with server - OAuth state valid in Redis for GOOGLE - Existing password user with same email | F52: Passed | G52: 46300 | H52: Trung | I52: Pending | L52: Pending
A53: FR3.2.3-04 | B53: [Normal] Sign In with Google OAuth with code = valid code, state = valid state | C53: 1. Prepare the state listed in Pre-conditions. 2. Call OAuthService (GoogleOAuthService).handleCallback with: code = valid code; state = valid state. 3. Check the response / error and the log. | D53: 200 OK - CallbackResult(twoFactorToken), no access token | E53: - Can connect with server - OAuth state valid in Redis for GOOGLE - Google account already linked to a user - 2FA enabled for user | F53: Passed | G53: 46300 | H53: Trung | I53: Pending | L53: Pending
A54: FR3.2.3-05 | B54: [Normal] Sign In with Google OAuth with code = valid code, state = valid link state | C54: 1. Prepare the state listed in Pre-conditions. 2. Call OAuthService (GoogleOAuthService).handleCallback with: code = valid code; state = valid link state. 3. Check the response / error and the log. | D54: 200 OK - CallbackResult(isLinkMode=true, linkedProvider=GOOGLE) | E54: - Can connect with server - OAuth state valid in Redis for GOOGLE with linkingUserId - Link email equals current user email | F54: Passed | G54: 46300 | H54: Trung | I54: Pending | L54: Pending
A55: FR3.2.3-06 | B55: [Normal] Sign In with Google OAuth with code = valid code, state = valid state | C55: 1. Prepare the state listed in Pre-conditions. 2. Call OAuthService (GoogleOAuthService).handleCallback with: code = valid code; state = valid state. 3. Check the response / error and the log. | D55: 200 OK - state key consumed (getAndDelete), lastLoginAt updated | E55: - Can connect with server - OAuth state valid in Redis for GOOGLE - Google account already linked to a user | F55: Passed | G55: 46300 | H55: Trung | I55: Pending | L55: Pending
A56: FR3.2.3-07 | B56: [Normal] Sign In with Google OAuth with code = valid code, state = valid state | C56: 1. Prepare the state listed in Pre-conditions. 2. Call OAuthService (GoogleOAuthService).handleCallback with: code = valid code; state = valid state. 3. Check the response / error and the log. | D56: 200 OK - new user avatarUrl taken from Google profile | E56: - Can connect with server - OAuth state valid in Redis for GOOGLE - No user with Google email - Google profile has avatar | F56: Passed | G56: 46300 | H56: Trung | I56: Pending | L56: Pending
A57: FR3.2.3-08 | B57: [Normal] Sign In with Google OAuth with code = valid code, state = valid state | C57: 1. Prepare the state listed in Pre-conditions. 2. Call OAuthService (GoogleOAuthService).handleCallback with: code = valid code; state = valid state. 3. Check the response / error and the log. | D57: 200 OK - access token has workspaceId claim | E57: - Can connect with server - OAuth state valid in Redis for GOOGLE - Existing user has active workspace | F57: Passed | G57: 46300 | H57: Trung | I57: Pending | L57: Pending
A58: FR3.2.3-09 | B58: [Boundary] Sign In with Google OAuth with code = valid code, state = valid state | C58: 1. Prepare the state listed in Pre-conditions. 2. Call OAuthService (GoogleOAuthService).handleCallback with: code = valid code; state = valid state. 3. Check the response / error and the log. | D58: 200 OK - email lowercased and trimmed before lookup/create | E58: - Can connect with server - OAuth state valid in Redis for GOOGLE - Google email has mixed case/spaces | F58: Passed | G58: 46300 | H58: Trung | I58: Pending | L58: Pending
A59: FR3.2.3-10 | B59: [Boundary] Sign In with Google OAuth with code = valid code, state = valid link state | C59: 1. Prepare the state listed in Pre-conditions. 2. Call OAuthService (GoogleOAuthService).handleCallback with: code = valid code; state = valid link state. 3. Check the response / error and the log. | D59: 200 OK - equalsIgnoreCase match, provider linked | E59: - Can connect with server - OAuth state valid in Redis for GOOGLE with linkingUserId - Link email differs only by case | F59: Passed | G59: 46300 | H59: Trung | I59: Pending | L59: Pending
A60: FR3.2.3-11 | B60: [Abnormal] Sign In with Google OAuth with code = valid code, state = expired state | C60: 1. Prepare the state listed in Pre-conditions. 2. Call OAuthService (GoogleOAuthService).handleCallback with: code = valid code; state = expired state. 3. Check the response / error and the log. | D60: Error: OAUTH_STATE_INVALID - 400 OAuth state is invalid or has expired | E60: - Can connect with server - State not in Redis (expired or reused) | F60: Passed | G60: 46300 | H60: Trung | I60: Pending | L60: Pending
A61: FR3.2.3-12 | B61: [Abnormal] Sign In with Google OAuth with code = valid code, state = foreign state | C61: 1. Prepare the state listed in Pre-conditions. 2. Call OAuthService (GoogleOAuthService).handleCallback with: code = valid code; state = foreign state. 3. Check the response / error and the log. | D61: Error: OAUTH_STATE_INVALID - 400 OAuth state is invalid or has expired | E61: - Can connect with server - State stored for a different provider | F61: Passed | G61: 46300 | H61: Trung | I61: Pending | L61: Pending
... A68: FR3.2.3-19 | B68: [Abnormal] Sign In with Google OAuth with code = valid code, state = valid link state | C68: 1. Prepare the state listed in Pre-conditions. 2. Call OAuthService (GoogleOAuthService).handleCallback with: code = valid code; state = valid link state. 3. Check the response / error and the log. | D68: Error: USER_NOT_FOUND - 404 User not found | E68: - Can connect with server - OAuth state valid in Redis for GOOGLE with linkingUserId - Linking user deleted | F68: Passed | G68: 46300 | H68: Trung | I68: Pending | L68: Pending
A69: 3.2.4 Reset Password
A70: FR3.2.4-01 | B70: [Normal] Reset Password with token = valid 64-hex token, newPassword = NewPass123 | C70: 1. Prepare the state listed in Pre-conditions. 2. Call AuthServiceImpl.resetPassword with: token = valid 64-hex token; newPassword = NewPass123. 3. Check the response / error and the log. | D70: 200 OK - password hash updated | E70: - Can connect with server - Reset token valid in Redis | F70: Passed | G70: 46300 | H70: Trung | I70: Pending | L70: Pending
A71: FR3.2.4-02 | B71: [Normal] Reset Password with token = valid 64-hex token, newPassword = NewPass123 | C71: 1. Prepare the state listed in Pre-conditions. 2. Call AuthServiceImpl.resetPassword with: token = valid 64-hex token; newPassword = NewPass123. 3. Check the response / error and the log. | D71: 200 OK - lastPasswordChange set (old refresh tokens rejected) | E71: - Can connect with server - Reset token valid in Redis | F71: Passed | G71: 46300 | H71: Trung | I71: Pending | L71: Pending
A72: FR3.2.4-03 | B72: [Normal] Reset Password with token = valid 64-hex token, newPassword = NewPass123 | C72: 1. Prepare the state listed in Pre-conditions. 2. Call AuthServiceImpl.resetPassword with: token = valid 64-hex token; newPassword = NewPass123. 3. Check the response / error and the log. | D72: 200 OK - reset token key deleted from Redis | E72: - Can connect with server - Reset token valid in Redis | F72: Passed | G72: 46300 | H72: Trung | I72: Pending | L72: Pending
A73: FR3.2.4-04 | B73: [Normal] Reset Password with token = valid 64-hex token, newPassword = NewPass123 | C73: 1. Prepare the state listed in Pre-conditions. 2. Call AuthServiceImpl.resetPassword with: token = valid 64-hex token; newPassword = NewPass123. 3. Check the response / error and the log. | D73: 200 OK - per-user reset pointer key deleted | E73: - Can connect with server - Reset token valid in Redis | F73: Passed | G73: 46300 | H73: Trung | I73: Pending | L73: Pending
A74: FR3.2.4-05 | B74: [Normal] Reset Password with token = valid 64-hex token, newPassword = NewPass123 | C74: 1. Prepare the state listed in Pre-conditions. 2. Call AuthServiceImpl.resetPassword with: token = valid 64-hex token; newPassword = NewPass123. 3. Check the response / error and the log. | D74: 200 OK - password reset, 2FA setting unchanged | E74: - Can connect with server - Reset token valid in Redis - User has 2FA enabled | F74: Passed | G74: 46300 | H74: Trung | I74: Pending | L74: Pending
A75: FR3.2.4-06 | B75: [Normal] Reset Password with token = valid 64-hex token, newPassword = NewPass123 | C75: 1. Prepare the state listed in Pre-conditions. 2. Call AuthServiceImpl.resetPassword with: token = valid 64-hex token; newPassword = NewPass123. 3. Check the response / error and the log. | D75: 200 OK - password set for the first time | E75: - Can connect with server - Reset token valid in Redis - OAuth-only user (no password) | F75: Passed | G75: 46300 | H75: Trung | I75: Pending | L75: Pending
A76: FR3.2.4-07 | B76: [Normal] Reset Password with token = valid 64-hex token, newPassword = P@ss w0rd!long-pass | C76: 1. Prepare the state listed in Pre-conditions. 2. Call AuthServiceImpl.resetPassword with: token = valid 64-hex token; newPassword = P@ss w0rd!long-pass. 3. Check the response / error and the log. | D76: 200 OK - long password with symbols accepted | E76: - Can connect with server - Reset token valid in Redis | F76: Passed | G76: 46300 | H76: Trung | I76: Pending | L76: Pending
A77: FR3.2.4-08 | B77: [Normal] Reset Password with token = second token, newPassword = NewPass123 | C77: 1. Prepare the state listed in Pre-conditions. 2. Call AuthServiceImpl.resetPassword with: token = second token; newPassword = NewPass123. 3. Check the response / error and the log. | D77: 200 OK - latest token works | E77: - Can connect with server - Reset requested twice (second token valid) | F77: Passed | G77: 46300 | H77: Trung | I77: Pending | L77: Pending
A78: FR3.2.4-09 | B78: [Boundary] Reset Password with token = valid 64-hex token, newPassword = Abcdef12 | C78: 1. Prepare the state listed in Pre-conditions. 2. Call AuthServiceImpl.resetPassword with: token = valid 64-hex token; newPassword = Abcdef12. 3. Check the response / error and the log. | D78: 200 OK - password exactly 8 chars with digit accepted | E78: - Can connect with server - Reset token valid in Redis | F78: Passed | G78: 46300 | H78: Trung | I78: Pending | L78: Pending
A79: FR3.2.4-10 | B79: [Boundary] Reset Password with token = valid 64-hex token, newPassword = Abcdef1 | C79: 1. Prepare the state listed in Pre-conditions. 2. Call AuthServiceImpl.resetPassword with: token = valid 64-hex token; newPassword = Abcdef1. 3. Check the response / error and the log. | D79: Error: VALIDATION_ERROR - Password must be at least 8 characters (7 chars) | E79: - Can connect with server - Reset token valid in Redis | F79: Passed | G79: 46300 | H79: Trung | I79: Pending | L79: Pending
A80: FR3.2.4-11 | B80: [Abnormal] Reset Password with token = unknown token, newPassword = NewPass123 | C80: 1. Prepare the state listed in Pre-conditions. 2. Call AuthServiceImpl.resetPassword with: token = unknown token; newPassword = NewPass123. 3. Check the response / error and the log. | D80: Error: RESET_TOKEN_INVALID - 400 Password reset token is invalid or has expired | E80: - Can connect with server - Token not in Redis | F80: Passed | G80: 46300 | H80: Trung | I80: Pending | L80: Pending
A81: FR3.2.4-12 | B81: [Abnormal] Reset Password with token = expired token, newPassword = NewPass123 | C81: 1. Prepare the state listed in Pre-conditions. 2. Call AuthServiceImpl.resetPassword with: token = expired token; newPassword = NewPass123. 3. Check the response / error and the log. | D81: Error: RESET_TOKEN_INVALID - 400 Password reset token is invalid or has expired | E81: - Can connect with server - Token TTL expired | F81: Passed | G81: 46300 | H81: Trung | I81: Pending | L81: Pending
... A87: FR3.2.4-18 | B87: [Abnormal] Reset Password with token = empty, newPassword = NewPass123 | C87: 1. Prepare the state listed in Pre-conditions. 2. Call AuthServiceImpl.resetPassword with: token = empty; newPassword = NewPass123. 3. Check the response / error and the log. | D87: Error: VALIDATION_ERROR - token must not be blank | E87: - Can connect with server | F87: Passed | G87: 46300 | H87: Trung | I87: Pending | L87: Pending
A88: 3.2.5 Change Password
A89: FR3.2.5-01 | B89: [Normal] Change Password with accessToken = valid JWT, currentPassword = OldPass123, newPassword = NewPass456 | C89: 1. Prepare the state listed in Pre-conditions. 2. Call AuthServiceImpl.changePassword with: accessToken = valid JWT; currentPassword = OldPass123; newPassword = NewPass456. 3. Check the response / error and the log. | D89: 200 OK - password hash updated | E89: - Can connect with server - User has password hash | F89: Passed | G89: 46300 | H89: Trung | I89: Pending | L89: Pending
A90: FR3.2.5-02 | B90: [Normal] Change Password with accessToken = valid JWT, currentPassword = OldPass123, newPassword = NewPass456 | C90: 1. Prepare the state listed in Pre-conditions. 2. Call AuthServiceImpl.changePassword with: accessToken = valid JWT; currentPassword = OldPass123; newPassword = NewPass456. 3. Check the response / error and the log. | D90: 200 OK - lastPasswordChange set, older refresh tokens invalid | E90: - Can connect with server - User has password hash | F90: Passed | G90: 46300 | H90: Trung | I90: Pending | L90: Pending
A91: FR3.2.5-03 | B91: [Normal] Change Password with accessToken = valid JWT, currentPassword = OldPass123, newPassword = NewPass456 | C91: 1. Prepare the state listed in Pre-conditions. 2. Call AuthServiceImpl.changePassword with: accessToken = valid JWT; currentPassword = OldPass123; newPassword = NewPass456. 3. Check the response / error and the log. | D91: 200 OK - new hash is bcrypt, differs from old hash | E91: - Can connect with server - User has password hash | F91: Passed | G91: 46300 | H91: Trung | I91: Pending | L91: Pending
A92: FR3.2.5-04 | B92: [Normal] Change Password with accessToken = valid JWT, currentPassword = OldPass123, newPassword = NewPass456 | C92: 1. Prepare the state listed in Pre-conditions. 2. Call AuthServiceImpl.changePassword with: accessToken = valid JWT; currentPassword = OldPass123; newPassword = NewPass456. 3. Check the response / error and the log. | D92: 200 OK - password changed, 2FA unchanged | E92: - Can connect with server - User has password hash - User has 2FA enabled | F92: Passed | G92: 46300 | H92: Trung | I92: Pending | L92: Pending
A93: FR3.2.5-05 | B93: [Normal] Change Password with accessToken = valid JWT, currentPassword = OldPass123, newPassword = Brand#Hub2026long | C93: 1. Prepare the state listed in Pre-conditions. 2. Call AuthServiceImpl.changePassword with: accessToken = valid JWT; currentPassword = OldPass123; newPassword = Brand#Hub2026long. 3. Check the response / error and the log. | D93: 200 OK - long password with symbols accepted | E93: - Can connect with server - User has password hash | F93: Passed | G93: 46300 | H93: Trung | I93: Pending | L93: Pending
A94: FR3.2.5-06 | B94: [Normal] Change Password with accessToken = valid JWT, currentPassword = OldPass123, newPassword = oldpass123 | C94: 1. Prepare the state listed in Pre-conditions. 2. Call AuthServiceImpl.changePassword with: accessToken = valid JWT; currentPassword = OldPass123; newPassword = oldpass123. 3. Check the response / error and the log. | D94: 200 OK - differs by case so treated as different | E94: - Can connect with server - User has password hash | F94: Passed | G94: 46300 | H94: Trung | I94: Pending | L94: Pending
A95: FR3.2.5-07 | B95: [Normal] Change Password with accessToken = valid JWT, currentPassword = OldPass123, newPassword = OldPass124 | C95: 1. Prepare the state listed in Pre-conditions. 2. Call AuthServiceImpl.changePassword with: accessToken = valid JWT; currentPassword = OldPass123; newPassword = OldPass124. 3. Check the response / error and the log. | D95: 200 OK - differs by one char accepted | E95: - Can connect with server - User has password hash | F95: Passed | G95: 46300 | H95: Trung | I95: Pending | L95: Pending
A96: FR3.2.5-08 | B96: [Normal] Change Password with accessToken = valid JWT, currentPassword = OldPass123, newPassword = NewPass456 | C96: 1. Prepare the state listed in Pre-conditions. 2. Call AuthServiceImpl.changePassword with: accessToken = valid JWT; currentPassword = OldPass123; newPassword = NewPass456. 3. Check the response / error and the log. | D96: 200 OK - password saved via applyPassword with new timestamp | E96: - Can connect with server - User has password hash | F96: Passed | G96: 46300 | H96: Trung | I96: Pending | L96: Pending
A97: FR3.2.5-09 | B97: [Boundary] Change Password with accessToken = valid JWT, currentPassword = OldPass123, newPassword = Abcdef12 | C97: 1. Prepare the state listed in Pre-conditions. 2. Call AuthServiceImpl.changePassword with: accessToken = valid JWT; currentPassword = OldPass123; newPassword = Abcdef12. 3. Check the response / error and the log. | D97: 200 OK - new password exactly 8 chars accepted | E97: - Can connect with server - User has password hash | F97: Passed | G97: 46300 | H97: Trung | I97: Pending | L97: Pending
A98: FR3.2.5-10 | B98: [Boundary] Change Password with accessToken = valid JWT, currentPassword = OldPass123, newPassword = Abcdef1 | C98: 1. Prepare the state listed in Pre-conditions. 2. Call AuthServiceImpl.changePassword with: accessToken = valid JWT; currentPassword = OldPass123; newPassword = Abcdef1. 3. Check the response / error and the log. | D98: Error: VALIDATION_ERROR - Password must be at least 8 characters (7 chars) | E98: - Can connect with server - User has password hash | F98: Passed | G98: 46300 | H98: Trung | I98: Pending | L98: Pending
A99: FR3.2.5-11 | B99: [Abnormal] Change Password with accessToken = valid JWT, currentPassword = WrongPass9, newPassword = NewPass456 | C99: 1. Prepare the state listed in Pre-conditions. 2. Call AuthServiceImpl.changePassword with: accessToken = valid JWT; currentPassword = WrongPass9; newPassword = NewPass456. 3. Check the response / error and the log. | D99: Error: WRONG_CURRENT_PASSWORD - 400 Current password is incorrect | E99: - Can connect with server - User has password hash | F99: Passed | G99: 46300 | H99: Trung | I99: Pending | L99: Pending
A100: FR3.2.5-12 | B100: [Abnormal] Change Password with accessToken = valid JWT, currentPassword = OldPass123, newPassword = OldPass123 | C100: 1. Prepare the state listed in Pre-conditions. 2. Call AuthServiceImpl.changePassword with: accessToken = valid JWT; currentPassword = OldPass123; newPassword = OldPass123. 3. Check the response / error and the log. | D100: Error: SAME_AS_CURRENT_PASSWORD - 400 New password must be different from current password | E100: - Can connect with server - User has password hash | F100: Passed | G100: 46300 | H100: Trung | I100: Pending | L100: Pending
... A105: FR3.2.5-17 | B105: [Abnormal] Change Password with accessToken = expired/invalid JWT, currentPassword = OldPass123, newPassword = NewPass456 | C105: 1. Prepare the state listed in Pre-conditions. 2. Call AuthServiceImpl.changePassword with: accessToken = expired/invalid JWT; currentPassword = OldPass123; newPassword = NewPass456. 3. Check the response / error and the log. | D105: Error: JwtException - token parse fails, 401 TOKEN_INVALID | E105: - Can connect with server | F105: Passed | G105: 46300 | H105: Trung | I105: Pending | L105: Pending
A106: 3.2.6 OTP Verification
A107: FR3.2.6-01 | B107: [Normal] OTP Verification with email = user@brandhub.vn, otpCode = 123456 | C107: 1. Prepare the state listed in Pre-conditions. 2. Call AuthServiceImpl.verifyOtp with: email = user@brandhub.vn; otpCode = 123456. 3. Check the response / error and the log. | D107: 200 OK - emailVerifiedAt set, otpCode/otpExpiry cleared | E107: - Can connect with server - User registered, email not verified, OTP valid | F107: Passed | G107: 46300 | H107: Trung | I107: Pending | L107: Pending
A108: FR3.2.6-02 | B108: [Normal] OTP Verification with email = USER@BrandHub.VN , otpCode = 123456 | C108: 1. Prepare the state listed in Pre-conditions. 2. Call AuthServiceImpl.verifyOtp with: email = USER@BrandHub.VN ; otpCode = 123456. 3. Check the response / error and the log. | D108: 200 OK - email normalized then verified | E108: - Can connect with server - User registered, email not verified, OTP valid | F108: Passed | G108: 46300 | H108: Trung | I108: Pending | L108: Pending
A109: FR3.2.6-03 | B109: [Normal] OTP Verification with email = user@brandhub.vn, otpCode = 123456 | C109: 1. Prepare the state listed in Pre-conditions. 2. Call AuthServiceImpl.verifyOtp with: email = user@brandhub.vn; otpCode = 123456. 3. Check the response / error and the log. | D109: 200 OK - attempt counter deleted from Redis | E109: - Can connect with server - User registered, email not verified, OTP valid | F109: Passed | G109: 46300 | H109: Trung | I109: Pending | L109: Pending
A110: FR3.2.6-04 | B110: [Normal] OTP Verification with email = user@brandhub.vn, otpCode = 123456 | C110: 1. Prepare the state listed in Pre-conditions. 2. Call AuthServiceImpl.verifyOtp with: email = user@brandhub.vn; otpCode = 123456. 3. Check the response / error and the log. | D110: 200 OK - user NOT auto logged in (no tokens) | E110: - Can connect with server - User registered, email not verified, OTP valid | F110: Passed | G110: 46300 | H110: Trung | I110: Pending | L110: Pending
A111: FR3.2.6-05 | B111: [Normal] OTP Verification with email = user@brandhub.vn, otpCode = 000000 | C111: 1. Prepare the state listed in Pre-conditions. 2. Call AuthServiceImpl.verifyOtp with: email = user@brandhub.vn; otpCode = 000000. 3. Check the response / error and the log. | D111: 200 OK - idempotent no-op, no error | E111: - Can connect with server - Email already verified | F111: Passed | G111: 46300 | H111: Trung | I111: Pending | L111: Pending
A112: FR3.2.6-06 | B112: [Normal] OTP Verification with email = user@brandhub.vn, otpCode = 123456 | C112: 1. Prepare the state listed in Pre-conditions. 2. Call AuthServiceImpl.verifyOtp with: email = user@brandhub.vn; otpCode = 123456. 3. Check the response / error and the log. | D112: 200 OK - correct code after a failure still verifies | E112: - Can connect with server - User registered, email not verified, OTP valid - 1 wrong attempt already | F112: Passed | G112: 46300 | H112: Trung | I112: Pending | L112: Pending
A113: FR3.2.6-07 | B113: [Normal] OTP Verification with email = user@brandhub.vn | C113: 1. Prepare the state listed in Pre-conditions. 2. Call AuthServiceImpl.verifyOtp with: email = user@brandhub.vn. 3. Check the response / error and the log. | D113: 200 OK - resendOtp issues new OTP (10 min) and 60s cooldown Log: OTP email sent | E113: - Can connect with server - Email not verified, no cooldown in Redis | F113: Passed | G113: 46300 | H113: Trung | I113: Pending | L113: Pending
A114: FR3.2.6-08 | B114: [Normal] OTP Verification with email = user@brandhub.vn | C114: 1. Prepare the state listed in Pre-conditions. 2. Call AuthServiceImpl.verifyOtp with: email = user@brandhub.vn. 3. Check the response / error and the log. | D114: 200 OK - resendOtp no-op, no email sent | E114: - Can connect with server - Email already verified | F114: Passed | G114: 46300 | H114: Trung | I114: Pending | L114: Pending
A115: FR3.2.6-09 | B115: [Boundary] OTP Verification with email = user@brandhub.vn, otpCode = 123456 | C115: 1. Prepare the state listed in Pre-conditions. 2. Call AuthServiceImpl.verifyOtp with: email = user@brandhub.vn; otpCode = 123456. 3. Check the response / error and the log. | D115: 200 OK - verified just before expiry | E115: - Can connect with server - User registered, email not verified, OTP valid - OTP expires in 1 second | F115: Passed | G115: 46300 | H115: Trung | I115: Pending | L115: Pending
A116: FR3.2.6-10 | B116: [Boundary] OTP Verification with email = user@brandhub.vn, otpCode = 123456 | C116: 1. Prepare the state listed in Pre-conditions. 2. Call AuthServiceImpl.verifyOtp with: email = user@brandhub.vn; otpCode = 123456. 3. Check the response / error and the log. | D116: Error: OTP_INVALID - 400 Verification code is invalid or has expired | E116: - Can connect with server - User registered, email not verified, OTP valid - OTP expired 1 second ago | F116: Passed | G116: 46300 | H116: Trung | I116: Pending | L116: Pending
A117: FR3.2.6-11 | B117: [Boundary] OTP Verification with email = user@brandhub.vn, otpCode = 111111 | C117: 1. Prepare the state listed in Pre-conditions. 2. Call AuthServiceImpl.verifyOtp with: email = user@brandhub.vn; otpCode = 111111. 3. Check the response / error and the log. | D117: Error: OTP_TOO_MANY_ATTEMPTS - 5th wrong attempt clears OTP, 400 | E117: - Can connect with server - User registered, email not verified, OTP valid - 4 failed attempts already | F117: Passed | G117: 46300 | H117: Trung | I117: Pending | L117: Pending
A118: FR3.2.6-12 | B118: [Boundary] OTP Verification with email = user@brandhub.vn, otpCode = 111111 | C118: 1. Prepare the state listed in Pre-conditions. 2. Call AuthServiceImpl.verifyOtp with: email = user@brandhub.vn; otpCode = 111111. 3. Check the response / error and the log. | D118: Error: OTP_INVALID - first wrong attempt, counter=1 with 10 min TTL | E118: - Can connect with server - User registered, email not verified, OTP valid - 0 failed attempts | F118: Passed | G118: 46300 | H118: Trung | I118: Pending | L118: Pending
... A124: FR3.2.6-18 | B124: [Abnormal] OTP Verification with email = ghost@brandhub.vn | C124: 1. Prepare the state listed in Pre-conditions. 2. Call AuthServiceImpl.verifyOtp with: email = ghost@brandhub.vn. 3. Check the response / error and the log. | D124: Error: USER_NOT_FOUND - 404 resendOtp for unknown email | E124: - Can connect with server - Email not registered | F124: Passed | G124: 46300 | H124: Trung | I124: Pending | L124: Pending
A125: 3.2.7 Two-Factor Authentication (TOTP)
A126: FR3.2.7-01 | B126: [Normal] Two-Factor Authentication (TOTP) with twoFactorToken = valid 2fa token, code = valid TOTP | C126: 1. Prepare the state listed in Pre-conditions. 2. Call AuthServiceImpl.verifyTwoFactor with: twoFactorToken = valid 2fa token; code = valid TOTP. 3. Check the response / error and the log. | D126: 200 OK - LoginResult with access + refresh token Log: Audit LOGIN saved | E126: - Can connect with server - User has 2FA enabled with TOTP secret | F126: Passed | G126: 46300 | H126: Trung | I126: Pending | L126: Pending
A127: FR3.2.7-02 | B127: [Normal] Two-Factor Authentication (TOTP) with twoFactorToken = valid 2fa token, code = valid TOTP | C127: 1. Prepare the state listed in Pre-conditions. 2. Call AuthServiceImpl.verifyTwoFactor with: twoFactorToken = valid 2fa token; code = valid TOTP. 3. Check the response / error and the log. | D127: 200 OK - lastLoginAt updated, attempt counter cleared | E127: - Can connect with server - User has 2FA enabled with TOTP secret | F127: Passed | G127: 46300 | H127: Trung | I127: Pending | L127: Pending
A128: FR3.2.7-03 | B128: [Normal] Two-Factor Authentication (TOTP) with twoFactorToken = valid 2fa token, code = valid TOTP | C128: 1. Prepare the state listed in Pre-conditions. 2. Call AuthServiceImpl.verifyTwoFactor with: twoFactorToken = valid 2fa token; code = valid TOTP. 3. Check the response / error and the log. | D128: 200 OK - access token role=ADMIN | E128: - Can connect with server - User has 2FA enabled with TOTP secret - User role ADMIN | F128: Passed | G128: 46300 | H128: Trung | I128: Pending | L128: Pending
A129: FR3.2.7-04 | B129: [Normal] Two-Factor Authentication (TOTP) with twoFactorToken = valid 2fa token, code = valid TOTP | C129: 1. Prepare the state listed in Pre-conditions. 2. Call AuthServiceImpl.verifyTwoFactor with: twoFactorToken = valid 2fa token; code = valid TOTP. 3. Check the response / error and the log. | D129: 200 OK - access token has workspaceId | E129: - Can connect with server - User has 2FA enabled with TOTP secret - User has active workspace | F129: Passed | G129: 46300 | H129: Trung | I129: Pending | L129: Pending
A130: FR3.2.7-05 | B130: [Normal] Two-Factor Authentication (TOTP) with userId = authenticated, code = valid TOTP | C130: 1. Prepare the state listed in Pre-conditions. 2. Call AuthServiceImpl.verifyTwoFactor with: userId = authenticated; code = valid TOTP. 3. Check the response / error and the log. | D130: 200 OK - confirmTwoFactor enables 2FA, secret saved, setup key deleted | E130: - Can connect with server - 2FA not enabled, setup secret in Redis | F130: Passed | G130: 46300 | H130: Trung | I130: Pending | L130: Pending
A131: FR3.2.7-06 | B131: [Normal] Two-Factor Authentication (TOTP) with userId = authenticated | C131: 1. Prepare the state listed in Pre-conditions. 2. Call AuthServiceImpl.verifyTwoFactor with: userId = authenticated. 3. Check the response / error and the log. | D131: 200 OK - setupTwoFactor returns otpauth URL, secret cached 10 min | E131: - Can connect with server - 2FA not enabled | F131: Passed | G131: 46300 | H131: Trung | I131: Pending | L131: Pending
A132: FR3.2.7-07 | B132: [Normal] Two-Factor Authentication (TOTP) with userId = authenticated, code = valid TOTP | C132: 1. Prepare the state listed in Pre-conditions. 2. Call AuthServiceImpl.verifyTwoFactor with: userId = authenticated; code = valid TOTP. 3. Check the response / error and the log. | D132: 200 OK - disableTwoFactor clears totpSecret and flag | E132: - Can connect with server - User has 2FA enabled with TOTP secret | F132: Passed | G132: 46300 | H132: Trung | I132: Pending | L132: Pending
...

Sheet Profile
A2: Feature | B2: Profile | R2: Passed
A3: Test requirement | B3: Functional test of 3.3.1 View User Profile; 3.3.2 Update Profile; 3.3.3 View Client Profile; 3.3.4 Update Client Profile | R3: Failed
A4: Number of TCs | B4: =COUNTA(F12:F1000) -> 71 | R4: Pending
A5: Testing Round | B5: Passed | C5: Failed | D5: Pending | E5: N/A | R5: N/A
A6: Round 1 | B6: =COUNTIF($F$10:$F$998,B$5) -> 71 | C6: =COUNTIF($F$10:$F$998,C$5) -> 0 | D6: =COUNTIF($F$10:$F$998,D$5) -> 0 | E6: =COUNTIF($F$10:$F$998,E$5) -> 0
A7: Round 2 | B7: =COUNTIF($I$10:$I$998,B$5) -> 0 | C7: =COUNTIF($I$10:$I$998,C$5) -> 0 | D7: =COUNTIF($I$10:$I$998,D$5) -> 71 | E7: =COUNTIF($I$10:$I$998,E$5) -> 0
A8: Round 3 | B8: =COUNTIF($L$10:$L$998,B$5) -> 0 | C8: =COUNTIF($L$10:$L$998,C$5) -> 0 | D8: =COUNTIF($L$10:$L$998,D$5) -> 71 | E8: =COUNTIF($L$10:$L$998,E$5) -> 0
A10: Test Case ID | B10: Test Case Description | C10: Test Case Procedure | D10: Expected Results | E10: Pre-conditions | F10: Round 1 | G10: Test date | H10: Tester | I10: Round 2 | J10: Test date | K10: Tester | L10: Round 3 | M10: Test date | N10: Tester | O10: Note
A11: 3.3.1 View User Profile
A12: FR3.3.1-01 | B12: [Normal] View User Profile with currentUser = valid user id | C12: 1. Prepare the state listed in Pre-conditions. 2. Call UserServiceImpl.getUserProfile with: currentUser = valid user id. 3. Check the response / error and the log. | D12: 200 OK - UserProfileResponse with fullName, email, phone | E12: - Can connect with server - User exists | F12: Passed | G12: 46300 | H12: Trung | I12: Pending | L12: Pending
A13: FR3.3.1-02 | B13: [Normal] View User Profile with currentUser = valid user id | C13: 1. Prepare the state listed in Pre-conditions. 2. Call UserServiceImpl.getUserProfile with: currentUser = valid user id. 3. Check the response / error and the log. | D13: 200 OK - timezone read from preferences | E13: - Can connect with server - User exists - Preferences JSON contains timezone | F13: Passed | G13: 46300 | H13: Trung | I13: Pending | L13: Pending
A14: FR3.3.1-03 | B14: [Normal] View User Profile with currentUser = valid user id | C14: 1. Prepare the state listed in Pre-conditions. 2. Call UserServiceImpl.getUserProfile with: currentUser = valid user id. 3. Check the response / error and the log. | D14: 200 OK - notificationPreferences map returned | E14: - Can connect with server - User exists - Preferences JSON contains notificationPreferences | F14: Passed | G14: 46300 | H14: Trung | I14: Pending | L14: Pending
A15: FR3.3.1-04 | B15: [Normal] View User Profile with currentUser = valid user id | C15: 1. Prepare the state listed in Pre-conditions. 2. Call UserServiceImpl.getUserProfile with: currentUser = valid user id. 3. Check the response / error and the log. | D15: 200 OK - skills and portfolioUrls parsed to lists | E15: - Can connect with server - User exists - Skills and portfolioUrls stored as JSON | F15: Passed | G15: 46300 | H15: Trung | I15: Pending | L15: Pending
A16: FR3.3.1-05 | B16: [Normal] View User Profile with currentUser = valid user id | C16: 1. Prepare the state listed in Pre-conditions. 2. Call UserServiceImpl.getUserProfile with: currentUser = valid user id. 3. Check the response / error and the log. | D16: 200 OK - avatarUrl and bannerUrl returned | E16: - Can connect with server - User exists - Avatar and banner uploaded | F16: Passed | G16: 46300 | H16: Trung | I16: Pending | L16: Pending
A17: FR3.3.1-06 | B17: [Normal] View User Profile with currentUser = valid user id | C17: 1. Prepare the state listed in Pre-conditions. 2. Call UserServiceImpl.getUserProfile with: currentUser = valid user id. 3. Check the response / error and the log. | D17: 200 OK - role included in response | E17: - Can connect with server - User exists - User has system role ADMIN | F17: Passed | G17: 46300 | H17: Trung | I17: Pending | L17: Pending
A18: FR3.3.1-07 | B18: [Normal] View User Profile with currentUser = valid user id | C18: 1. Prepare the state listed in Pre-conditions. 2. Call UserServiceImpl.getUserProfile with: currentUser = valid user id. 3. Check the response / error and the log. | D18: 200 OK - workspace role/permissions included | E18: - Can connect with server - User exists - User in workspace as MANAGER | F18: Passed | G18: 46300 | H18: Trung | I18: Pending | L18: Pending
A19: FR3.3.1-08 | B19: [Normal] View User Profile with currentUser = valid user id | C19: 1. Prepare the state listed in Pre-conditions. 2. Call UserServiceImpl.getUserProfile with: currentUser = valid user id. 3. Check the response / error and the log. | D19: 200 OK - linkedin/facebook/instagram/tiktok URLs returned | E19: - Can connect with server - User exists - Social URLs set | F19: Passed | G19: 46300 | H19: Trung | I19: Pending | L19: Pending
A20: FR3.3.1-09 | B20: [Normal] View User Profile with currentUser = valid user id | C20: 1. Prepare the state listed in Pre-conditions. 2. Call UserServiceImpl.getUserProfile with: currentUser = valid user id. 3. Check the response / error and the log. | D20: 200 OK - response has no passwordHash or totpSecret | E20: - Can connect with server - User exists | F20: Passed | G20: 46300 | H20: Trung | I20: Pending | L20: Pending
A21: FR3.3.1-10 | B21: [Boundary] View User Profile with currentUser = valid user id | C21: 1. Prepare the state listed in Pre-conditions. 2. Call UserServiceImpl.getUserProfile with: currentUser = valid user id. 3. Check the response / error and the log. | D21: 200 OK - default empty preferences, no error | E21: - Can connect with server - User exists - Preferences is null | F21: Passed | G21: 46300 | H21: Trung | I21: Pending | L21: Pending
A22: FR3.3.1-11 | B22: [Boundary] View User Profile with currentUser = valid user id | C22: 1. Prepare the state listed in Pre-conditions. 2. Call UserServiceImpl.getUserProfile with: currentUser = valid user id. 3. Check the response / error and the log. | D22: 200 OK - skills returns empty list | E22: - Can connect with server - User exists - Skills JSON is null/empty | F22: Passed | G22: 46300 | H22: Trung | I22: Pending | L22: Pending
A23: FR3.3.1-12 | B23: [Boundary] View User Profile with currentUser = valid user id | C23: 1. Prepare the state listed in Pre-conditions. 2. Call UserServiceImpl.getUserProfile with: currentUser = valid user id. 3. Check the response / error and the log. | D23: 200 OK - parseStringList falls back to empty list | E23: - Can connect with server - User exists - Skills JSON malformed | F23: Passed | G23: 46300 | H23: Trung | I23: Pending | L23: Pending
... A27: FR3.3.1-16 | B27: [Abnormal] View User Profile with currentUser = expired token | C27: 1. Prepare the state listed in Pre-conditions. 2. Call UserServiceImpl.getUserProfile with: currentUser = expired token. 3. Check the response / error and the log. | D27: Error: TOKEN_EXPIRED - 401 Authentication token has expired | E27: - Can connect with server - Access token expired | F27: Passed | G27: 46300 | H27: Trung | I27: Pending | L27: Pending
A28: 3.3.2 Update Profile
A29: FR3.3.2-01 | B29: [Normal] Update Profile with currentUser = valid user id, fullName = Nguyen Van B, phone = 0901234567 | C29: 1. Prepare the state listed in Pre-conditions. 2. Call UserServiceImpl.updateUserProfile with: currentUser = valid user id; fullName = Nguyen Van B; phone = 0901234567. 3. Check the response / error and the log. | D29: 200 OK - fullName and phone updated, other preferences kept | E29: - Can connect with server - User exists | F29: Passed | G29: 46300 | H29: Trung | I29: Pending | L29: Pending
A30: FR3.3.2-02 | B30: [Normal] Update Profile with currentUser = valid user id, fullName = Nguyen Van B, timezone = Asia/Ho_Chi_Minh | C30: 1. Prepare the state listed in Pre-conditions. 2. Call UserServiceImpl.updateUserProfile with: currentUser = valid user id; fullName = Nguyen Van B; timezone = Asia/Ho_Chi_Minh. 3. Check the response / error and the log. | D30: 200 OK - timezone merged, notificationPreferences preserved | E30: - Can connect with server - User exists - Existing notificationPreferences | F30: Passed | G30: 46300 | H30: Trung | I30: Pending | L30: Pending
A31: FR3.3.2-03 | B31: [Normal] Update Profile with currentUser = valid user id, fullName = Nguyen Van B, notificationPreferences = {email:true} | C31: 1. Prepare the state listed in Pre-conditions. 2. Call UserServiceImpl.updateUserProfile with: currentUser = valid user id; fullName = Nguyen Van B; notificationPreferences = {email:true}. 3. Check the response / error and the log. | D31: 200 OK - notificationPreferences replaced, timezone preserved | E31: - Can connect with server - User exists | F31: Passed | G31: 46300 | H31: Trung | I31: Pending | L31: Pending
A32: FR3.3.2-04 | B32: [Normal] Update Profile with currentUser = valid user id, fullName = Nguyen Van B | C32: 1. Prepare the state listed in Pre-conditions. 2. Call UserServiceImpl.updateUserProfile with: currentUser = valid user id; fullName = Nguyen Van B . 3. Check the response / error and the log. | D32: 200 OK - fullName stored trimmed | E32: - Can connect with server - User exists | F32: Passed | G32: 46300 | H32: Trung | I32: Pending | L32: Pending
A33: FR3.3.2-05 | B33: [Normal] Update Profile with currentUser = valid user id, fullName = Nguyen Van B, phone = null | C33: 1. Prepare the state listed in Pre-conditions. 2. Call UserServiceImpl.updateUserProfile with: currentUser = valid user id; fullName = Nguyen Van B; phone = null. 3. Check the response / error and the log. | D33: 200 OK - null phone leaves old phone unchanged | E33: - Can connect with server - User exists - Existing phone | F33: Passed | G33: 46300 | H33: Trung | I33: Pending | L33: Pending
A34: FR3.3.2-06 | B34: [Normal] Update Profile with currentUser = valid user id, fullName = Nguyen Van B, skills = [Design, Copywriting] | C34: 1. Prepare the state listed in Pre-conditions. 2. Call UserServiceImpl.updateUserProfile with: currentUser = valid user id; fullName = Nguyen Van B; skills = [Design, Copywriting]; portfolioUrls = [https://a.com]. 3. Check the response / error and the log. | D34: 200 OK - skills and portfolioUrls saved as JSON | E34: - Can connect with server - User exists | F34: Passed | G34: 46300 | H34: Trung | I34: Pending | L34: Pending
A35: FR3.3.2-07 | B35: [Normal] Update Profile with currentUser = valid user id, fullName = Nguyen Van B, professionalTitle = Content Lead | C35: 1. Prepare the state listed in Pre-conditions. 2. Call UserServiceImpl.updateUserProfile with: currentUser = valid user id; fullName = Nguyen Van B; professionalTitle = Content Lead; bio = 10 years in media. 3. Check the response / error and the log. | D35: 200 OK - title and bio saved | E35: - Can connect with server - User exists | F35: Passed | G35: 46300 | H35: Trung | I35: Pending | L35: Pending
A36: FR3.3.2-08 | B36: [Normal] Update Profile with currentUser = valid user id, fullName = Nguyen Van B, linkedinUrl = https://linkedin.com/in/b | C36: 1. Prepare the state listed in Pre-conditions. 2. Call UserServiceImpl.updateUserProfile with: currentUser = valid user id; fullName = Nguyen Van B; linkedinUrl = https://linkedin.com/in/b; website = https://b.vn. 3. Check the response / error and the log. | D36: 200 OK - social URLs and website saved | E36: - Can connect with server - User exists | F36: Passed | G36: 46300 | H36: Trung | I36: Pending | L36: Pending
A37: FR3.3.2-09 | B37: [Normal] Update Profile with currentUser = valid user id, fullName = Nguyen Van B, profileVisibility = PUBLIC | C37: 1. Prepare the state listed in Pre-conditions. 2. Call UserServiceImpl.updateUserProfile with: currentUser = valid user id; fullName = Nguyen Van B; profileVisibility = PUBLIC. 3. Check the response / error and the log. | D37: 200 OK - profileVisibility stored in preferences | E37: - Can connect with server - User exists | F37: Passed | G37: 46300 | H37: Trung | I37: Pending | L37: Pending
A38: FR3.3.2-10 | B38: [Normal] Update Profile with currentUser = valid user id, fullName = Nguyen Van B, location = Ha Noi | C38: 1. Prepare the state listed in Pre-conditions. 2. Call UserServiceImpl.updateUserProfile with: currentUser = valid user id; fullName = Nguyen Van B; location = Ha Noi; workingLanguage = vi; yearsOfExperience = 5. 3. Check the response / error and the log. | D38: 200 OK - location, language, experience saved | E38: - Can connect with server - User exists | F38: Passed | G38: 46300 | H38: Trung | I38: Pending | L38: Pending
A39: FR3.3.2-11 | B39: [Normal] Update Profile with currentUser = valid user id, fullName = Nguyen Van B | C39: 1. Prepare the state listed in Pre-conditions. 2. Call UserServiceImpl.updateUserProfile with: currentUser = valid user id; fullName = Nguyen Van B. 3. Check the response / error and the log. | D39: 200 OK - email not in request, email unchanged | E39: - Can connect with server - User exists | F39: Passed | G39: 46300 | H39: Trung | I39: Pending | L39: Pending
A40: FR3.3.2-12 | B40: [Boundary] Update Profile with currentUser = valid user id, fullName = N | C40: 1. Prepare the state listed in Pre-conditions. 2. Call UserServiceImpl.updateUserProfile with: currentUser = valid user id; fullName = N. 3. Check the response / error and the log. | D40: 200 OK - fullName 1 char accepted | E40: - Can connect with server - User exists | F40: Passed | G40: 46300 | H40: Trung | I40: Pending | L40: Pending
... A48: FR3.3.2-20 | B48: [Abnormal] Update Profile with currentUser = valid user id, fullName = Nguyen Van B, timezone = UTC | C48: 1. Prepare the state listed in Pre-conditions. 2. Call UserServiceImpl.updateUserProfile with: currentUser = valid user id; fullName = Nguyen Van B; timezone = UTC. 3. Check the response / error and the log. | D48: Error: INVALID_REQUEST - 400 Invalid request format or parameters | E48: - Can connect with server - User exists - Preferences serialization fails | F48: Passed | G48: 46300 | H48: Trung | I48: Pending | L48: Pending
A49: 3.3.3 View Client Profile
A50: FR3.3.3-01 | B50: [Normal] View Client Profile with currentUser = valid user id | C50: 1. Prepare the state listed in Pre-conditions. 2. Call ClientProfileServiceImpl.listMine with: currentUser = valid user id. 3. Check the response / error and the log. | D50: 200 OK - list with 1 ClientProfileResponse | E50: - Can connect with server - User owns 1 client profile | F50: Passed | G50: 46300 | H50: Trung | I50: Pending | L50: Pending
A51: FR3.3.3-02 | B51: [Normal] View Client Profile with currentUser = valid user id | C51: 1. Prepare the state listed in Pre-conditions. 2. Call ClientProfileServiceImpl.listMine with: currentUser = valid user id. 3. Check the response / error and the log. | D51: 200 OK - list with both profiles, no data mixed | E51: - Can connect with server - User owns 2 client profiles (Nike, Adidas) | F51: Passed | G51: 46300 | H51: Trung | I51: Pending | L51: Pending
A52: FR3.3.3-03 | B52: [Normal] View Client Profile with currentUser = valid user id | C52: 1. Prepare the state listed in Pre-conditions. 2. Call ClientProfileServiceImpl.listMine with: currentUser = valid user id. 3. Check the response / error and the log. | D52: 200 OK - response has no agencyId and no email | E52: - Can connect with server - User owns profiles | F52: Passed | G52: 46300 | H52: Trung | I52: Pending | L52: Pending
A53: FR3.3.3-04 | B53: [Normal] View Client Profile with currentUser = valid user id | C53: 1. Prepare the state listed in Pre-conditions. 2. Call ClientProfileServiceImpl.listMine with: currentUser = valid user id. 3. Check the response / error and the log. | D53: 200 OK - socialLinks parsed to map | E53: - Can connect with server - Profile has socialLinks JSON | F53: Passed | G53: 46300 | H53: Trung | I53: Pending | L53: Pending
A54: FR3.3.3-05 | B54: [Normal] View Client Profile with currentUser = valid user id | C54: 1. Prepare the state listed in Pre-conditions. 2. Call ClientProfileServiceImpl.listMine with: currentUser = valid user id. 3. Check the response / error and the log. | D54: 200 OK - tagline, foundedYear, budgetRange, taxCode returned | E54: - Can connect with server - Profile has brand fields set | F54: Passed | G54: 46300 | H54: Trung | I54: Pending | L54: Pending
A55: FR3.3.3-06 | B55: [Normal] View Client Profile with currentUser = valid user id | C55: 1. Prepare the state listed in Pre-conditions. 2. Call ClientProfileServiceImpl.listMine with: currentUser = valid user id. 3. Check the response / error and the log. | D55: 200 OK - only caller's profiles returned | E55: - Can connect with server - Other users also have profiles | F55: Passed | G55: 46300 | H55: Trung | I55: Pending | L55: Pending
A56: FR3.3.3-07 | B56: [Normal] View Client Profile with currentUser = valid user id, profileId = own profile id | C56: 1. Prepare the state listed in Pre-conditions. 2. Call ClientProfileServiceImpl.listMine with: currentUser = valid user id; profileId = own profile id. 3. Check the response / error and the log. | D56: 200 OK - getById returns the profile | E56: - Can connect with server - User owns profile | F56: Passed | G56: 46300 | H56: Trung | I56: Pending | L56: Pending
A57: FR3.3.3-08 | B57: [Normal] View Client Profile with currentUser = valid user id | C57: 1. Prepare the state listed in Pre-conditions. 2. Call ClientProfileServiceImpl.listMine with: currentUser = valid user id. 3. Check the response / error and the log. | D57: 200 OK - same single profile listed once | E57: - Can connect with server - Profile linked to workspaces of 2 agencies | F57: Passed | G57: 46300 | H57: Trung | I57: Pending | L57: Pending
A58: FR3.3.3-09 | B58: [Boundary] View Client Profile with currentUser = valid user id | C58: 1. Prepare the state listed in Pre-conditions. 2. Call ClientProfileServiceImpl.listMine with: currentUser = valid user id. 3. Check the response / error and the log. | D58: 200 OK - empty list, not 404 | E58: - Can connect with server - User has no client profile | F58: Passed | G58: 46300 | H58: Trung | I58: Pending | L58: Pending
A59: FR3.3.3-10 | B59: [Boundary] View Client Profile with currentUser = valid user id | C59: 1. Prepare the state listed in Pre-conditions. 2. Call ClientProfileServiceImpl.listMine with: currentUser = valid user id. 3. Check the response / error and the log. | D59: 200 OK - null fields returned as null | E59: - Can connect with server - Profile company/phone/note null | F59: Passed | G59: 46300 | H59: Trung | I59: Pending | L59: Pending
A60: FR3.3.3-11 | B60: [Boundary] View Client Profile with currentUser = valid user id | C60: 1. Prepare the state listed in Pre-conditions. 2. Call ClientProfileServiceImpl.listMine with: currentUser = valid user id. 3. Check the response / error and the log. | D60: 200 OK - socialLinks empty map | E60: - Can connect with server - Profile socialLinks null | F60: Passed | G60: 46300 | H60: Trung | I60: Pending | L60: Pending
A61: FR3.3.3-12 | B61: [Boundary] View Client Profile with currentUser = valid user id | C61: 1. Prepare the state listed in Pre-conditions. 2. Call ClientProfileServiceImpl.listMine with: currentUser = valid user id. 3. Check the response / error and the log. | D61: 200 OK - parseSocialLinks falls back to empty map | E61: - Can connect with server - Profile socialLinks malformed JSON | F61: Passed | G61: 46300 | H61: Trung | I61: Pending | L61: Pending
... A66: FR3.3.3-17 | B66: [Abnormal] View Client Profile with currentUser = expired token | C66: 1. Prepare the state listed in Pre-conditions. 2. Call ClientProfileServiceImpl.listMine with: currentUser = expired token. 3. Check the response / error and the log. | D66: Error: TOKEN_EXPIRED - 401 Authentication token has expired | E66: - Can connect with server - Access token expired | F66: Passed | G66: 46300 | H66: Trung | I66: Pending | L66: Pending
A67: 3.3.4 Update Client Profile
A68: FR3.3.4-01 | B68: [Normal] Update Client Profile with currentUser = valid user id, profileId = own profile id, displayName = Nike VN | C68: 1. Prepare the state listed in Pre-conditions. 2. Call ClientProfileServiceImpl.updateById with: currentUser = valid user id; profileId = own profile id; displayName = Nike VN; company = Nike; phone = 0901234567; note = VIP. 3. Check the response / error and the log. | D68: 200 OK - ClientProfileResponse with updated fields | E68: - Can connect with server - User owns the client profile | F68: Passed | G68: 46300 | H68: Trung | I68: Pending | L68: Pending
A69: FR3.3.4-02 | B69: [Normal] Update Client Profile with currentUser = valid user id, profileId = own profile id, displayName = Nike VN | C69: 1. Prepare the state listed in Pre-conditions. 2. Call ClientProfileServiceImpl.updateById with: currentUser = valid user id; profileId = own profile id; displayName = Nike VN . 3. Check the response / error and the log. | D69: 200 OK - displayName stored trimmed | E69: - Can connect with server - User owns the client profile | F69: Passed | G69: 46300 | H69: Trung | I69: Pending | L69: Pending
A70: FR3.3.4-03 | B70: [Normal] Update Client Profile with currentUser = valid user id, profileId = own profile id, displayName = Nike VN | C70: 1. Prepare the state listed in Pre-conditions. 2. Call ClientProfileServiceImpl.updateById with: currentUser = valid user id; profileId = own profile id; displayName = Nike VN; logoUrl = https://cdn/l.png; website = https://nike.vn; industry = Sport. 3. Check the response / error and the log. | D70: 200 OK - logo, website, industry saved | E70: - Can connect with server - User owns the client profile | F70: Passed | G70: 46300 | H70: Trung | I70: Pending | L70: Pending
A71: FR3.3.4-04 | B71: [Normal] Update Client Profile with currentUser = valid user id, profileId = own profile id, displayName = Nike VN | C71: 1. Prepare the state listed in Pre-conditions. 2. Call ClientProfileServiceImpl.updateById with: currentUser = valid user id; profileId = own profile id; displayName = Nike VN; socialLinks = {facebook: url}. 3. Check the response / error and the log. | D71: 200 OK - socialLinks serialized to JSON | E71: - Can connect with server - User owns the client profile | F71: Passed | G71: 46300 | H71: Trung | I71: Pending | L71: Pending
A72: FR3.3.4-05 | B72: [Normal] Update Client Profile with currentUser = valid user id, profileId = own profile id, displayName = Nike VN | C72: 1. Prepare the state listed in Pre-conditions. 2. Call ClientProfileServiceImpl.updateById with: currentUser = valid user id; profileId = own profile id; displayName = Nike VN; tagline = Just do it; foundedYear = 1964; budgetRange = 10k-50k. 3. Check the response / error and the log. | D72: 200 OK - brand fields saved | E72: - Can connect with server - User owns the client profile | F72: Passed | G72: 46300 | H72: Trung | I72: Pending | L72: Pending
A73: FR3.3.4-06 | B73: [Normal] Update Client Profile with currentUser = valid user id, profileId = own profile id, displayName = Nike VN | C73: 1. Prepare the state listed in Pre-conditions. 2. Call ClientProfileServiceImpl.updateById with: currentUser = valid user id; profileId = own profile id; displayName = Nike VN; company = empty; phone = empty; note = empty. 3. Check the response / error and the log. | D73: 200 OK - optional fields saved empty/null | E73: - Can connect with server - User owns the client profile | F73: Passed | G73: 46300 | H73: Trung | I73: Pending | L73: Pending
A74: FR3.3.4-07 | B74: [Normal] Update Client Profile with currentUser = valid user id, profileId = own profile id, displayName = Nike VN | C74: 1. Prepare the state listed in Pre-conditions. 2. Call ClientProfileServiceImpl.updateById with: currentUser = valid user id; profileId = own profile id; displayName = Nike VN. 3. Check the response / error and the log. | D74: 200 OK - single record updated, change visible everywhere | E74: - Can connect with server - User owns the client profile - Profile linked to 2 workspaces | F74: Passed | G74: 46300 | H74: Trung | I74: Pending | L74: Pending
A75: FR3.3.4-08 | B75: [Normal] Update Client Profile with currentUser = valid user id, displayName = New Brand | C75: 1. Prepare the state listed in Pre-conditions. 2. Call ClientProfileServiceImpl.updateById with: currentUser = valid user id; displayName = New Brand. 3. Check the response / error and the log. | D75: 200 OK - createProfile saves profile with userId = caller | E75: - Can connect with server - No profile for caller | F75: Passed | G75: 46300 | H75: Trung | I75: Pending | L75: Pending
A76: FR3.3.4-09 | B76: [Normal] Update Client Profile with currentUser = valid user id, profileId = own profile id | C76: 1. Prepare the state listed in Pre-conditions. 2. Call ClientProfileServiceImpl.updateById with: currentUser = valid user id; profileId = own profile id. 3. Check the response / error and the log. | D76: 204 No Content - deleteById removes profile | E76: - Can connect with server - User owns the client profile - Profile not linked to active workspace | F76: Passed | G76: 46300 | H76: Trung | I76: Pending | L76: Pending
A77: FR3.3.4-10 | B77: [Normal] Update Client Profile with currentUser = valid user id, profileId = own profile id, displayName = Nike VN | C77: 1. Prepare the state listed in Pre-conditions. 2. Call ClientProfileServiceImpl.updateById with: currentUser = valid user id; profileId = own profile id; displayName = Nike VN. 3. Check the response / error and the log. | D77: 200 OK - updatedAt refreshed, email never changed | E77: - Can connect with server - User owns the client profile | F77: Passed | G77: 46300 | H77: Trung | I77: Pending | L77: Pending
A78: FR3.3.4-11 | B78: [Boundary] Update Client Profile with currentUser = valid user id, profileId = own profile id, displayName = N | C78: 1. Prepare the state listed in Pre-conditions. 2. Call ClientProfileServiceImpl.updateById with: currentUser = valid user id; profileId = own profile id; displayName = N. 3. Check the response / error and the log. | D78: 200 OK - displayName 1 char accepted | E78: - Can connect with server - User owns the client profile | F78: Passed | G78: 46300 | H78: Trung | I78: Pending | L78: Pending
A79: FR3.3.4-12 | B79: [Boundary] Update Client Profile with currentUser = valid user id, profileId = own profile id, displayName = Nike VN | C79: 1. Prepare the state listed in Pre-conditions. 2. Call ClientProfileServiceImpl.updateById with: currentUser = valid user id; profileId = own profile id; displayName = Nike VN; foundedYear = null; socialLinks = null. 3. Check the response / error and the log. | D79: 200 OK - null socialLinks/foundedYear stored as null | E79: - Can connect with server - User owns the client profile | F79: Passed | G79: 46300 | H79: Trung | I79: Pending | L79: Pending
... A85: FR3.3.4-18 | B85: [Abnormal] Update Client Profile with currentUser = valid user id, profileId = other user's profile id | C85: 1. Prepare the state listed in Pre-conditions. 2. Call ClientProfileServiceImpl.updateById with: currentUser = valid user id; profileId = other user's profile id. 3. Check the response / error and the log. | D85: Error: CLIENT_PROFILE_NOT_OWNED - 403 delete other's profile | E85: - Can connect with server - Profile owned by another user | F85: Passed | G85: 46300 | H85: Trung | I85: Pending | L85: Pending

Sheet Agency & Workspace
A2: Feature | B2: Agency & Workspace | R2: Passed
A3: Test requirement | B3: Functional test of 3.4.1 List Agency; 3.4.2 View Agency Dashboard; 3.4.3 Create Agency; 3.4.4 View Agency Profile and 17 more | R3: Failed
A4: Number of TCs | B4: =COUNTA(F12:F1000) -> 394 | R4: Pending
A5: Testing Round | B5: Passed | C5: Failed | D5: Pending | E5: N/A | R5: N/A
A6: Round 1 | B6: =COUNTIF($F$10:$F$998,B$5) -> 394 | C6: =COUNTIF($F$10:$F$998,C$5) -> 0 | D6: =COUNTIF($F$10:$F$998,D$5) -> 0 | E6: =COUNTIF($F$10:$F$998,E$5) -> 0
A7: Round 2 | B7: =COUNTIF($I$10:$I$998,B$5) -> 0 | C7: =COUNTIF($I$10:$I$998,C$5) -> 0 | D7: =COUNTIF($I$10:$I$998,D$5) -> 394 | E7: =COUNTIF($I$10:$I$998,E$5) -> 0
A8: Round 3 | B8: =COUNTIF($L$10:$L$998,B$5) -> 0 | C8: =COUNTIF($L$10:$L$998,C$5) -> 0 | D8: =COUNTIF($L$10:$L$998,D$5) -> 394 | E8: =COUNTIF($L$10:$L$998,E$5) -> 0
A10: Test Case ID | B10: Test Case Description | C10: Test Case Procedure | D10: Expected Results | E10: Pre-conditions | F10: Round 1 | G10: Test date | H10: Tester | I10: Round 2 | J10: Test date | K10: Tester | L10: Round 3 | M10: Test date | N10: Tester | O10: Note
A11: 3.4.1 List Agency
A12: FR3.4.1-01 | B12: [Normal] List Agency with currentUser = owner user | C12: 1. Prepare the state listed in Pre-conditions. 2. Call AgencyServiceImpl.listMyAgencies with: currentUser = owner user. 3. Check the response / error and the log. | D12: 200 - [AgencyResponse(myRole=OWNER)] | E12: - Can connect with server - User owns 1 active agency | F12: Passed | G12: 46300 | H12: Trung | I12: Pending | L12: Pending
A13: FR3.4.1-02 | B13: [Normal] List Agency with currentUser = member user | C13: 1. Prepare the state listed in Pre-conditions. 2. Call AgencyServiceImpl.listMyAgencies with: currentUser = member user. 3. Check the response / error and the log. | D13: 200 - [AgencyResponse(myRole=role of membership)] | E13: - Can connect with server - User is member of 1 agency | F13: Passed | G13: 46300 | H13: Trung | I13: Pending | L13: Pending
A14: FR3.4.1-03 | B14: [Normal] List Agency with currentUser = mixed user | C14: 1. Prepare the state listed in Pre-conditions. 2. Call AgencyServiceImpl.listMyAgencies with: currentUser = mixed user. 3. Check the response / error and the log. | D14: 200 - 2 AgencyResponse items | E14: - Can connect with server - User owns 1 agency and is member of another | F14: Passed | G14: 46300 | H14: Trung | I14: Pending | L14: Pending
A15: FR3.4.1-04 | B15: [Normal] List Agency with currentUser = owner user | C15: 1. Prepare the state listed in Pre-conditions. 2. Call AgencyServiceImpl.listMyAgencies with: currentUser = owner user. 3. Check the response / error and the log. | D15: 200 - agency listed once (ids deduplicated) | E15: - Can connect with server - User owns agency with owner membership row | F15: Passed | G15: 46300 | H15: Trung | I15: Pending | L15: Pending
A16: FR3.4.1-05 | B16: [Normal] List Agency with currentUser = manager user | C16: 1. Prepare the state listed in Pre-conditions. 2. Call AgencyServiceImpl.listMyAgencies with: currentUser = manager user. 3. Check the response / error and the log. | D16: 200 - [AgencyResponse(myRole=MANAGER)] | E16: - Can connect with server - User is member with role MANAGER | F16: Passed | G16: 46300 | H16: Trung | I16: Pending | L16: Pending
A17: FR3.4.1-06 | B17: [Normal] List Agency with currentUser = staff user | C17: 1. Prepare the state listed in Pre-conditions. 2. Call AgencyServiceImpl.listMyAgencies with: currentUser = staff user. 3. Check the response / error and the log. | D17: 200 - [AgencyResponse(myRole=STAFF)] | E17: - Can connect with server - User is member with role STAFF | F17: Passed | G17: 46300 | H17: Trung | I17: Pending | L17: Pending
A18: FR3.4.1-07 | B18: [Normal] List Agency with currentUser = owner user | C18: 1. Prepare the state listed in Pre-conditions. 2. Call AgencyServiceImpl.listMyAgencies with: currentUser = owner user. 3. Check the response / error and the log. | D18: 200 - 3 AgencyResponse items | E18: - Can connect with server - User owns 3 agencies | F18: Passed | G18: 46300 | H18: Trung | I18: Pending | L18: Pending
A19: FR3.4.1-08 | B19: [Boundary] List Agency with currentUser = new user | C19: 1. Prepare the state listed in Pre-conditions. 2. Call AgencyServiceImpl.listMyAgencies with: currentUser = new user. 3. Check the response / error and the log. | D19: 200 - empty list | E19: - Can connect with server - User has no agency and no membership | F19: Passed | G19: 46300 | H19: Trung | I19: Pending | L19: Pending
A20: FR3.4.1-09 | B20: [Boundary] List Agency with currentUser = owner user | C20: 1. Prepare the state listed in Pre-conditions. 2. Call AgencyServiceImpl.listMyAgencies with: currentUser = owner user. 3. Check the response / error and the log. | D20: 200 - list size 1 | E20: - Can connect with server - User owns exactly 1 agency | F20: Passed | G20: 46300 | H20: Trung | I20: Pending | L20: Pending
A21: FR3.4.1-10 | B21: [Boundary] List Agency with currentUser = owner user | C21: 1. Prepare the state listed in Pre-conditions. 2. Call AgencyServiceImpl.listMyAgencies with: currentUser = owner user. 3. Check the response / error and the log. | D21: 200 - agency included | E21: - Can connect with server - User owns 1 agency, status ACTIVE | F21: Passed | G21: 46300 | H21: Trung | I21: Pending | L21: Pending
A22: FR3.4.1-11 | B22: [Boundary] List Agency with currentUser = member user | C22: 1. Prepare the state listed in Pre-conditions. 2. Call AgencyServiceImpl.listMyAgencies with: currentUser = member user. 3. Check the response / error and the log. | D22: 200 - list size 1 | E22: - Can connect with server - User is member of 1 agency only | F22: Passed | G22: 46300 | H22: Trung | I22: Pending | L22: Pending
A23: FR3.4.1-12 | B23: [Abnormal] List Agency with currentUser = owner user | C23: 1. Prepare the state listed in Pre-conditions. 2. Call AgencyServiceImpl.listMyAgencies with: currentUser = owner user. 3. Check the response / error and the log. | D23: 200 - empty list (soft-deleted filtered) | E23: - Can connect with server - User owns 1 SOFT_DELETED agency only | F23: Passed | G23: 46300 | H23: Trung | I23: Pending | L23: Pending
... A27: FR3.4.1-16 | B27: [Abnormal] List Agency with currentUser = null | C27: 1. Prepare the state listed in Pre-conditions. 2. Call AgencyServiceImpl.listMyAgencies with: currentUser = null. 3. Check the response / error and the log. | D27: Error: 401 UNAUTHORIZED - authentication required | E27: - Can connect with server - Request without valid token | F27: Passed | G27: 46300 | H27: Trung | I27: Pending | L27: Pending
A28: 3.4.2 View Agency Dashboard
A29: FR3.4.2-01 | B29: [Normal] View Agency Dashboard with agencyId = existing id, from = null, to = null | C29: 1. Prepare the state listed in Pre-conditions. 2. Call AgencyServiceImpl.getStats with: agencyId = existing id; from = null; to = null. 3. Check the response / error and the log. | D29: 200 - AgencyStatsResponse with totals, membersByRole, workspacesByIndustry, contentByStatus | E29: - Can connect with server - User is OWNER of agency - Agency has members, workspaces, posts | F29: Passed | G29: 46300 | H29: Trung | I29: Pending | L29: Pending
A30: FR3.4.2-02 | B30: [Normal] View Agency Dashboard with agencyId = existing id, from = null, to = null | C30: 1. Prepare the state listed in Pre-conditions. 2. Call AgencyServiceImpl.getStats with: agencyId = existing id; from = null; to = null. 3. Check the response / error and the log. | D30: 200 - AgencyStatsResponse | E30: - Can connect with server - User is MEMBER of agency (not owner) - Agency has data | F30: Passed | G30: 46300 | H30: Trung | I30: Pending | L30: Pending
A31: FR3.4.2-03 | B31: [Normal] View Agency Dashboard with agencyId = existing id, from = 2026-01-01, to = 2026-06-30 | C31: 1. Prepare the state listed in Pre-conditions. 2. Call AgencyServiceImpl.getStats with: agencyId = existing id; from = 2026-01-01; to = 2026-06-30. 3. Check the response / error and the log. | D31: 200 - stats filtered to date range | E31: - Can connect with server - User is OWNER of agency - Agency has data | F31: Passed | G31: 46300 | H31: Trung | I31: Pending | L31: Pending
A32: FR3.4.2-04 | B32: [Normal] View Agency Dashboard with agencyId = existing id, from = null, to = null | C32: 1. Prepare the state listed in Pre-conditions. 2. Call AgencyServiceImpl.getStats with: agencyId = existing id; from = null; to = null. 3. Check the response / error and the log. | D32: 200 - postsPublishedByMonth grouped yyyy-MM | E32: - Can connect with server - User is OWNER of agency - Agency has PUBLISHED posts | F32: Passed | G32: 46300 | H32: Trung | I32: Pending | L32: Pending
A33: FR3.4.2-05 | B33: [Normal] View Agency Dashboard with agencyId = existing id, from = null, to = null | C33: 1. Prepare the state listed in Pre-conditions. 2. Call AgencyServiceImpl.getStats with: agencyId = existing id; from = null; to = null. 3. Check the response / error and the log. | D33: 200 - memberGrowthByMonth grouped by month | E33: - Can connect with server - User is OWNER of agency - Agency has members joined in different months | F33: Passed | G33: 46300 | H33: Trung | I33: Pending | L33: Pending
A34: FR3.4.2-06 | B34: [Normal] View Agency Dashboard with agencyId = existing id, from = null, to = null | C34: 1. Prepare the state listed in Pre-conditions. 2. Call AgencyServiceImpl.getStats with: agencyId = existing id; from = null; to = null. 3. Check the response / error and the log. | D34: 200 - workspacesByIndustry counts | E34: - Can connect with server - User is OWNER of agency - Agency has workspaces with industry | F34: Passed | G34: 46300 | H34: Trung | I34: Pending | L34: Pending
A35: FR3.4.2-07 | B35: [Boundary] View Agency Dashboard with agencyId = existing id, from = null, to = null | C35: 1. Prepare the state listed in Pre-conditions. 2. Call AgencyServiceImpl.getStats with: agencyId = existing id; from = null; to = null. 3. Check the response / error and the log. | D35: 200 - totalWorkspaces=0, no Mongo query, empty content maps | E35: - Can connect with server - User is OWNER of agency - Agency has no workspaces | F35: Passed | G35: 46300 | H35: Trung | I35: Pending | L35: Pending
A36: FR3.4.2-08 | B36: [Boundary] View Agency Dashboard with agencyId = existing id, from = null, to = null | C36: 1. Prepare the state listed in Pre-conditions. 2. Call AgencyServiceImpl.getStats with: agencyId = existing id; from = null; to = null. 3. Check the response / error and the log. | D36: 200 - totalMembers=1, membersByRole={OWNER:1} | E36: - Can connect with server - User is OWNER of agency - Agency has only the owner member | F36: Passed | G36: 46300 | H36: Trung | I36: Pending | L36: Pending
A37: FR3.4.2-09 | B37: [Boundary] View Agency Dashboard with agencyId = existing id, from = joinedAt date, to = null | C37: 1. Prepare the state listed in Pre-conditions. 2. Call AgencyServiceImpl.getStats with: agencyId = existing id; from = joinedAt date; to = null. 3. Check the response / error and the log. | D37: 200 - member included (inclusive bound) | E37: - Can connect with server - User is OWNER of agency - Member joined exactly on from date | F37: Passed | G37: 46300 | H37: Trung | I37: Pending | L37: Pending
A38: FR3.4.2-10 | B38: [Boundary] View Agency Dashboard with agencyId = existing id, from = null, to = joinedAt date | C38: 1. Prepare the state listed in Pre-conditions. 2. Call AgencyServiceImpl.getStats with: agencyId = existing id; from = null; to = joinedAt date. 3. Check the response / error and the log. | D38: 200 - member included (inclusive bound) | E38: - Can connect with server - User is OWNER of agency - Member joined exactly on to date | F38: Passed | G38: 46300 | H38: Trung | I38: Pending | L38: Pending
A39: FR3.4.2-11 | B39: [Boundary] View Agency Dashboard with agencyId = existing id, from = only from set, to = null | C39: 1. Prepare the state listed in Pre-conditions. 2. Call AgencyServiceImpl.getStats with: agencyId = existing id; from = only from set; to = null. 3. Check the response / error and the log. | D39: 200 - open-ended range filter applied | E39: - Can connect with server - User is OWNER of agency - Agency has data | F39: Passed | G39: 46300 | H39: Trung | I39: Pending | L39: Pending
A40: FR3.4.2-12 | B40: [Abnormal] View Agency Dashboard with agencyId = existing id, from = not-a-date, to = null | C40: 1. Prepare the state listed in Pre-conditions. 2. Call AgencyServiceImpl.getStats with: agencyId = existing id; from = not-a-date; to = null. 3. Check the response / error and the log. | D40: 200 - invalid date ignored, full-range stats | E40: - Can connect with server - User is OWNER of agency - Agency has data | F40: Passed | G40: 46300 | H40: Trung | I40: Pending | L40: Pending
... A44: FR3.4.2-16 | B44: [Abnormal] View Agency Dashboard with agencyId = existing id, from = 2000-01-01, to = 2000-01-31 | C44: 1. Prepare the state listed in Pre-conditions. 2. Call AgencyServiceImpl.getStats with: agencyId = existing id; from = 2000-01-01; to = 2000-01-31. 3. Check the response / error and the log. | D44: 200 - all counts 0, empty maps | E44: - Can connect with server - User is OWNER of agency - Range excludes all data | F44: Passed | G44: 46300 | H44: Trung | I44: Pending | L44: Pending
A45: 3.4.3 Create Agency
A46: FR3.4.3-01 | B46: [Normal] Create Agency with currentUser = authenticated user, name = valid name | C46: 1. Prepare the state listed in Pre-conditions. 2. Call AgencyServiceImpl.createAgency with: currentUser = authenticated user; name = valid name. 3. Check the response / error and the log. | D46: 201 - AgencyResponse(myRole=OWNER), owner membership saved | E46: - Can connect with server - User authenticated | F46: Passed | G46: 46300 | H46: Trung | I46: Pending | L46: Pending
A47: FR3.4.3-02 | B47: [Normal] Create Agency with currentUser = authenticated user, name = valid name, category = valid category | C47: 1. Prepare the state listed in Pre-conditions. 2. Call AgencyServiceImpl.createAgency with: currentUser = authenticated user; name = valid name; category = valid category; companySize = valid size. 3. Check the response / error and the log. | D47: 201 - AgencyResponse with category and size | E47: - Can connect with server - User authenticated | F47: Passed | G47: 46300 | H47: Trung | I47: Pending | L47: Pending
A48: FR3.4.3-03 | B48: [Normal] Create Agency with currentUser = authenticated user, name = valid name, website = https://brandhub.vn | C48: 1. Prepare the state listed in Pre-conditions. 2. Call AgencyServiceImpl.createAgency with: currentUser = authenticated user; name = valid name; website = https://brandhub.vn; phone = valid phone. 3. Check the response / error and the log. | D48: 201 - AgencyResponse with website and phone | E48: - Can connect with server - User authenticated | F48: Passed | G48: 46300 | H48: Trung | I48: Pending | L48: Pending
A49: FR3.4.3-04 | B49: [Normal] Create Agency with currentUser = authenticated user, name = valid name, logoUrl = valid url | C49: 1. Prepare the state listed in Pre-conditions. 2. Call AgencyServiceImpl.createAgency with: currentUser = authenticated user; name = valid name; logoUrl = valid url; bannerUrl = valid url. 3. Check the response / error and the log. | D49: 201 - AgencyResponse with logo and banner | E49: - Can connect with server - User authenticated | F49: Passed | G49: 46300 | H49: Trung | I49: Pending | L49: Pending
A50: FR3.4.3-05 | B50: [Normal] Create Agency with currentUser = authenticated user, name = valid name, brandColor = #FF5500 | C50: 1. Prepare the state listed in Pre-conditions. 2. Call AgencyServiceImpl.createAgency with: currentUser = authenticated user; name = valid name; brandColor = #FF5500; tagline = valid tagline; foundedYear = 2020. 3. Check the response / error and the log. | D50: 201 - AgencyResponse with branding fields | E50: - Can connect with server - User authenticated | F50: Passed | G50: 46300 | H50: Trung | I50: Pending | L50: Pending
A51: FR3.4.3-06 | B51: [Normal] Create Agency with currentUser = authenticated user, name = valid name, facebookUrl = valid url | C51: 1. Prepare the state listed in Pre-conditions. 2. Call AgencyServiceImpl.createAgency with: currentUser = authenticated user; name = valid name; facebookUrl = valid url; linkedinUrl = valid url; instagramUrl = valid url. 3. Check the response / error and the log. | D51: 201 - AgencyResponse with social links | E51: - Can connect with server - User authenticated | F51: Passed | G51: 46300 | H51: Trung | I51: Pending | L51: Pending
A52: FR3.4.3-07 | B52: [Normal] Create Agency with currentUser = authenticated user, name = padded name | C52: 1. Prepare the state listed in Pre-conditions. 2. Call AgencyServiceImpl.createAgency with: currentUser = authenticated user; name = padded name . 3. Check the response / error and the log. | D52: 201 - name trimmed to 'padded name' | E52: - Can connect with server - User authenticated | F52: Passed | G52: 46300 | H52: Trung | I52: Pending | L52: Pending
A53: FR3.4.3-08 | B53: [Normal] Create Agency with currentUser = authenticated user, name = another valid name | C53: 1. Prepare the state listed in Pre-conditions. 2. Call AgencyServiceImpl.createAgency with: currentUser = authenticated user; name = another valid name. 3. Check the response / error and the log. | D53: 201 - second agency created, caller OWNER | E53: - Can connect with server - User already owns an agency | F53: Passed | G53: 46300 | H53: Trung | I53: Pending | L53: Pending
A54: FR3.4.3-09 | B54: [Boundary] Create Agency with currentUser = authenticated user, name = 1 char name | C54: 1. Prepare the state listed in Pre-conditions. 2. Call AgencyServiceImpl.createAgency with: currentUser = authenticated user; name = 1 char name. 3. Check the response / error and the log. | D54: 201 - AgencyResponse created | E54: - Can connect with server - User authenticated | F54: Passed | G54: 46300 | H54: Trung | I54: Pending | L54: Pending
A55: FR3.4.3-10 | B55: [Boundary] Create Agency with currentUser = authenticated user, name = valid name, description = null | C55: 1. Prepare the state listed in Pre-conditions. 2. Call AgencyServiceImpl.createAgency with: currentUser = authenticated user; name = valid name; description = null; tagline = null. 3. Check the response / error and the log. | D55: 201 - optional fields stored as null | E55: - Can connect with server - User authenticated | F55: Passed | G55: 46300 | H55: Trung | I55: Pending | L55: Pending
A56: FR3.4.3-11 | B56: [Boundary] Create Agency with currentUser = authenticated user, name = valid name, foundedYear = 1900 | C56: 1. Prepare the state listed in Pre-conditions. 2. Call AgencyServiceImpl.createAgency with: currentUser = authenticated user; name = valid name; foundedYear = 1900. 3. Check the response / error and the log. | D56: 201 - AgencyResponse created | E56: - Can connect with server - User authenticated | F56: Passed | G56: 46300 | H56: Trung | I56: Pending | L56: Pending
A57: FR3.4.3-12 | B57: [Boundary] Create Agency with currentUser = authenticated user, name = valid name, description = very long text | C57: 1. Prepare the state listed in Pre-conditions. 2. Call AgencyServiceImpl.createAgency with: currentUser = authenticated user; name = valid name; description = very long text. 3. Check the response / error and the log. | D57: 201 - AgencyResponse created | E57: - Can connect with server - User authenticated | F57: Passed | G57: 46300 | H57: Trung | I57: Pending | L57: Pending
... A62: FR3.4.3-17 | B62: [Abnormal] Create Agency with currentUser = authenticated user, name = valid name, category = unknown enum value | C62: 1. Prepare the state listed in Pre-conditions. 2. Call AgencyServiceImpl.createAgency with: currentUser = authenticated user; name = valid name; category = unknown enum value. 3. Check the response / error and the log. | D62: Error: 400 HttpMessageNotReadableException - invalid category | E62: - Can connect with server - User authenticated | F62: Passed | G62: 46300 | H62: Trung | I62: Pending | L62: Pending
A63: 3.4.4 View Agency Profile
A64: FR3.4.4-01 | B64: [Normal] View Agency Profile with agencyId = existing id | C64: 1. Prepare the state listed in Pre-conditions. 2. Call AgencyServiceImpl.getAgency with: agencyId = existing id. 3. Check the response / error and the log. | D64: 200 - AgencyResponse(myRole=OWNER) | E64: - Can connect with server - User is OWNER of agency | F64: Passed | G64: 46300 | H64: Trung | I64: Pending | L64: Pending
A65: FR3.4.4-02 | B65: [Normal] View Agency Profile with agencyId = existing id | C65: 1. Prepare the state listed in Pre-conditions. 2. Call AgencyServiceImpl.getAgency with: agencyId = existing id. 3. Check the response / error and the log. | D65: 200 - AgencyResponse(myRole=MANAGER) | E65: - Can connect with server - User is MEMBER of agency (not owner) - Member role MANAGER | F65: Passed | G65: 46300 | H65: Trung | I65: Pending | L65: Pending
A66: FR3.4.4-03 | B66: [Normal] View Agency Profile with agencyId = existing id | C66: 1. Prepare the state listed in Pre-conditions. 2. Call AgencyServiceImpl.getAgency with: agencyId = existing id. 3. Check the response / error and the log. | D66: 200 - AgencyResponse(myRole=STAFF) | E66: - Can connect with server - User is MEMBER of agency (not owner) - Member role STAFF | F66: Passed | G66: 46300 | H66: Trung | I66: Pending | L66: Pending
A67: FR3.4.4-04 | B67: [Normal] View Agency Profile with agencyId = existing id | C67: 1. Prepare the state listed in Pre-conditions. 2. Call AgencyServiceImpl.getAgency with: agencyId = existing id. 3. Check the response / error and the log. | D67: 200 - AgencyResponse(myRole=null) | E67: - Can connect with server - User is CLIENT in a workspace of agency | F67: Passed | G67: 46300 | H67: Trung | I67: Pending | L67: Pending
A68: FR3.4.4-05 | B68: [Normal] View Agency Profile with agencyId = existing id | C68: 1. Prepare the state listed in Pre-conditions. 2. Call AgencyServiceImpl.getAgency with: agencyId = existing id. 3. Check the response / error and the log. | D68: 200 - AgencyResponse with all fields | E68: - Can connect with server - User is OWNER of agency - Agency has all profile fields | F68: Passed | G68: 46300 | H68: Trung | I68: Pending | L68: Pending
A69: FR3.4.4-06 | B69: [Normal] View Agency Profile with agencyId = existing id | C69: 1. Prepare the state listed in Pre-conditions. 2. Call AgencyServiceImpl.getAgency with: agencyId = existing id. 3. Check the response / error and the log. | D69: 200 - AgencyResponse(myRole=OWNER fallback) | E69: - Can connect with server - User is OWNER of agency - Owner has no agency_members row | F69: Passed | G69: 46300 | H69: Trung | I69: Pending | L69: Pending
A70: FR3.4.4-07 | B70: [Normal] View Agency Profile with agencyId = existing id | C70: 1. Prepare the state listed in Pre-conditions. 2. Call AgencyServiceImpl.getAgency with: agencyId = existing id. 3. Check the response / error and the log. | D70: 200 - AgencyResponse(myRole=null) | E70: - Can connect with server - User is CLIENT in 2 workspaces of agency | F70: Passed | G70: 46300 | H70: Trung | I70: Pending | L70: Pending
A71: FR3.4.4-08 | B71: [Boundary] View Agency Profile with agencyId = existing id | C71: 1. Prepare the state listed in Pre-conditions. 2. Call AgencyServiceImpl.getAgency with: agencyId = existing id. 3. Check the response / error and the log. | D71: 200 - AgencyResponse, optional fields null | E71: - Can connect with server - User is OWNER of agency - Agency has only mandatory fields | F71: Passed | G71: 46300 | H71: Trung | I71: Pending | L71: Pending
A72: FR3.4.4-09 | B72: [Boundary] View Agency Profile with agencyId = existing id | C72: 1. Prepare the state listed in Pre-conditions. 2. Call AgencyServiceImpl.getAgency with: agencyId = existing id. 3. Check the response / error and the log. | D72: 200 - AgencyResponse | E72: - Can connect with server - User is MEMBER of agency (not owner) - Member is the only non-owner member | F72: Passed | G72: 46300 | H72: Trung | I72: Pending | L72: Pending
A73: FR3.4.4-10 | B73: [Boundary] View Agency Profile with agencyId = existing id | C73: 1. Prepare the state listed in Pre-conditions. 2. Call AgencyServiceImpl.getAgency with: agencyId = existing id. 3. Check the response / error and the log. | D73: Error: NOT_AGENCY_MEMBER: User is not a member of this agency | E73: - Can connect with server - User has client profile but no active workspace membership | F73: Passed | G73: 46300 | H73: Trung | I73: Pending | L73: Pending
A74: FR3.4.4-11 | B74: [Abnormal] View Agency Profile with agencyId = non-existing id | C74: 1. Prepare the state listed in Pre-conditions. 2. Call AgencyServiceImpl.getAgency with: agencyId = non-existing id. 3. Check the response / error and the log. | D74: Error: AGENCY_NOT_FOUND: Agency not found | E74: - Can connect with server - Agency does not exist | F74: Passed | G74: 46300 | H74: Trung | I74: Pending | L74: Pending
A75: FR3.4.4-12 | B75: [Abnormal] View Agency Profile with agencyId = existing id | C75: 1. Prepare the state listed in Pre-conditions. 2. Call AgencyServiceImpl.getAgency with: agencyId = existing id. 3. Check the response / error and the log. | D75: Error: NOT_AGENCY_MEMBER: User is not a member of this agency | E75: - Can connect with server - User is not related to agency | F75: Passed | G75: 46300 | H75: Trung | I75: Pending | L75: Pending
... A79: FR3.4.4-16 | B79: [Abnormal] View Agency Profile with agencyId = existing id, currentUser = null | C79: 1. Prepare the state listed in Pre-conditions. 2. Call AgencyServiceImpl.getAgency with: agencyId = existing id; currentUser = null. 3. Check the response / error and the log. | D79: Error: 401 UNAUTHORIZED - authentication required | E79: - Can connect with server - Request without valid token | F79: Passed | G79: 46300 | H79: Trung | I79: Pending | L79: Pending
A80: 3.4.5 Update Agency Profile
A81: FR3.4.5-01 | B81: [Normal] Update Agency Profile with agencyId = existing id, name = new valid name | C81: 1. Prepare the state listed in Pre-conditions. 2. Call AgencyServiceImpl.updateAgency with: agencyId = existing id; name = new valid name. 3. Check the response / error and the log. | D81: 200 - AgencyResponse(myRole=OWNER) with updated name | E81: - Can connect with server - User is OWNER of agency | F81: Passed | G81: 46300 | H81: Trung | I81: Pending | L81: Pending
A82: FR3.4.5-02 | B82: [Normal] Update Agency Profile with agencyId = existing id, name = valid name, description = new description | C82: 1. Prepare the state listed in Pre-conditions. 2. Call AgencyServiceImpl.updateAgency with: agencyId = existing id; name = valid name; description = new description. 3. Check the response / error and the log. | D82: 200 - description updated | E82: - Can connect with server - User is OWNER of agency | F82: Passed | G82: 46300 | H82: Trung | I82: Pending | L82: Pending
A83: FR3.4.5-03 | B83: [Normal] Update Agency Profile with agencyId = existing id, name = valid name, category = valid category | C83: 1. Prepare the state listed in Pre-conditions. 2. Call AgencyServiceImpl.updateAgency with: agencyId = existing id; name = valid name; category = valid category; companySize = valid size. 3. Check the response / error and the log. | D83: 200 - category and size updated | E83: - Can connect with server - User is OWNER of agency | F83: Passed | G83: 46300 | H83: Trung | I83: Pending | L83: Pending
A84: FR3.4.5-04 | B84: [Normal] Update Agency Profile with agencyId = existing id, name = valid name, website = https://brandhub.vn | C84: 1. Prepare the state listed in Pre-conditions. 2. Call AgencyServiceImpl.updateAgency with: agencyId = existing id; name = valid name; website = https://brandhub.vn; phone = valid phone; location = valid location. 3. Check the response / error and the log. | D84: 200 - contact fields updated | E84: - Can connect with server - User is OWNER of agency | F84: Passed | G84: 46300 | H84: Trung | I84: Pending | L84: Pending
A85: FR3.4.5-05 | B85: [Normal] Update Agency Profile with agencyId = existing id, name = valid name, bannerUrl = new banner url | C85: 1. Prepare the state listed in Pre-conditions. 2. Call AgencyServiceImpl.updateAgency with: agencyId = existing id; name = valid name; bannerUrl = new banner url. 3. Check the response / error and the log. | D85: 200 - bannerUrl replaced | E85: - Can connect with server - User is OWNER of agency | F85: Passed | G85: 46300 | H85: Trung | I85: Pending | L85: Pending
A86: FR3.4.5-06 | B86: [Normal] Update Agency Profile with agencyId = existing id, name = valid name, bannerUrl = null | C86: 1. Prepare the state listed in Pre-conditions. 2. Call AgencyServiceImpl.updateAgency with: agencyId = existing id; name = valid name; bannerUrl = null. 3. Check the response / error and the log. | D86: 200 - existing bannerUrl kept unchanged | E86: - Can connect with server - User is OWNER of agency | F86: Passed | G86: 46300 | H86: Trung | I86: Pending | L86: Pending
A87: FR3.4.5-07 | B87: [Normal] Update Agency Profile with agencyId = existing id, name = padded name | C87: 1. Prepare the state listed in Pre-conditions. 2. Call AgencyServiceImpl.updateAgency with: agencyId = existing id; name = padded name . 3. Check the response / error and the log. | D87: 200 - name trimmed | E87: - Can connect with server - User is OWNER of agency | F87: Passed | G87: 46300 | H87: Trung | I87: Pending | L87: Pending
A88: FR3.4.5-08 | B88: [Normal] Update Agency Profile with agencyId = existing id, name = valid name, brandColor = #00AAFF | C88: 1. Prepare the state listed in Pre-conditions. 2. Call AgencyServiceImpl.updateAgency with: agencyId = existing id; name = valid name; brandColor = #00AAFF; logoIcon = icon; tagline = new tagline. 3. Check the response / error and the log. | D88: 200 - branding updated | E88: - Can connect with server - User is OWNER of agency | F88: Passed | G88: 46300 | H88: Trung | I88: Pending | L88: Pending
A89: FR3.4.5-09 | B89: [Normal] Update Agency Profile with agencyId = existing id, name = valid name, facebookUrl = valid url | C89: 1. Prepare the state listed in Pre-conditions. 2. Call AgencyServiceImpl.updateAgency with: agencyId = existing id; name = valid name; facebookUrl = valid url; linkedinUrl = valid url; instagramUrl = valid url. 3. Check the response / error and the log. | D89: 200 - social links updated | E89: - Can connect with server - User is OWNER of agency | F89: Passed | G89: 46300 | H89: Trung | I89: Pending | L89: Pending
A90: FR3.4.5-10 | B90: [Boundary] Update Agency Profile with agencyId = existing id, name = 1 char name | C90: 1. Prepare the state listed in Pre-conditions. 2. Call AgencyServiceImpl.updateAgency with: agencyId = existing id; name = 1 char name. 3. Check the response / error and the log. | D90: 200 - name updated | E90: - Can connect with server - User is OWNER of agency | F90: Passed | G90: 46300 | H90: Trung | I90: Pending | L90: Pending
A91: FR3.4.5-11 | B91: [Boundary] Update Agency Profile with agencyId = existing id, name = valid name, logoUrl = null | C91: 1. Prepare the state listed in Pre-conditions. 2. Call AgencyServiceImpl.updateAgency with: agencyId = existing id; name = valid name; logoUrl = null; description = null. 3. Check the response / error and the log. | D91: 200 - logoUrl and description set to null | E91: - Can connect with server - User is OWNER of agency | F91: Passed | G91: 46300 | H91: Trung | I91: Pending | L91: Pending
A92: FR3.4.5-12 | B92: [Boundary] Update Agency Profile with agencyId = existing id, name = valid name, foundedYear = 1900 | C92: 1. Prepare the state listed in Pre-conditions. 2. Call AgencyServiceImpl.updateAgency with: agencyId = existing id; name = valid name; foundedYear = 1900. 3. Check the response / error and the log. | D92: 200 - foundedYear updated | E92: - Can connect with server - User is OWNER of agency | F92: Passed | G92: 46300 | H92: Trung | I92: Pending | L92: Pending
... A97: FR3.4.5-17 | B97: [Abnormal] Update Agency Profile with agencyId = existing id, name = valid name | C97: 1. Prepare the state listed in Pre-conditions. 2. Call AgencyServiceImpl.updateAgency with: agencyId = existing id; name = valid name. 3. Check the response / error and the log. | D97: Error: NOT_AGENCY_OWNER: Only the agency owner can perform this action | E97: - Can connect with server - User is not related to agency | F97: Passed | G97: 46300 | H97: Trung | I97: Pending | L97: Pending
A98: 3.4.6 Remove Agency
A99: FR3.4.6-01 | B99: [Normal] Remove Agency with agencyId = existing id | C99: 1. Prepare the state listed in Pre-conditions. 2. Call AgencyServiceImpl.removeAgency with: agencyId = existing id. 3. Check the response / error and the log. | D99: 204 - agency and 2 workspaces SOFT_DELETED with deletedAt | E99: - Can connect with server - User is OWNER of agency - Agency has 2 workspaces | F99: Passed | G99: 46300 | H99: Trung | I99: Pending | L99: Pending
A100: FR3.4.6-02 | B100: [Normal] Remove Agency with agencyId = existing id | C100: 1. Prepare the state listed in Pre-conditions. 2. Call AgencyServiceImpl.removeAgency with: agencyId = existing id. 3. Check the response / error and the log. | D100: 204 - agency and workspace SOFT_DELETED | E100: - Can connect with server - User is OWNER of agency - Agency has 1 workspace | F100: Passed | G100: 46300 | H100: Trung | I100: Pending | L100: Pending
A101: FR3.4.6-03 | B101: [Normal] Remove Agency with agencyId = existing id | C101: 1. Prepare the state listed in Pre-conditions. 2. Call AgencyServiceImpl.removeAgency with: agencyId = existing id. 3. Check the response / error and the log. | D101: 204 - agency SOFT_DELETED, member rows kept | E101: - Can connect with server - User is OWNER of agency - Agency has members | F101: Passed | G101: 46300 | H101: Trung | I101: Pending | L101: Pending
A102: FR3.4.6-04 | B102: [Normal] Remove Agency with agencyId = existing id | C102: 1. Prepare the state listed in Pre-conditions. 2. Call AgencyServiceImpl.removeAgency with: agencyId = existing id. 3. Check the response / error and the log. | D102: 204 - agency SOFT_DELETED | E102: - Can connect with server - User is OWNER of agency - Agency has pending invitations | F102: Passed | G102: 46300 | H102: Trung | I102: Pending | L102: Pending
A103: FR3.4.6-05 | B103: [Normal] Remove Agency with agencyId = existing id | C103: 1. Prepare the state listed in Pre-conditions. 2. Call AgencyServiceImpl.removeAgency with: agencyId = existing id. 3. Check the response / error and the log. | D103: 204 - agency and workspaces get same deletedAt timestamp | E103: - Can connect with server - User is OWNER of agency - Agency has 2 workspaces | F103: Passed | G103: 46300 | H103: Trung | I103: Pending | L103: Pending
A104: FR3.4.6-06 | B104: [Normal] Remove Agency with agencyId = existing id | C104: 1. Prepare the state listed in Pre-conditions. 2. Call AgencyServiceImpl.removeAgency with: agencyId = existing id. 3. Check the response / error and the log. | D104: 204 - status changed ACTIVE to SOFT_DELETED | E104: - Can connect with server - User is OWNER of agency - Agency status ACTIVE | F104: Passed | G104: 46300 | H104: Trung | I104: Pending | L104: Pending
A105: FR3.4.6-07 | B105: [Boundary] Remove Agency with agencyId = existing id | C105: 1. Prepare the state listed in Pre-conditions. 2. Call AgencyServiceImpl.removeAgency with: agencyId = existing id. 3. Check the response / error and the log. | D105: 204 - only agency SOFT_DELETED | E105: - Can connect with server - User is OWNER of agency - Agency has no workspace | F105: Passed | G105: 46300 | H105: Trung | I105: Pending | L105: Pending
A106: FR3.4.6-08 | B106: [Boundary] Remove Agency with agencyId = existing id | C106: 1. Prepare the state listed in Pre-conditions. 2. Call AgencyServiceImpl.removeAgency with: agencyId = existing id. 3. Check the response / error and the log. | D106: 204 - agency SOFT_DELETED | E106: - Can connect with server - User is OWNER of agency - Agency has only owner member | F106: Passed | G106: 46300 | H106: Trung | I106: Pending | L106: Pending
A107: FR3.4.6-09 | B107: [Boundary] Remove Agency with agencyId = existing id | C107: 1. Prepare the state listed in Pre-conditions. 2. Call AgencyServiceImpl.removeAgency with: agencyId = existing id. 3. Check the response / error and the log. | D107: 204 - workspace deletedAt overwritten, no error | E107: - Can connect with server - User is OWNER of agency - Agency has 1 workspace already SOFT_DELETED | F107: Passed | G107: 46300 | H107: Trung | I107: Pending | L107: Pending
A108: FR3.4.6-10 | B108: [Boundary] Remove Agency with agencyId = existing id | C108: 1. Prepare the state listed in Pre-conditions. 2. Call AgencyServiceImpl.removeAgency with: agencyId = existing id. 3. Check the response / error and the log. | D108: 204 - status stays SOFT_DELETED (idempotent) | E108: - Can connect with server - User is OWNER of agency - Agency already SOFT_DELETED | F108: Passed | G108: 46300 | H108: Trung | I108: Pending | L108: Pending
A109: FR3.4.6-11 | B109: [Abnormal] Remove Agency with agencyId = non-existing id | C109: 1. Prepare the state listed in Pre-conditions. 2. Call AgencyServiceImpl.removeAgency with: agencyId = non-existing id. 3. Check the response / error and the log. | D109: Error: AGENCY_NOT_FOUND: Agency not found | E109: - Can connect with server - Agency does not exist | F109: Passed | G109: 46300 | H109: Trung | I109: Pending | L109: Pending
A110: FR3.4.6-12 | B110: [Abnormal] Remove Agency with agencyId = existing id | C110: 1. Prepare the state listed in Pre-conditions. 2. Call AgencyServiceImpl.removeAgency with: agencyId = existing id. 3. Check the response / error and the log. | D110: Error: NOT_AGENCY_OWNER: Only the agency owner can perform this action | E110: - Can connect with server - User is MEMBER of agency (not owner) - Member role MANAGER | F110: Passed | G110: 46300 | H110: Trung | I110: Pending | L110: Pending
... A114: FR3.4.6-16 | B114: [Abnormal] Remove Agency with agencyId = existing id, currentUser = null | C114: 1. Prepare the state listed in Pre-conditions. 2. Call AgencyServiceImpl.removeAgency with: agencyId = existing id; currentUser = null. 3. Check the response / error and the log. | D114: Error: 401 UNAUTHORIZED - authentication required | E114: - Can connect with server - Request without valid token | F114: Passed | G114: 46300 | H114: Trung | I114: Pending | L114: Pending
A115: 3.4.7 Invite Agency Member
A116: FR3.4.7-01 | B116: [Normal] Invite Agency Member with agencyId = existing id, email = new@brandhub.vn | C116: 1. Prepare the state listed in Pre-conditions. 2. Call AgencyServiceImpl.inviteMember with: agencyId = existing id; email = new@brandhub.vn. 3. Check the response / error and the log. | D116: 201 - AgencyInvitationResponse(status=PENDING, expires in 30 days) Log: Agency invitation email sent | E116: - Can connect with server - User is OWNER of agency | F116: Passed | G116: 46300 | H116: Trung | I116: Pending | L116: Pending
A117: FR3.4.7-02 | B117: [Normal] Invite Agency Member with agencyId = existing id, email = NEW@BrandHub.vn | C117: 1. Prepare the state listed in Pre-conditions. 2. Call AgencyServiceImpl.inviteMember with: agencyId = existing id; email = NEW@BrandHub.vn . 3. Check the response / error and the log. | D117: 201 - email normalized to lowercase and trimmed Log: Agency invitation email sent | E117: - Can connect with server - User is OWNER of agency | F117: Passed | G117: 46300 | H117: Trung | I117: Pending | L117: Pending
A118: FR3.4.7-03 | B118: [Normal] Invite Agency Member with agencyId = existing id, email = new@brandhub.vn, expiryDays = 7 | C118: 1. Prepare the state listed in Pre-conditions. 2. Call AgencyServiceImpl.inviteMember with: agencyId = existing id; email = new@brandhub.vn; expiryDays = 7. 3. Check the response / error and the log. | D118: 201 - expiresAt = now + 7 days Log: Agency invitation email sent | E118: - Can connect with server - User is OWNER of agency | F118: Passed | G118: 46300 | H118: Trung | I118: Pending | L118: Pending
A119: FR3.4.7-04 | B119: [Normal] Invite Agency Member with agencyId = existing id, email = new@brandhub.vn, note = Welcome aboard | C119: 1. Prepare the state listed in Pre-conditions. 2. Call AgencyServiceImpl.inviteMember with: agencyId = existing id; email = new@brandhub.vn; note = Welcome aboard; inviteeName = An. 3. Check the response / error and the log. | D119: 201 - invitation with note Log: Agency invitation email sent | E119: - Can connect with server - User is OWNER of agency | F119: Passed | G119: 46300 | H119: Trung | I119: Pending | L119: Pending
A120: FR3.4.7-05 | B120: [Normal] Invite Agency Member with agencyId = existing id, email = new@brandhub.vn, workspaceId = agency workspace id | C120: 1. Prepare the state listed in Pre-conditions. 2. Call AgencyServiceImpl.inviteMember with: agencyId = existing id; email = new@brandhub.vn; workspaceId = agency workspace id; role = STAFF. 3. Check the response / error and the log. | D120: 201 - invitation assigned to workspace with role STAFF Log: Agency invitation email sent | E120: - Can connect with server - User is OWNER of agency - Workspace belongs to agency | F120: Passed | G120: 46300 | H120: Trung | I120: Pending | L120: Pending
A121: FR3.4.7-06 | B121: [Normal] Invite Agency Member with agencyId = existing id, email = new@brandhub.vn, workspaceId = agency workspace id | C121: 1. Prepare the state listed in Pre-conditions. 2. Call AgencyServiceImpl.inviteMember with: agencyId = existing id; email = new@brandhub.vn; workspaceId = agency workspace id; role = MANAGER. 3. Check the response / error and the log. | D121: 201 - invitation with role MANAGER Log: Agency invitation email sent | E121: - Can connect with server - User is OWNER of agency - Workspace belongs to agency and has no manager | F121: Passed | G121: 46300 | H121: Trung | I121: Pending | L121: Pending
A122: FR3.4.7-07 | B122: [Normal] Invite Agency Member with agencyId = existing id, email = client@brandhub.vn, workspaceId = agency workspace id | C122: 1. Prepare the state listed in Pre-conditions. 2. Call AgencyServiceImpl.inviteMember with: agencyId = existing id; email = client@brandhub.vn; workspaceId = agency workspace id; role = CLIENT. 3. Check the response / error and the log. | D122: 201 - CLIENT invitation scoped to workspace Log: Agency invitation email sent | E122: - Can connect with server - User is OWNER of agency - Workspace belongs to agency | F122: Passed | G122: 46300 | H122: Trung | I122: Pending | L122: Pending
...

Sheet Media Package
A2: Feature | B2: Media Package | R2: Passed
A3: Test requirement | B3: Functional test of 3.5.1 Create Media Package; 3.5.2 View the Template Media Package; 3.5.3 Request Media Package (Negotiate Terms); 3.5.4 Approve Media Package and 6 more | R3: Failed
A4: Number of TCs | B4: =COUNTA(F12:F1000) -> 199 | R4: Pending
A5: Testing Round | B5: Passed | C5: Failed | D5: Pending | E5: N/A | R5: N/A
A6: Round 1 | B6: =COUNTIF($F$10:$F$998,B$5) -> 73 | C6: =COUNTIF($F$10:$F$998,C$5) -> 0 | D6: =COUNTIF($F$10:$F$998,D$5) -> 126 | E6: =COUNTIF($F$10:$F$998,E$5) -> 0
A7: Round 2 | B7: =COUNTIF($I$10:$I$998,B$5) -> 0 | C7: =COUNTIF($I$10:$I$998,C$5) -> 0 | D7: =COUNTIF($I$10:$I$998,D$5) -> 199 | E7: =COUNTIF($I$10:$I$998,E$5) -> 0
A8: Round 3 | B8: =COUNTIF($L$10:$L$998,B$5) -> 0 | C8: =COUNTIF($L$10:$L$998,C$5) -> 0 | D8: =COUNTIF($L$10:$L$998,D$5) -> 199 | E8: =COUNTIF($L$10:$L$998,E$5) -> 0
A10: Test Case ID | B10: Test Case Description | C10: Test Case Procedure | D10: Expected Results | E10: Pre-conditions | F10: Round 1 | G10: Test date | H10: Tester | I10: Round 2 | J10: Test date | K10: Tester | L10: Round 3 | M10: Test date | N10: Tester | O10: Note
A11: 3.5.1 Create Media Package
A12: FR3.5.1-01 | B12: [Normal] Create Media Package with agencyId = existing agency, name = Starter, type = BY_DURATION | C12: 1. Prepare the state listed in Pre-conditions. 2. Call MediaPackageServiceImpl.createCustomPackage with: agencyId = existing agency; name = Starter; type = BY_DURATION; durationWeeks = 4; budgetAmount = null; sourceTemplateId = null. 3. Check the response / error and the log. | D12: MediaPackageResponse(isTemplate=false, agencyId, availableToWorkspaces=true) Log: Package saved | E12: - Can connect with server - Agency exists - User is OWNER of agency | F12: Passed | G12: 46300 | H12: Lộc | I12: Pending | L12: Pending
A13: FR3.5.1-02 | B13: [Normal] Create Media Package with agencyId = existing agency, name = Budget Pack, type = BY_BUDGET | C13: 1. Prepare the state listed in Pre-conditions. 2. Call MediaPackageServiceImpl.createCustomPackage with: agencyId = existing agency; name = Budget Pack; type = BY_BUDGET; budgetAmount = 5000.00; durationWeeks = null; sourceTemplateId = null. 3. Check the response / error and the log. | D13: MediaPackageResponse(packageType=BY_BUDGET, budgetAmount=5000.00) | E13: - Can connect with server - Agency exists - User is OWNER of agency | F13: Passed | G13: 46300 | H13: Lộc | I13: Pending | L13: Pending
A14: FR3.5.1-03 | B14: [Normal] Create Media Package with agencyId = existing agency, name = Full Pack, type = FULL_DELEGATION | C14: 1. Prepare the state listed in Pre-conditions. 2. Call MediaPackageServiceImpl.createCustomPackage with: agencyId = existing agency; name = Full Pack; type = FULL_DELEGATION; durationWeeks = null; budgetAmount = null; sourceTemplateId = null. 3. Check the response / error and the log. | D14: MediaPackageResponse(packageType=FULL_DELEGATION) | E14: - Can connect with server - Agency exists - User is OWNER of agency | F14: Passed | G14: 46300 | H14: Lộc | I14: Pending | L14: Pending
A15: FR3.5.1-04 | B15: [Normal] Create Media Package with agencyId = existing agency, name = From Template, type = BY_DURATION | C15: 1. Prepare the state listed in Pre-conditions. 2. Call MediaPackageServiceImpl.createCustomPackage with: agencyId = existing agency; name = From Template; type = BY_DURATION; durationWeeks = 8; sourceTemplateId = valid template id. 3. Check the response / error and the log. | D15: MediaPackageResponse(sourceTemplateId set, isTemplate=false) | E15: - Can connect with server - Agency exists - User is OWNER of agency - Source template is a system template | F15: Passed | G15: 46300 | H15: Lộc | I15: Pending | L15: Pending
A16: FR3.5.1-05 | B16: [Normal] Create Media Package with agencyId = existing agency, name = Padded , type = FULL_DELEGATION | C16: 1. Prepare the state listed in Pre-conditions. 2. Call MediaPackageServiceImpl.createCustomPackage with: agencyId = existing agency; name = Padded ; type = FULL_DELEGATION; scopeDescription = scope text . 3. Check the response / error and the log. | D16: name trimmed to 'Padded', scopeDescription trimmed | E16: - Can connect with server - Agency exists - User is OWNER of agency | F16: Passed | G16: 46300 | H16: Lộc | I16: Pending | L16: Pending
A17: FR3.5.1-06 | B17: [Normal] Create Media Package with agencyId = existing agency, name = Blank Scope, type = FULL_DELEGATION | C17: 1. Prepare the state listed in Pre-conditions. 2. Call MediaPackageServiceImpl.createCustomPackage with: agencyId = existing agency; name = Blank Scope; type = FULL_DELEGATION; scopeDescription = blank. 3. Check the response / error and the log. | D17: MediaPackageResponse(scopeDescription=null) | E17: - Can connect with server - Agency exists - User is OWNER of agency | F17: Passed | G17: 46300 | H17: Lộc | I17: Pending | L17: Pending
A18: FR3.5.1-07 | B18: [Normal] Create Media Package with agencyId = existing agency, name = Mgr Pack, type = FULL_DELEGATION | C18: 1. Prepare the state listed in Pre-conditions. 2. Call MediaPackageServiceImpl.createCustomPackage with: agencyId = existing agency; name = Mgr Pack; type = FULL_DELEGATION; workspaceId = workspace of same agency. 3. Check the response / error and the log. | D18: MediaPackageResponse(createdBy=manager id) | E18: - Can connect with server - Agency exists - User is MANAGER of workspace - Workspace belongs to the agency | F18: Passed | G18: 46300 | H18: Lộc | I18: Pending | L18: Pending
A19: FR3.5.1-08 | B19: [Normal] Create Media Package with agencyId = existing agency, name = Owner With Ws, type = FULL_DELEGATION | C19: 1. Prepare the state listed in Pre-conditions. 2. Call MediaPackageServiceImpl.createCustomPackage with: agencyId = existing agency; name = Owner With Ws; type = FULL_DELEGATION; workspaceId = any (ignored). 3. Check the response / error and the log. | D19: Owner path skips workspace check; package created | E19: - Can connect with server - Agency exists - User is OWNER of agency | F19: Passed | G19: 46300 | H19: Lộc | I19: Pending | L19: Pending
A20: FR3.5.1-09 | B20: [Boundary] Create Media Package with agencyId = existing agency, name = A, type = BY_DURATION | C20: 1. Prepare the state listed in Pre-conditions. 2. Call MediaPackageServiceImpl.createCustomPackage with: agencyId = existing agency; name = A; type = BY_DURATION; durationWeeks = 1. 3. Check the response / error and the log. | D20: MediaPackageResponse(durationWeeks=1) | E20: - Can connect with server - Agency exists - User is OWNER of agency | F20: Passed | G20: 46300 | H20: Lộc | I20: Pending | L20: Pending
A21: FR3.5.1-10 | B21: [Boundary] Create Media Package with agencyId = existing agency, name = Zero Budget, type = BY_BUDGET | C21: 1. Prepare the state listed in Pre-conditions. 2. Call MediaPackageServiceImpl.createCustomPackage with: agencyId = existing agency; name = Zero Budget; type = BY_BUDGET; budgetAmount = 0. 3. Check the response / error and the log. | D21: MediaPackageResponse(budgetAmount=0) - no range check in service | E21: - Can connect with server - Agency exists - User is OWNER of agency | F21: Passed | G21: 46300 | H21: Lộc | I21: Pending | L21: Pending
A22: FR3.5.1-11 | B22: [Boundary] Create Media Package with agencyId = existing agency, name = Dur+Budget, type = BY_DURATION | C22: 1. Prepare the state listed in Pre-conditions. 2. Call MediaPackageServiceImpl.createCustomPackage with: agencyId = existing agency; name = Dur+Budget; type = BY_DURATION; durationWeeks = 4; budgetAmount = 1000. 3. Check the response / error and the log. | D22: Created; extra budgetAmount persisted (only required field checked) | E22: - Can connect with server - Agency exists - User is OWNER of agency | F22: Passed | G22: 46300 | H22: Lộc | I22: Pending | L22: Pending
A23: FR3.5.1-12 | B23: [Abnormal] Create Media Package with agencyId = existing agency, name = Dur Missing, type = BY_DURATION | C23: 1. Prepare the state listed in Pre-conditions. 2. Call MediaPackageServiceImpl.createCustomPackage with: agencyId = existing agency; name = Dur Missing; type = BY_DURATION; durationWeeks = null. 3. Check the response / error and the log. | D23: Error: INVALID_MEDIA_PACKAGE_CONFIGURATION: Media package fields do not match its type | E23: - Can connect with server - Agency exists - User is OWNER of agency | F23: Passed | G23: 46300 | H23: Lộc | I23: Pending | L23: Pending
... A31: FR3.5.1-20 | B31: [Abnormal] Create Media Package with agencyId = existing agency, name = X, type = FULL_DELEGATION | C31: 1. Prepare the state listed in Pre-conditions. 2. Call MediaPackageServiceImpl.createCustomPackage with: agencyId = existing agency; name = X; type = FULL_DELEGATION; workspaceId = non-existent workspace. 3. Check the response / error and the log. | D31: Error: WORKSPACE_NOT_FOUND: Workspace not found | E31: - Can connect with server - Agency exists - User is not owner of agency | F31: Passed | G31: 46300 | H31: Lộc | I31: Pending | L31: Pending
A32: 3.5.2 View the Template Media Package
A33: FR3.5.2-01 | B33: [Normal] View the Template Media Package with workspaceId = existing workspace | C33: 1. Prepare the state listed in Pre-conditions. 2. Call MediaPackageServiceImpl.getWorkspacePackage with: workspaceId = existing workspace. 3. Check the response / error and the log. | D33: WorkspaceMediaPackageResponse(packageType=BY_DURATION, durationWeeks, termsVersion=1, status=DRAFT) | E33: - Can connect with server - Workspace exists - Workspace has selected package - Package type is BY_DURATION | F33: Passed | G33: 46300 | H33: Lộc | I33: Pending | L33: Pending
A34: FR3.5.2-02 | B34: [Normal] View the Template Media Package with workspaceId = existing workspace | C34: 1. Prepare the state listed in Pre-conditions. 2. Call MediaPackageServiceImpl.getWorkspacePackage with: workspaceId = existing workspace. 3. Check the response / error and the log. | D34: WorkspaceMediaPackageResponse(packageType=BY_BUDGET, budgetAmount) | E34: - Can connect with server - Workspace exists - Workspace has selected package - Package type is BY_BUDGET | F34: Passed | G34: 46300 | H34: Lộc | I34: Pending | L34: Pending
A35: FR3.5.2-03 | B35: [Normal] View the Template Media Package with workspaceId = existing workspace | C35: 1. Prepare the state listed in Pre-conditions. 2. Call MediaPackageServiceImpl.getWorkspacePackage with: workspaceId = existing workspace. 3. Check the response / error and the log. | D35: WorkspaceMediaPackageResponse(packageType=FULL_DELEGATION, no duration/budget) | E35: - Can connect with server - Workspace exists - Workspace has selected package - Package type is FULL_DELEGATION | F35: Passed | G35: 46300 | H35: Lộc | I35: Pending | L35: Pending
A36: FR3.5.2-04 | B36: [Normal] View the Template Media Package with workspaceId = existing workspace | C36: 1. Prepare the state listed in Pre-conditions. 2. Call MediaPackageServiceImpl.getWorkspacePackage with: workspaceId = existing workspace. 3. Check the response / error and the log. | D36: 200 OK - null (no-selection response) | E36: - Can connect with server - Workspace exists - Workspace has no selected package | F36: Passed | G36: 46300 | H36: Lộc | I36: Pending | L36: Pending
A37: FR3.5.2-05 | B37: [Normal] View the Template Media Package with workspaceId = existing workspace | C37: 1. Prepare the state listed in Pre-conditions. 2. Call MediaPackageServiceImpl.getWorkspacePackage with: workspaceId = existing workspace. 3. Check the response / error and the log. | D37: Response with status=CLIENT_REQUESTED_CHANGE, finalTerms parsed | E37: - Can connect with server - Workspace exists - Workspace has selected package - Negotiation status CLIENT_REQUESTED_CHANGE | F37: Passed | G37: 46300 | H37: Lộc | I37: Pending | L37: Pending
A38: FR3.5.2-06 | B38: [Normal] View the Template Media Package with workspaceId = existing workspace | C38: 1. Prepare the state listed in Pre-conditions. 2. Call MediaPackageServiceImpl.getWorkspacePackage with: workspaceId = existing workspace. 3. Check the response / error and the log. | D38: Response with status=AGENCY_COUNTERED, approvedByAgencyAt set | E38: - Can connect with server - Workspace exists - Workspace has selected package - Negotiation status AGENCY_COUNTERED | F38: Passed | G38: 46300 | H38: Lộc | I38: Pending | L38: Pending
A39: FR3.5.2-07 | B39: [Normal] View the Template Media Package with workspaceId = existing workspace | C39: 1. Prepare the state listed in Pre-conditions. 2. Call MediaPackageServiceImpl.getWorkspacePackage with: workspaceId = existing workspace. 3. Check the response / error and the log. | D39: Response with status=APPROVED, both approval timestamps set | E39: - Can connect with server - Workspace exists - Workspace has selected package - Both parties approved | F39: Passed | G39: 46300 | H39: Lộc | I39: Pending | L39: Pending
A40: FR3.5.2-08 | B40: [Normal] View the Template Media Package with workspaceId = existing workspace | C40: 1. Prepare the state listed in Pre-conditions. 2. Call MediaPackageServiceImpl.getWorkspacePackage with: workspaceId = existing workspace. 3. Check the response / error and the log. | D40: Selected package still returned | E40: - Can connect with server - Workspace exists - Workspace has selected package - Package hidden by Owner after selection | F40: Passed | G40: 46300 | H40: Lộc | I40: Pending | L40: Pending
A41: FR3.5.2-09 | B41: [Normal] View the Template Media Package with workspaceId = existing workspace | C41: 1. Prepare the state listed in Pre-conditions. 2. Call MediaPackageServiceImpl.getWorkspacePackage with: workspaceId = existing workspace. 3. Check the response / error and the log. | D41: Effective terms reflect latest finalTerms and termsVersion | E41: - Can connect with server - Workspace exists - Workspace has selected package - finalTerms edited by negotiation | F41: Passed | G41: 46300 | H41: Lộc | I41: Pending | L41: Pending
A42: FR3.5.2-10 | B42: [Boundary] View the Template Media Package with workspaceId = existing workspace | C42: 1. Prepare the state listed in Pre-conditions. 2. Call MediaPackageServiceImpl.getWorkspacePackage with: workspaceId = existing workspace. 3. Check the response / error and the log. | D42: termsVersion=1 returned | E42: - Can connect with server - Workspace exists - Workspace has selected package - termsVersion is 1 | F42: Passed | G42: 46300 | H42: Lộc | I42: Pending | L42: Pending
A43: FR3.5.2-11 | B43: [Boundary] View the Template Media Package with workspaceId = existing workspace | C43: 1. Prepare the state listed in Pre-conditions. 2. Call MediaPackageServiceImpl.getWorkspacePackage with: workspaceId = existing workspace. 3. Check the response / error and the log. | D43: parseTerms fallback; response returned without error | E43: - Can connect with server - Workspace exists - Workspace has selected package - finalTerms is invalid JSON | F43: Passed | G43: 46300 | H43: Lộc | I43: Pending | L43: Pending
A44: FR3.5.2-12 | B44: [Abnormal] View the Template Media Package with workspaceId = non-existent id | C44: 1. Prepare the state listed in Pre-conditions. 2. Call MediaPackageServiceImpl.getWorkspacePackage with: workspaceId = non-existent id. 3. Check the response / error and the log. | D44: Error: WORKSPACE_NOT_FOUND: Workspace not found | E44: - Can connect with server - Workspace exists | F44: Passed | G44: 46300 | H44: Lộc | I44: Pending | L44: Pending
... A49: FR3.5.2-17 | B49: [Abnormal] View the Template Media Package with workspaceId = non-existent id, op = listAvailablePackages | C49: 1. Prepare the state listed in Pre-conditions. 2. Call MediaPackageServiceImpl.getWorkspacePackage with: workspaceId = non-existent id; op = listAvailablePackages. 3. Check the response / error and the log. | D49: Error: WORKSPACE_NOT_FOUND: Workspace not found | E49: - Can connect with server - Workspace exists | F49: Passed | G49: 46300 | H49: Lộc | I49: Pending | L49: Pending
A50: 3.5.3 Request Media Package (Negotiate Terms)
A51: FR3.5.3-01 | B51: [Normal] Request Media Package (Negotiate Terms) with workspaceId = existing workspace, budgetAmount = 7000.00 | C51: 1. Prepare the state listed in Pre-conditions. 2. Call MediaPackageServiceImpl.negotiateTerms with: workspaceId = existing workspace; budgetAmount = 7000.00. 3. Check the response / error and the log. | D51: status=CLIENT_REQUESTED_CHANGE, termsVersion+1, approvedByClientAt set, agency approval null | E51: - Can connect with server - Workspace exists - Workspace has selected package - User is CLIENT of workspace - Status DRAFT | F51: Passed | G51: 46300 | H51: Lộc | I51: Pending | L51: Pending
A52: FR3.5.3-02 | B52: [Normal] Request Media Package (Negotiate Terms) with workspaceId = existing workspace, durationWeeks = 6 | C52: 1. Prepare the state listed in Pre-conditions. 2. Call MediaPackageServiceImpl.negotiateTerms with: workspaceId = existing workspace; durationWeeks = 6. 3. Check the response / error and the log. | D52: status=AGENCY_COUNTERED, approvedByAgencyAt set, client approval null | E52: - Can connect with server - Workspace exists - Workspace has selected package - User is MANAGER of workspace - Status CLIENT_REQUESTED_CHANGE | F52: Passed | G52: 46300 | H52: Lộc | I52: Pending | L52: Pending
A53: FR3.5.3-03 | B53: [Normal] Request Media Package (Negotiate Terms) with workspaceId = existing workspace, scopeDescription = New scope | C53: 1. Prepare the state listed in Pre-conditions. 2. Call MediaPackageServiceImpl.negotiateTerms with: workspaceId = existing workspace; scopeDescription = New scope. 3. Check the response / error and the log. | D53: status=AGENCY_COUNTERED, scopeDescription updated | E53: - Can connect with server - Workspace exists - Workspace has selected package - User is OWNER of agency - Status CLIENT_REQUESTED_CHANGE | F53: Passed | G53: 46300 | H53: Lộc | I53: Pending | L53: Pending
A54: FR3.5.3-04 | B54: [Normal] Request Media Package (Negotiate Terms) with workspaceId = existing workspace, budgetAmount = 6500.00 | C54: 1. Prepare the state listed in Pre-conditions. 2. Call MediaPackageServiceImpl.negotiateTerms with: workspaceId = existing workspace; budgetAmount = 6500.00. 3. Check the response / error and the log. | D54: status=CLIENT_REQUESTED_CHANGE; agency approval cleared | E54: - Can connect with server - Workspace exists - Workspace has selected package - User is CLIENT of workspace - Status AGENCY_COUNTERED | F54: Passed | G54: 46300 | H54: Lộc | I54: Pending | L54: Pending
A55: FR3.5.3-05 | B55: [Normal] Request Media Package (Negotiate Terms) with workspaceId = existing workspace, budgetAmount = 1000, durationWeeks = 4 | C55: 1. Prepare the state listed in Pre-conditions. 2. Call MediaPackageServiceImpl.negotiateTerms with: workspaceId = existing workspace; budgetAmount = 1000; durationWeeks = 4; scopeDescription = s. 3. Check the response / error and the log. | D55: All three term fields updated in finalTerms | E55: - Can connect with server - Workspace exists - Workspace has selected package - User is CLIENT of workspace - Status DRAFT | F55: Passed | G55: 46300 | H55: Lộc | I55: Pending | L55: Pending
A56: FR3.5.3-06 | B56: [Normal] Request Media Package (Negotiate Terms) with workspaceId = existing workspace, budgetAmount = null, durationWeeks = null | C56: 1. Prepare the state listed in Pre-conditions. 2. Call MediaPackageServiceImpl.negotiateTerms with: workspaceId = existing workspace; budgetAmount = null; durationWeeks = null; scopeDescription = null. 3. Check the response / error and the log. | D56: No field changed but termsVersion still +1 | E56: - Can connect with server - Workspace exists - Workspace has selected package - User is CLIENT of workspace - Status DRAFT | F56: Passed | G56: 46300 | H56: Lộc | I56: Pending | L56: Pending
A57: FR3.5.3-07 | B57: [Normal] Request Media Package (Negotiate Terms) with workspaceId = existing workspace, budgetAmount = 2nd round value | C57: 1. Prepare the state listed in Pre-conditions. 2. Call MediaPackageServiceImpl.negotiateTerms with: workspaceId = existing workspace; budgetAmount = 2nd round value. 3. Check the response / error and the log. | D57: termsVersion increments each round (2 -> 3) | E57: - Can connect with server - Workspace exists - Workspace has selected package - User is CLIENT of workspace - Multiple negotiation rounds | F57: Passed | G57: 46300 | H57: Lộc | I57: Pending | L57: Pending
A58: FR3.5.3-08 | B58: [Normal] Request Media Package (Negotiate Terms) with workspaceId = existing workspace, budgetAmount = 900 | C58: 1. Prepare the state listed in Pre-conditions. 2. Call MediaPackageServiceImpl.negotiateTerms with: workspaceId = existing workspace; budgetAmount = 900. 3. Check the response / error and the log. | D58: Role resolved as CLIENT via clientProfile; change accepted | E58: - Can connect with server - Workspace exists - Workspace has selected package - User is CLIENT of workspace - Client resolved via clientProfile (not direct member) | F58: Passed | G58: 46300 | H58: Lộc | I58: Pending | L58: Pending
A59: FR3.5.3-09 | B59: [Normal] Request Media Package (Negotiate Terms) with workspaceId = existing workspace, durationWeeks = 3 | C59: 1. Prepare the state listed in Pre-conditions. 2. Call MediaPackageServiceImpl.negotiateTerms with: workspaceId = existing workspace; durationWeeks = 3. 3. Check the response / error and the log. | D59: Agency approval invalidated (null) | E59: - Can connect with server - Workspace exists - Workspace has selected package - User is CLIENT of workspace - Only agency approved before | F59: Passed | G59: 46300 | H59: Lộc | I59: Pending | L59: Pending
A60: FR3.5.3-10 | B60: [Boundary] Request Media Package (Negotiate Terms) with workspaceId = existing workspace, durationWeeks = 1 | C60: 1. Prepare the state listed in Pre-conditions. 2. Call MediaPackageServiceImpl.negotiateTerms with: workspaceId = existing workspace; durationWeeks = 1. 3. Check the response / error and the log. | D60: termsVersion=2 | E60: - Can connect with server - Workspace exists - Workspace has selected package - User is CLIENT of workspace - termsVersion is 1 | F60: Passed | G60: 46300 | H60: Lộc | I60: Pending | L60: Pending
A61: FR3.5.3-11 | B61: [Boundary] Request Media Package (Negotiate Terms) with workspaceId = existing workspace, budgetAmount = 100 | C61: 1. Prepare the state listed in Pre-conditions. 2. Call MediaPackageServiceImpl.negotiateTerms with: workspaceId = existing workspace; budgetAmount = 100. 3. Check the response / error and the log. | D61: Terms rebuilt from empty object; update succeeds | E61: - Can connect with server - Workspace exists - Workspace has selected package - User is CLIENT of workspace - finalTerms is corrupt JSON | F61: Passed | G61: 46300 | H61: Lộc | I61: Pending | L61: Pending
A62: FR3.5.3-12 | B62: [Boundary] Request Media Package (Negotiate Terms) with workspaceId = existing workspace, scopeDescription = blank | C62: 1. Prepare the state listed in Pre-conditions. 2. Call MediaPackageServiceImpl.negotiateTerms with: workspaceId = existing workspace; scopeDescription = blank. 3. Check the response / error and the log. | D62: scopeDescription stored as null | E62: - Can connect with server - Workspace exists - Workspace has selected package - User is CLIENT of workspace | F62: Passed | G62: 46300 | H62: Lộc | I62: Pending | L62: Pending
... A68: FR3.5.3-18 | B68: [Abnormal] Request Media Package (Negotiate Terms) with workspaceId = non-existent id, budgetAmount = 100 | C68: 1. Prepare the state listed in Pre-conditions. 2. Call MediaPackageServiceImpl.negotiateTerms with: workspaceId = non-existent id; budgetAmount = 100. 3. Check the response / error and the log. | D68: Error: WORKSPACE_NOT_FOUND: Workspace not found | E68: - Can connect with server - Workspace exists | F68: Passed | G68: 46300 | H68: Lộc | I68: Pending | L68: Pending
A69: 3.5.4 Approve Media Package
A70: FR3.5.4-01 | B70: [Normal] Approve Media Package with workspaceId = existing workspace | C70: 1. Prepare the state listed in Pre-conditions. 2. Call MediaPackageServiceImpl.approvePackage with: workspaceId = existing workspace. 3. Check the response / error and the log. | D70: approvedByAgencyAt set; status unchanged (not APPROVED) | E70: - Can connect with server - Workspace exists - Workspace has selected package - User is OWNER of agency - Client not yet approved | F70: Passed | G70: 46300 | H70: Lộc | I70: Pending | L70: Pending
A71: FR3.5.4-02 | B71: [Normal] Approve Media Package with workspaceId = existing workspace | C71: 1. Prepare the state listed in Pre-conditions. 2. Call MediaPackageServiceImpl.approvePackage with: workspaceId = existing workspace. 3. Check the response / error and the log. | D71: approvedByAgencyAt set; status unchanged | E71: - Can connect with server - Workspace exists - Workspace has selected package - User is MANAGER of workspace - Client not yet approved | F71: Passed | G71: 46300 | H71: Lộc | I71: Pending | L71: Pending
A72: FR3.5.4-03 | B72: [Normal] Approve Media Package with workspaceId = existing workspace | C72: 1. Prepare the state listed in Pre-conditions. 2. Call MediaPackageServiceImpl.approvePackage with: workspaceId = existing workspace. 3. Check the response / error and the log. | D72: approvedByClientAt set; status unchanged | E72: - Can connect with server - Workspace exists - Workspace has selected package - User is CLIENT of workspace - Agency not yet approved | F72: Passed | G72: 46300 | H72: Lộc | I72: Pending | L72: Pending
A73: FR3.5.4-04 | B73: [Normal] Approve Media Package with workspaceId = existing workspace | C73: 1. Prepare the state listed in Pre-conditions. 2. Call MediaPackageServiceImpl.approvePackage with: workspaceId = existing workspace. 3. Check the response / error and the log. | D73: Both timestamps set; status=APPROVED | E73: - Can connect with server - Workspace exists - Workspace has selected package - User is CLIENT of workspace - Agency already approved same version | F73: Passed | G73: 46300 | H73: Lộc | I73: Pending | L73: Pending
A74: FR3.5.4-05 | B74: [Normal] Approve Media Package with workspaceId = existing workspace | C74: 1. Prepare the state listed in Pre-conditions. 2. Call MediaPackageServiceImpl.approvePackage with: workspaceId = existing workspace. 3. Check the response / error and the log. | D74: Both timestamps set; status=APPROVED | E74: - Can connect with server - Workspace exists - Workspace has selected package - User is OWNER of agency - Client already approved same version | F74: Passed | G74: 46300 | H74: Lộc | I74: Pending | L74: Pending
A75: FR3.5.4-06 | B75: [Normal] Approve Media Package with workspaceId = existing workspace | C75: 1. Prepare the state listed in Pre-conditions. 2. Call MediaPackageServiceImpl.approvePackage with: workspaceId = existing workspace. 3. Check the response / error and the log. | D75: Both timestamps set; status=APPROVED | E75: - Can connect with server - Workspace exists - Workspace has selected package - User is MANAGER of workspace - Client already approved same version | F75: Passed | G75: 46300 | H75: Lộc | I75: Pending | L75: Pending
A76: FR3.5.4-07 | B76: [Normal] Approve Media Package with workspaceId = existing workspace | C76: 1. Prepare the state listed in Pre-conditions. 2. Call MediaPackageServiceImpl.approvePackage with: workspaceId = existing workspace. 3. Check the response / error and the log. | D76: 200 - existing APPROVED response, idempotent, timestamps unchanged | E76: - Can connect with server - Workspace exists - Workspace has selected package - User is CLIENT of workspace - Status already APPROVED | F76: Passed | G76: 46300 | H76: Lộc | I76: Pending | L76: Pending
A77: FR3.5.4-08 | B77: [Normal] Approve Media Package with workspaceId = existing workspace | C77: 1. Prepare the state listed in Pre-conditions. 2. Call MediaPackageServiceImpl.approvePackage with: workspaceId = existing workspace. 3. Check the response / error and the log. | D77: 200 - existing APPROVED response, no state change | E77: - Can connect with server - Workspace exists - Workspace has selected package - User is OWNER of agency - Status already APPROVED | F77: Passed | G77: 46300 | H77: Lộc | I77: Pending | L77: Pending
A78: FR3.5.4-09 | B78: [Normal] Approve Media Package with workspaceId = existing workspace | C78: 1. Prepare the state listed in Pre-conditions. 2. Call MediaPackageServiceImpl.approvePackage with: workspaceId = existing workspace. 3. Check the response / error and the log. | D78: approvedByClientAt refreshed; still not APPROVED | E78: - Can connect with server - Workspace exists - Workspace has selected package - User is CLIENT of workspace - Client already approved, agency not | F78: Passed | G78: 46300 | H78: Lộc | I78: Pending | L78: Pending
A79: FR3.5.4-10 | B79: [Normal] Approve Media Package with workspaceId = existing workspace | C79: 1. Prepare the state listed in Pre-conditions. 2. Call MediaPackageServiceImpl.approvePackage with: workspaceId = existing workspace. 3. Check the response / error and the log. | D79: Only client timestamp set; agency must re-approve | E79: - Can connect with server - Workspace exists - Workspace has selected package - User is CLIENT of workspace - Terms changed after earlier approval (approvals reset) | F79: Passed | G79: 46300 | H79: Lộc | I79: Pending | L79: Pending
A80: FR3.5.4-11 | B80: [Boundary] Approve Media Package with workspaceId = existing workspace | C80: 1. Prepare the state listed in Pre-conditions. 2. Call MediaPackageServiceImpl.approvePackage with: workspaceId = existing workspace. 3. Check the response / error and the log. | D80: Both timestamps; APPROVED at termsVersion=1 | E80: - Can connect with server - Workspace exists - Workspace has selected package - User is CLIENT of workspace - Agency approved, terms version 1 | F80: Passed | G80: 46300 | H80: Lộc | I80: Pending | L80: Pending
A81: FR3.5.4-12 | B81: [Boundary] Approve Media Package with workspaceId = existing workspace | C81: 1. Prepare the state listed in Pre-conditions. 2. Call MediaPackageServiceImpl.approvePackage with: workspaceId = existing workspace. 3. Check the response / error and the log. | D81: First approval ever: single timestamp, status stays DRAFT | E81: - Can connect with server - Workspace exists - Workspace has selected package - User is OWNER of agency - Status DRAFT, no approvals | F81: Passed | G81: 46300 | H81: Lộc | I81: Pending | L81: Pending
... A87: FR3.5.4-18 | B87: [Abnormal] Approve Media Package with workspaceId = existing workspace | C87: 1. Prepare the state listed in Pre-conditions. 2. Call MediaPackageServiceImpl.approvePackage with: workspaceId = existing workspace. 3. Check the response / error and the log. | D87: Error: AGENCY_NOT_FOUND: Agency not found | E87: - Can connect with server - Workspace exists - Workspace has selected package - Workspace's agency missing | F87: Passed | G87: 46300 | H87: Lộc | I87: Pending | L87: Pending
A88: 3.5.5 Create Media Campaign
A89: FR3.5.5-01 | B89: [Normal] Create Media Campaign with workspaceId = valid, name = Q4 Launch, workItems = 1 item {id, name, type=POST, dueDate} | C89: 1. Prepare the state listed in Pre-conditions. 2. Call MediaCampaignServiceImpl.createCampaign with: workspaceId = valid; name = Q4 Launch; workItems = 1 item {id, name, type=POST, dueDate}. 3. Check the response / error and the log. | D89: 201 Created - MediaCampaignResponse(status=DRAFT) | E89: - Can connect with server - Package is APPROVED - User is MANAGER of workspace | F89: Pending | I89: Pending | L89: Pending | O89: Feature not implemented yet
A90: FR3.5.5-02 | B90: [Normal] Create Media Campaign with workspaceId = valid, name = Q4 Launch, workItems = 1 item {id, name, type=POST, dueDate} | C90: 1. Prepare the state listed in Pre-conditions. 2. Call MediaCampaignServiceImpl.createCampaign with: workspaceId = valid; name = Q4 Launch; workItems = 1 item {id, name, type=POST, dueDate}. 3. Check the response / error and the log. | D90: 201 Created - status=DRAFT | E90: - Can connect with server - Package is APPROVED - User is OWNER of agency | F90: Pending | I90: Pending | L90: Pending | O90: Feature not implemented yet
A91: FR3.5.5-03 | B91: [Normal] Create Media Campaign with workspaceId = valid, name = Live, workItems = 1 item type=LIVESTREAM | C91: 1. Prepare the state listed in Pre-conditions. 2. Call MediaCampaignServiceImpl.createCampaign with: workspaceId = valid; name = Live; workItems = 1 item type=LIVESTREAM. 3. Check the response / error and the log. | D91: 201 Created - workItem type LIVESTREAM kept | E91: - Can connect with server - Package is APPROVED - User is MANAGER of workspace | F91: Pending | I91: Pending | L91: Pending | O91: Feature not implemented yet
A92: FR3.5.5-04 | B92: [Normal] Create Media Campaign with workspaceId = valid, name = Survey, workItems = 1 item type=SURVEY | C92: 1. Prepare the state listed in Pre-conditions. 2. Call MediaCampaignServiceImpl.createCampaign with: workspaceId = valid; name = Survey; workItems = 1 item type=SURVEY. 3. Check the response / error and the log. | D92: 201 Created - workItem type SURVEY kept | E92: - Can connect with server - Package is APPROVED - User is MANAGER of workspace | F92: Pending | I92: Pending | L92: Pending | O92: Feature not implemented yet
A93: FR3.5.5-05 | B93: [Normal] Create Media Campaign with workspaceId = valid, name = Second, workItems = 1 item {id, name, type=POST, dueDate} | C93: 1. Prepare the state listed in Pre-conditions. 2. Call MediaCampaignServiceImpl.createCampaign with: workspaceId = valid; name = Second; workItems = 1 item {id, name, type=POST, dueDate}. 3. Check the response / error and the log. | D93: 201 Created - multiple campaigns allowed | E93: - Can connect with server - Package is APPROVED - User is MANAGER of workspace - Workspace already has a campaign | F93: Pending | I93: Pending | L93: Pending | O93: Feature not implemented yet
A94: FR3.5.5-06 | B94: [Normal] Create Media Campaign with workspaceId = valid, name = Stable, workItems = 3 items without ids | C94: 1. Prepare the state listed in Pre-conditions. 2. Call MediaCampaignServiceImpl.createCampaign with: workspaceId = valid; name = Stable; workItems = 3 items without ids. 3. Check the response / error and the log. | D94: 201 Created - stable work item IDs generated | E94: - Can connect with server - Package is APPROVED - User is MANAGER of workspace | F94: Pending | I94: Pending | L94: Pending | O94: Feature not implemented yet
A95: FR3.5.5-07 | B95: [Normal] Create Media Campaign with workspaceId = valid, name = Preserve, workItems = items with client-supplied ids | C95: 1. Prepare the state listed in Pre-conditions. 2. Call MediaCampaignServiceImpl.createCampaign with: workspaceId = valid; name = Preserve; workItems = items with client-supplied ids. 3. Check the response / error and the log. | D95: 201 Created - provided stable IDs preserved | E95: - Can connect with server - Package is APPROVED - User is MANAGER of workspace | F95: Pending | I95: Pending | L95: Pending | O95: Feature not implemented yet
A96: FR3.5.5-08 | B96: [Normal] Create Media Campaign with workspaceId = valid, name = Ordered, workItems = 3 items | C96: 1. Prepare the state listed in Pre-conditions. 2. Call MediaCampaignServiceImpl.createCampaign with: workspaceId = valid; name = Ordered; workItems = 3 items. 3. Check the response / error and the log. | D96: Work items stored as JSONB in given order; no tasks created | E96: - Can connect with server - Package is APPROVED - User is MANAGER of workspace | F96: Pending | I96: Pending | L96: Pending | O96: Feature not implemented yet
A97: FR3.5.5-09 | B97: [Normal] Create Media Campaign with workspaceId = valid, name = Get, op = getCampaign | C97: 1. Prepare the state listed in Pre-conditions. 2. Call MediaCampaignServiceImpl.createCampaign with: workspaceId = valid; name = Get; op = getCampaign; workItems = 1 item {id, name, type=POST, dueDate}. 3. Check the response / error and the log. | D97: 200 OK - campaign detail | E97: - Can connect with server - Package is APPROVED - User is MANAGER of workspace | F97: Pending | I97: Pending | L97: Pending | O97: Feature not implemented yet
A98: FR3.5.5-10 | B98: [Normal] Create Media Campaign with workspaceId = valid, op = listByWorkspace | C98: 1. Prepare the state listed in Pre-conditions. 2. Call MediaCampaignServiceImpl.createCampaign with: workspaceId = valid; op = listByWorkspace. 3. Check the response / error and the log. | D98: 200 OK - list of campaigns for workspace | E98: - Can connect with server - Package is APPROVED - User is MANAGER of workspace | F98: Pending | I98: Pending | L98: Pending | O98: Feature not implemented yet
A99: FR3.5.5-11 | B99: [Boundary] Create Media Campaign with workspaceId = valid, name = Min, workItems = exactly 1 item | C99: 1. Prepare the state listed in Pre-conditions. 2. Call MediaCampaignServiceImpl.createCampaign with: workspaceId = valid; name = Min; workItems = exactly 1 item. 3. Check the response / error and the log. | D99: 201 Created - minimum work item count | E99: - Can connect with server - Package is APPROVED - User is MANAGER of workspace | F99: Pending | I99: Pending | L99: Pending | O99: Feature not implemented yet
A100: FR3.5.5-12 | B100: [Boundary] Create Media Campaign with workspaceId = valid, name = Big, workItems = max allowed items (spec TBD) | C100: 1. Prepare the state listed in Pre-conditions. 2. Call MediaCampaignServiceImpl.createCampaign with: workspaceId = valid; name = Big; workItems = max allowed items (spec TBD). 3. Check the response / error and the log. | D100: 201 Created - maximum work item count | E100: - Can connect with server - Package is APPROVED - User is MANAGER of workspace | F100: Pending | I100: Pending | L100: Pending | O100: Feature not implemented yet
... A111: FR3.5.5-23 | B111: [Abnormal] Create Media Campaign with campaignId = non-existent, op = getCampaign | C111: 1. Prepare the state listed in Pre-conditions. 2. Call MediaCampaignServiceImpl.createCampaign with: campaignId = non-existent; op = getCampaign. 3. Check the response / error and the log. | D111: Error: Campaign not found (404) | E111: - Can connect with server - Campaign exists in DRAFT | F111: Pending | I111: Pending | L111: Pending | O111: Feature not implemented yet
A112: 3.5.6 Approve Media Campaign
A113: FR3.5.6-01 | B113: [Normal] Approve Media Campaign with campaignId = valid | C113: 1. Prepare the state listed in Pre-conditions. 2. Call MediaCampaignServiceImpl.approveCampaign with: campaignId = valid. 3. Check the response / error and the log. | D113: Agency timestamp set; campaign not yet deployable | E113: - Can connect with server - Campaign exists in DRAFT - User is MANAGER of workspace | F113: Pending | I113: Pending | L113: Pending | O113: Feature not implemented yet
A114: FR3.5.6-02 | B114: [Normal] Approve Media Campaign with campaignId = valid | C114: 1. Prepare the state listed in Pre-conditions. 2. Call MediaCampaignServiceImpl.approveCampaign with: campaignId = valid. 3. Check the response / error and the log. | D114: Agency timestamp set; not deployable | E114: - Can connect with server - Campaign exists in DRAFT - User is OWNER of agency | F114: Pending | I114: Pending | L114: Pending | O114: Feature not implemented yet
A115: FR3.5.6-03 | B115: [Normal] Approve Media Campaign with campaignId = valid | C115: 1. Prepare the state listed in Pre-conditions. 2. Call MediaCampaignServiceImpl.approveCampaign with: campaignId = valid. 3. Check the response / error and the log. | D115: Client timestamp set; not deployable | E115: - Can connect with server - Campaign exists in DRAFT - User is CLIENT of workspace | F115: Pending | I115: Pending | L115: Pending | O115: Feature not implemented yet
A116: FR3.5.6-04 | B116: [Normal] Approve Media Campaign with campaignId = valid | C116: 1. Prepare the state listed in Pre-conditions. 2. Call MediaCampaignServiceImpl.approveCampaign with: campaignId = valid. 3. Check the response / error and the log. | D116: Both approvals; campaign deployable | E116: - Can connect with server - Campaign exists in DRAFT - Agency already approved - User is CLIENT of workspace | F116: Pending | I116: Pending | L116: Pending | O116: Feature not implemented yet
A117: FR3.5.6-05 | B117: [Normal] Approve Media Campaign with campaignId = valid | C117: 1. Prepare the state listed in Pre-conditions. 2. Call MediaCampaignServiceImpl.approveCampaign with: campaignId = valid. 3. Check the response / error and the log. | D117: Both approvals; campaign deployable | E117: - Can connect with server - Campaign exists in DRAFT - Client already approved - User is MANAGER of workspace | F117: Pending | I117: Pending | L117: Pending | O117: Feature not implemented yet
A118: FR3.5.6-06 | B118: [Normal] Approve Media Campaign with campaignId = valid, op = deploy | C118: 1. Prepare the state listed in Pre-conditions. 2. Call MediaCampaignServiceImpl.approveCampaign with: campaignId = valid; op = deploy. 3. Check the response / error and the log. | D118: 3 backlog tasks created with campaignId, no assignee; status IN_PROGRESS | E118: - Can connect with server - Campaign fully approved, 3 work items | F118: Pending | I118: Pending | L118: Pending | O118: Feature not implemented yet
A119: FR3.5.6-07 | B119: [Normal] Approve Media Campaign with campaignId = valid, op = deploy | C119: 1. Prepare the state listed in Pre-conditions. 2. Call MediaCampaignServiceImpl.approveCampaign with: campaignId = valid; op = deploy. 3. Check the response / error and the log. | D119: 1 task with workspaceId, type, name, dueDate, status=backlog | E119: - Can connect with server - Campaign fully approved, 1 work item | F119: Pending | I119: Pending | L119: Pending | O119: Feature not implemented yet
A120: FR3.5.6-08 | B120: [Normal] Approve Media Campaign with campaignId = valid, op = deploy | C120: 1. Prepare the state listed in Pre-conditions. 2. Call MediaCampaignServiceImpl.approveCampaign with: campaignId = valid; op = deploy. 3. Check the response / error and the log. | D120: Retry: same task count and identities, no duplicates | E120: - Can connect with server - Campaign already deployed | F120: Pending | I120: Pending | L120: Pending | O120: Feature not implemented yet
A121: FR3.5.6-09 | B121: [Normal] Approve Media Campaign with campaignId = valid, op = deploy | C121: 1. Prepare the state listed in Pre-conditions. 2. Call MediaCampaignServiceImpl.approveCampaign with: campaignId = valid; op = deploy. 3. Check the response / error and the log. | D121: Retry upserts remaining items on {campaignId, workItemId}; no duplicates | E121: - Can connect with server - Deploy partially failed in Mongo | F121: Pending | I121: Pending | L121: Pending | O121: Feature not implemented yet
A122: FR3.5.6-10 | B122: [Normal] Approve Media Campaign with campaignId = valid | C122: 1. Prepare the state listed in Pre-conditions. 2. Call MediaCampaignServiceImpl.approveCampaign with: campaignId = valid. 3. Check the response / error and the log. | D122: Idempotent response; no change | E122: - Can connect with server - Caller already approved this campaign | F122: Pending | I122: Pending | L122: Pending | O122: Feature not implemented yet
A123: FR3.5.6-11 | B123: [Boundary] Approve Media Campaign with campaignId = valid, op = deploy, workItems = 1 item | C123: 1. Prepare the state listed in Pre-conditions. 2. Call MediaCampaignServiceImpl.approveCampaign with: campaignId = valid; op = deploy; workItems = 1 item. 3. Check the response / error and the log. | D123: Boundary: single task created | E123: - Can connect with server - Campaign fully approved, 1 work item | F123: Pending | I123: Pending | L123: Pending | O123: Feature not implemented yet
A124: FR3.5.6-12 | B124: [Boundary] Approve Media Campaign with campaignId = valid, op = deploy, workItems = 0 items | C124: 1. Prepare the state listed in Pre-conditions. 2. Call MediaCampaignServiceImpl.approveCampaign with: campaignId = valid; op = deploy; workItems = 0 items. 3. Check the response / error and the log. | D124: No tasks created; status behaviour per spec | E124: - Can connect with server - Campaign fully approved, no work items | F124: Pending | I124: Pending | L124: Pending | O124: Feature not implemented yet
... A130: FR3.5.6-18 | B130: [Abnormal] Approve Media Campaign with campaignId = valid | C130: 1. Prepare the state listed in Pre-conditions. 2. Call MediaCampaignServiceImpl.approveCampaign with: campaignId = valid. 3. Check the response / error and the log. | D130: Error: Campaign not approvable in current state (409) | E130: - Can connect with server - Campaign is not DRAFT (e.g. IN_PROGRESS) | F130: Pending | I130: Pending | L130: Pending | O130: Feature not implemented yet
A131: 3.5.7 Create Content Request
A132: FR3.5.7-01 | B132: [Normal] Create Content Request with title = Promo post, description = Describe, type = POST | C132: 1. Prepare the state listed in Pre-conditions. 2. Call TaskContentServiceImpl.createContentRequest with: title = Promo post; description = Describe; type = POST; dueDate = future date. 3. Check the response / error and the log. | D132: 201 Created - ContentRequestResponse(status=PENDING) | E132: - Can connect with server - Workspace has Client member - User is CLIENT of workspace | F132: Pending | I132: Pending | L132: Pending | O132: Feature not implemented yet
A133: FR3.5.7-02 | B133: [Normal] Create Content Request with title = Promo post, description = Describe, type = LIVESTREAM | C133: 1. Prepare the state listed in Pre-conditions. 2. Call TaskContentServiceImpl.createContentRequest with: title = Promo post; description = Describe; type = LIVESTREAM; dueDate = future date. 3. Check the response / error and the log. | D133: 201 Created - type=LIVESTREAM | E133: - Can connect with server - Workspace has Client member - User is CLIENT of workspace | F133: Pending | I133: Pending | L133: Pending | O133: Feature not implemented yet
A134: FR3.5.7-03 | B134: [Normal] Create Content Request with title = Promo post, description = Describe, type = SURVEY | C134: 1. Prepare the state listed in Pre-conditions. 2. Call TaskContentServiceImpl.createContentRequest with: title = Promo post; description = Describe; type = SURVEY; dueDate = future date. 3. Check the response / error and the log. | D134: 201 Created - type=SURVEY | E134: - Can connect with server - Workspace has Client member - User is CLIENT of workspace | F134: Pending | I134: Pending | L134: Pending | O134: Feature not implemented yet
A135: FR3.5.7-04 | B135: [Normal] Create Content Request with title = Promo post, description = null, type = POST | C135: 1. Prepare the state listed in Pre-conditions. 2. Call TaskContentServiceImpl.createContentRequest with: title = Promo post; description = null; type = POST; dueDate = future date. 3. Check the response / error and the log. | D135: 201 Created - description optional | E135: - Can connect with server - Workspace has Client member - User is CLIENT of workspace | F135: Pending | I135: Pending | L135: Pending | O135: Feature not implemented yet
A136: FR3.5.7-05 | B136: [Normal] Create Content Request with title = No task check, description = Describe, type = POST | C136: 1. Prepare the state listed in Pre-conditions. 2. Call TaskContentServiceImpl.createContentRequest with: title = No task check; description = Describe; type = POST; dueDate = future date. 3. Check the response / error and the log. | D136: No task created in Mongo at creation | E136: - Can connect with server - Workspace has Client member - User is CLIENT of workspace | F136: Pending | I136: Pending | L136: Pending | O136: Feature not implemented yet
A137: FR3.5.7-06 | B137: [Normal] Create Content Request with title = Second, description = Describe, type = POST | C137: 1. Prepare the state listed in Pre-conditions. 2. Call TaskContentServiceImpl.createContentRequest with: title = Second; description = Describe; type = POST; dueDate = future date. 3. Check the response / error and the log. | D137: 201 Created - multiple requests allowed | E137: - Can connect with server - Workspace has Client member - User is CLIENT of workspace - Client already has pending request | F137: Pending | I137: Pending | L137: Pending | O137: Feature not implemented yet
A138: FR3.5.7-07 | B138: [Normal] Create Content Request with title = Trim me , description = Describe, type = POST | C138: 1. Prepare the state listed in Pre-conditions. 2. Call TaskContentServiceImpl.createContentRequest with: title = Trim me ; description = Describe; type = POST; dueDate = future date. 3. Check the response / error and the log. | D138: 201 Created - title trimmed | E138: - Can connect with server - Workspace has Client member - User is CLIENT of workspace | F138: Pending | I138: Pending | L138: Pending | O138: Feature not implemented yet
...

Sheet Content & Task
A2: Feature | B2: Content & Task | R2: Passed
A3: Test requirement | B3: Functional test of 3.6.1 Identify Task Detail; 3.6.2 Assign Task To Creator; 3.6.3 Add Comments On Task; 3.6.4 List Task View and 32 more | R3: Failed
A4: Number of TCs | B4: =COUNTA(F12:F1000) -> 662 | R4: Pending
A5: Testing Round | B5: Passed | C5: Failed | D5: Pending | E5: N/A | R5: N/A
A6: Round 1 | B6: =COUNTIF($F$10:$F$998,B$5) -> 151 | C6: =COUNTIF($F$10:$F$998,C$5) -> 0 | D6: =COUNTIF($F$10:$F$998,D$5) -> 511 | E6: =COUNTIF($F$10:$F$998,E$5) -> 0
A7: Round 2 | B7: =COUNTIF($I$10:$I$998,B$5) -> 0 | C7: =COUNTIF($I$10:$I$998,C$5) -> 0 | D7: =COUNTIF($I$10:$I$998,D$5) -> 662 | E7: =COUNTIF($I$10:$I$998,E$5) -> 0
A8: Round 3 | B8: =COUNTIF($L$10:$L$998,B$5) -> 0 | C8: =COUNTIF($L$10:$L$998,C$5) -> 0 | D8: =COUNTIF($L$10:$L$998,D$5) -> 662 | E8: =COUNTIF($L$10:$L$998,E$5) -> 0
A10: Test Case ID | B10: Test Case Description | C10: Test Case Procedure | D10: Expected Results | E10: Pre-conditions | F10: Round 1 | G10: Test date | H10: Tester | I10: Round 2 | J10: Test date | K10: Tester | L10: Round 3 | M10: Test date | N10: Tester | O10: Note
A11: 3.6.1 Identify Task Detail
A12: FR3.6.1-01 | B12: [Normal] Identify Task Detail with description = valid text, dueDate = future date, typeSpecificFields = valid post fields | C12: 1. Prepare the state listed in Pre-conditions. 2. Call TaskServiceImpl.identifyDetail with: description = valid text; dueDate = future date; typeSpecificFields = valid post fields. 3. Check the response / error and the log. | D12: 200 OK - task status=DETAIL_IDENTIFIED | E12: - Can connect with server - User is MANAGER of workspace - Task status is BACKLOG - Task type is POST | F12: Pending | I12: Pending | L12: Pending | O12: Feature not implemented yet
A13: FR3.6.1-02 | B13: [Normal] Identify Task Detail with description = valid text, dueDate = future date, typeSpecificFields = valid livestream fields | C13: 1. Prepare the state listed in Pre-conditions. 2. Call TaskServiceImpl.identifyDetail with: description = valid text; dueDate = future date; typeSpecificFields = valid livestream fields. 3. Check the response / error and the log. | D13: 200 OK - task status=DETAIL_IDENTIFIED | E13: - Can connect with server - User is MANAGER of workspace - Task status is BACKLOG - Task type is LIVESTREAM | F13: Pending | I13: Pending | L13: Pending | O13: Feature not implemented yet
A14: FR3.6.1-03 | B14: [Normal] Identify Task Detail with description = valid text, dueDate = future date, typeSpecificFields = valid survey fields | C14: 1. Prepare the state listed in Pre-conditions. 2. Call TaskServiceImpl.identifyDetail with: description = valid text; dueDate = future date; typeSpecificFields = valid survey fields. 3. Check the response / error and the log. | D14: 200 OK - task status=DETAIL_IDENTIFIED | E14: - Can connect with server - User is MANAGER of workspace - Task status is BACKLOG - Task type is SURVEY | F14: Pending | I14: Pending | L14: Pending | O14: Feature not implemented yet
A15: FR3.6.1-04 | B15: [Normal] Identify Task Detail with description = null (keep original), dueDate = future date | C15: 1. Prepare the state listed in Pre-conditions. 2. Call TaskServiceImpl.identifyDetail with: description = null (keep original); dueDate = future date. 3. Check the response / error and the log. | D15: 200 OK - original description kept, DETAIL_IDENTIFIED | E15: - Can connect with server - User is MANAGER of workspace - Task status is BACKLOG - Task from Content Request with client description | F15: Pending | I15: Pending | L15: Pending | O15: Feature not implemented yet
A16: FR3.6.1-05 | B16: [Normal] Identify Task Detail with description = original + extra notes, dueDate = future date | C16: 1. Prepare the state listed in Pre-conditions. 2. Call TaskServiceImpl.identifyDetail with: description = original + extra notes; dueDate = future date. 3. Check the response / error and the log. | D16: 200 OK - description updated, DETAIL_IDENTIFIED | E16: - Can connect with server - User is MANAGER of workspace - Task status is BACKLOG - Task from Content Request with client description | F16: Pending | I16: Pending | L16: Pending | O16: Feature not implemented yet
A17: FR3.6.1-06 | B17: [Normal] Identify Task Detail with description = valid text, dueDate = future date, typeSpecificFields = empty object | C17: 1. Prepare the state listed in Pre-conditions. 2. Call TaskServiceImpl.identifyDetail with: description = valid text; dueDate = future date; typeSpecificFields = empty object. 3. Check the response / error and the log. | D17: 200 OK - DETAIL_IDENTIFIED | E17: - Can connect with server - User is MANAGER of workspace - Task status is BACKLOG - Task type is POST | F17: Pending | I17: Pending | L17: Pending | O17: Feature not implemented yet
A18: FR3.6.1-07 | B18: [Normal] Identify Task Detail with description = valid text, dueDate = today | C18: 1. Prepare the state listed in Pre-conditions. 2. Call TaskServiceImpl.identifyDetail with: description = valid text; dueDate = today. 3. Check the response / error and the log. | D18: 200 OK - DETAIL_IDENTIFIED | E18: - Can connect with server - User is MANAGER of workspace - Task status is BACKLOG - Task type is POST | F18: Pending | I18: Pending | L18: Pending | O18: Feature not implemented yet
A19: FR3.6.1-08 | B19: [Boundary] Identify Task Detail with description = 1 char, dueDate = future date | C19: 1. Prepare the state listed in Pre-conditions. 2. Call TaskServiceImpl.identifyDetail with: description = 1 char; dueDate = future date. 3. Check the response / error and the log. | D19: 200 OK - DETAIL_IDENTIFIED | E19: - Can connect with server - User is MANAGER of workspace - Task status is BACKLOG - Task type is POST | F19: Pending | I19: Pending | L19: Pending | O19: Feature not implemented yet
A20: FR3.6.1-09 | B20: [Boundary] Identify Task Detail with description = max length text, dueDate = future date | C20: 1. Prepare the state listed in Pre-conditions. 2. Call TaskServiceImpl.identifyDetail with: description = max length text; dueDate = future date. 3. Check the response / error and the log. | D20: 200 OK - DETAIL_IDENTIFIED | E20: - Can connect with server - User is MANAGER of workspace - Task status is BACKLOG - Task type is POST | F20: Pending | I20: Pending | L20: Pending | O20: Feature not implemented yet
A21: FR3.6.1-10 | B21: [Boundary] Identify Task Detail with description = valid text, dueDate = tomorrow (min future) | C21: 1. Prepare the state listed in Pre-conditions. 2. Call TaskServiceImpl.identifyDetail with: description = valid text; dueDate = tomorrow (min future). 3. Check the response / error and the log. | D21: 200 OK - DETAIL_IDENTIFIED | E21: - Can connect with server - User is MANAGER of workspace - Task status is BACKLOG - Task type is POST | F21: Pending | I21: Pending | L21: Pending | O21: Feature not implemented yet
A22: FR3.6.1-11 | B22: [Boundary] Identify Task Detail with description = valid text, dueDate = far future (1 year) | C22: 1. Prepare the state listed in Pre-conditions. 2. Call TaskServiceImpl.identifyDetail with: description = valid text; dueDate = far future (1 year). 3. Check the response / error and the log. | D22: 200 OK - DETAIL_IDENTIFIED | E22: - Can connect with server - User is MANAGER of workspace - Task status is BACKLOG - Task type is POST | F22: Pending | I22: Pending | L22: Pending | O22: Feature not implemented yet
A23: FR3.6.1-12 | B23: [Abnormal] Identify Task Detail with description = valid text, dueDate = future date | C23: 1. Prepare the state listed in Pre-conditions. 2. Call TaskServiceImpl.identifyDetail with: description = valid text; dueDate = future date. 3. Check the response / error and the log. | D23: Error: 409 TASK_NOT_IN_BACKLOG | E23: - Can connect with server - User is MANAGER of workspace - Task status is ASSIGNED | F23: Pending | I23: Pending | L23: Pending | O23: Feature not implemented yet
... A29: FR3.6.1-18 | B29: [Abnormal] Identify Task Detail with description = null, dueDate = null | C29: 1. Prepare the state listed in Pre-conditions. 2. Call TaskServiceImpl.identifyDetail with: description = null; dueDate = null. 3. Check the response / error and the log. | D29: Error: 400 VALIDATION_ERROR - Request validation failed | E29: - Can connect with server - User is MANAGER of workspace - Task status is BACKLOG | F29: Pending | I29: Pending | L29: Pending | O29: Feature not implemented yet
A30: 3.6.2 Assign Task To Creator
A31: FR3.6.2-01 | B31: [Normal] Assign Task To Creator with assigneeId = valid creator, qcAssigneeId = null, requiresClientApproval = false | C31: 1. Prepare the state listed in Pre-conditions. 2. Call TaskServiceImpl.assignTask with: assigneeId = valid creator; qcAssigneeId = null; requiresClientApproval = false. 3. Check the response / error and the log. | D31: 200 OK - status=ASSIGNED, no QC step Log: Notification sent to assignee | E31: - Can connect with server - User is MANAGER of workspace - Task status is DETAIL_IDENTIFIED - assignee is MEMBER of workspace | F31: Pending | I31: Pending | L31: Pending | O31: Feature not implemented yet
A32: FR3.6.2-02 | B32: [Normal] Assign Task To Creator with assigneeId = valid creator, qcAssigneeId = other valid creator, requiresClientApproval = false | C32: 1. Prepare the state listed in Pre-conditions. 2. Call TaskServiceImpl.assignTask with: assigneeId = valid creator; qcAssigneeId = other valid creator; requiresClientApproval = false. 3. Check the response / error and the log. | D32: 200 OK - status=ASSIGNED, QC step enabled Log: Notification sent to assignee | E32: - Can connect with server - User is MANAGER of workspace - Task status is DETAIL_IDENTIFIED - assignee is MEMBER of workspace | F32: Pending | I32: Pending | L32: Pending | O32: Feature not implemented yet
A33: FR3.6.2-03 | B33: [Normal] Assign Task To Creator with assigneeId = valid creator, qcAssigneeId = null, requiresClientApproval = true | C33: 1. Prepare the state listed in Pre-conditions. 2. Call TaskServiceImpl.assignTask with: assigneeId = valid creator; qcAssigneeId = null; requiresClientApproval = true. 3. Check the response / error and the log. | D33: 200 OK - status=ASSIGNED, client approval required Log: Notification sent to assignee | E33: - Can connect with server - User is MANAGER of workspace - Task status is DETAIL_IDENTIFIED - assignee is MEMBER of workspace | F33: Pending | I33: Pending | L33: Pending | O33: Feature not implemented yet
A34: FR3.6.2-04 | B34: [Normal] Assign Task To Creator with assigneeId = valid creator, qcAssigneeId = other valid creator, requiresClientApproval = true | C34: 1. Prepare the state listed in Pre-conditions. 2. Call TaskServiceImpl.assignTask with: assigneeId = valid creator; qcAssigneeId = other valid creator; requiresClientApproval = true. 3. Check the response / error and the log. | D34: 200 OK - ASSIGNED, QC + client approval Log: Notification sent to assignee | E34: - Can connect with server - User is MANAGER of workspace - Task status is DETAIL_IDENTIFIED - assignee is MEMBER of workspace | F34: Pending | I34: Pending | L34: Pending | O34: Feature not implemented yet
A35: FR3.6.2-05 | B35: [Normal] Assign Task To Creator with assigneeId = valid creator, requiresClientApproval = false | C35: 1. Prepare the state listed in Pre-conditions. 2. Call TaskServiceImpl.assignTask with: assigneeId = valid creator; requiresClientApproval = false. 3. Check the response / error and the log. | D35: 200 OK - ASSIGNED, qcAssigneeId omitted treated as null Log: Notification sent to assignee | E35: - Can connect with server - User is MANAGER of workspace - Task status is DETAIL_IDENTIFIED - assignee is MEMBER of workspace | F35: Pending | I35: Pending | L35: Pending | O35: Feature not implemented yet
A36: FR3.6.2-06 | B36: [Boundary] Assign Task To Creator with assigneeId = the only creator, requiresClientApproval = false | C36: 1. Prepare the state listed in Pre-conditions. 2. Call TaskServiceImpl.assignTask with: assigneeId = the only creator; requiresClientApproval = false. 3. Check the response / error and the log. | D36: 200 OK - status=ASSIGNED Log: Notification sent to assignee | E36: - Can connect with server - User is MANAGER of workspace - Task status is DETAIL_IDENTIFIED - workspace has only 1 creator | F36: Pending | I36: Pending | L36: Pending | O36: Feature not implemented yet
A37: FR3.6.2-07 | B37: [Boundary] Assign Task To Creator with assigneeId = creator A, qcAssigneeId = creator B, requiresClientApproval = false | C37: 1. Prepare the state listed in Pre-conditions. 2. Call TaskServiceImpl.assignTask with: assigneeId = creator A; qcAssigneeId = creator B; requiresClientApproval = false. 3. Check the response / error and the log. | D37: 200 OK - QC is the last available creator Log: Notification sent to assignee | E37: - Can connect with server - User is MANAGER of workspace - Task status is DETAIL_IDENTIFIED - workspace has 2 creators | F37: Pending | I37: Pending | L37: Pending | O37: Feature not implemented yet
A38: FR3.6.2-08 | B38: [Abnormal] Assign Task To Creator with assigneeId = user with role CLIENT, requiresClientApproval = false | C38: 1. Prepare the state listed in Pre-conditions. 2. Call TaskServiceImpl.assignTask with: assigneeId = user with role CLIENT; requiresClientApproval = false. 3. Check the response / error and the log. | D38: Error: 400 INVALID_ASSIGNEE | E38: - Can connect with server - User is MANAGER of workspace - Task status is DETAIL_IDENTIFIED | F38: Pending | I38: Pending | L38: Pending | O38: Feature not implemented yet
A39: FR3.6.2-09 | B39: [Abnormal] Assign Task To Creator with assigneeId = user not in workspace, requiresClientApproval = false | C39: 1. Prepare the state listed in Pre-conditions. 2. Call TaskServiceImpl.assignTask with: assigneeId = user not in workspace; requiresClientApproval = false. 3. Check the response / error and the log. | D39: Error: 400 INVALID_ASSIGNEE | E39: - Can connect with server - User is MANAGER of workspace - Task status is DETAIL_IDENTIFIED | F39: Pending | I39: Pending | L39: Pending | O39: Feature not implemented yet
A40: FR3.6.2-10 | B40: [Abnormal] Assign Task To Creator with assigneeId = manager of workspace, requiresClientApproval = false | C40: 1. Prepare the state listed in Pre-conditions. 2. Call TaskServiceImpl.assignTask with: assigneeId = manager of workspace; requiresClientApproval = false. 3. Check the response / error and the log. | D40: Error: 400 INVALID_ASSIGNEE | E40: - Can connect with server - User is MANAGER of workspace - Task status is DETAIL_IDENTIFIED | F40: Pending | I40: Pending | L40: Pending | O40: Feature not implemented yet
A41: FR3.6.2-11 | B41: [Abnormal] Assign Task To Creator with assigneeId = null, requiresClientApproval = false | C41: 1. Prepare the state listed in Pre-conditions. 2. Call TaskServiceImpl.assignTask with: assigneeId = null; requiresClientApproval = false. 3. Check the response / error and the log. | D41: Error: 400 VALIDATION_ERROR - Request validation failed | E41: - Can connect with server - User is MANAGER of workspace - Task status is DETAIL_IDENTIFIED | F41: Pending | I41: Pending | L41: Pending | O41: Feature not implemented yet
A42: FR3.6.2-12 | B42: [Abnormal] Assign Task To Creator with assigneeId = valid creator, qcAssigneeId = same as assignee, requiresClientApproval = false | C42: 1. Prepare the state listed in Pre-conditions. 2. Call TaskServiceImpl.assignTask with: assigneeId = valid creator; qcAssigneeId = same as assignee; requiresClientApproval = false. 3. Check the response / error and the log. | D42: Error: 400 QC_CANNOT_BE_SAME_AS_ASSIGNEE | E42: - Can connect with server - User is MANAGER of workspace - Task status is DETAIL_IDENTIFIED | F42: Pending | I42: Pending | L42: Pending | O42: Feature not implemented yet
... A48: FR3.6.2-18 | B48: [Abnormal] Assign Task To Creator with assigneeId = valid creator, requiresClientApproval = null | C48: 1. Prepare the state listed in Pre-conditions. 2. Call TaskServiceImpl.assignTask with: assigneeId = valid creator; requiresClientApproval = null. 3. Check the response / error and the log. | D48: Error: 400 VALIDATION_ERROR - Request validation failed | E48: - Can connect with server - User is MANAGER of workspace - Task status is DETAIL_IDENTIFIED | F48: Pending | I48: Pending | L48: Pending | O48: Feature not implemented yet
A49: 3.6.3 Add Comments On Task
A50: FR3.6.3-01 | B50: [Normal] Add Comments On Task with content = valid text | C50: 1. Prepare the state listed in Pre-conditions. 2. Call TaskCommentServiceImpl.addComment with: content = valid text. 3. Check the response / error and the log. | D50: 201 Created - CommentResponse(id, content, authorId, createdAt) | E50: - Can connect with server - User is MANAGER of workspace - Task exists in workspace | F50: Pending | I50: Pending | L50: Pending | O50: Feature not implemented yet
A51: FR3.6.3-02 | B51: [Normal] Add Comments On Task with content = valid text | C51: 1. Prepare the state listed in Pre-conditions. 2. Call TaskCommentServiceImpl.addComment with: content = valid text. 3. Check the response / error and the log. | D51: 201 Created - CommentResponse | E51: - Can connect with server - User is CREATOR of workspace - Task exists in workspace | F51: Pending | I51: Pending | L51: Pending | O51: Feature not implemented yet
A52: FR3.6.3-03 | B52: [Normal] Add Comments On Task with content = valid text | C52: 1. Prepare the state listed in Pre-conditions. 2. Call TaskCommentServiceImpl.addComment with: content = valid text. 3. Check the response / error and the log. | D52: 201 Created - CommentResponse | E52: - Can connect with server - User is CLIENT of workspace - Task exists in workspace | F52: Pending | I52: Pending | L52: Pending | O52: Feature not implemented yet
A53: FR3.6.3-04 | B53: [Normal] Add Comments On Task with content = valid text | C53: 1. Prepare the state listed in Pre-conditions. 2. Call TaskCommentServiceImpl.addComment with: content = valid text. 3. Check the response / error and the log. | D53: 201 Created - comment allowed regardless of approval flag | E53: - Can connect with server - User is CLIENT of workspace - Task exists in workspace - Task requiresClientApproval=false | F53: Pending | I53: Pending | L53: Pending | O53: Feature not implemented yet
A54: FR3.6.3-05 | B54: [Normal] Add Comments On Task with content = text with @mention of member | C54: 1. Prepare the state listed in Pre-conditions. 2. Call TaskCommentServiceImpl.addComment with: content = text with @mention of member. 3. Check the response / error and the log. | D54: 201 Created - CommentResponse Log: Mentioned user notified | E54: - Can connect with server - User is MANAGER of workspace - Task exists in workspace | F54: Pending | I54: Pending | L54: Pending | O54: Feature not implemented yet
A55: FR3.6.3-06 | B55: [Normal] Add Comments On Task with content = valid text, attachments = 1 image URL | C55: 1. Prepare the state listed in Pre-conditions. 2. Call TaskCommentServiceImpl.addComment with: content = valid text; attachments = 1 image URL. 3. Check the response / error and the log. | D55: 201 Created - CommentResponse with attachment | E55: - Can connect with server - User is CREATOR of workspace - Task exists in workspace | F55: Pending | I55: Pending | L55: Pending | O55: Feature not implemented yet
A56: FR3.6.3-07 | B56: [Normal] Add Comments On Task with content = valid text, attachments = 2 reference links | C56: 1. Prepare the state listed in Pre-conditions. 2. Call TaskCommentServiceImpl.addComment with: content = valid text; attachments = 2 reference links. 3. Check the response / error and the log. | D56: 201 Created - CommentResponse with 2 attachments | E56: - Can connect with server - User is CREATOR of workspace - Task exists in workspace | F56: Pending | I56: Pending | L56: Pending | O56: Feature not implemented yet
A57: FR3.6.3-08 | B57: [Normal] Add Comments On Task with taskId = valid task | C57: 1. Prepare the state listed in Pre-conditions. 2. Call TaskCommentServiceImpl.addComment with: taskId = valid task. 3. Check the response / error and the log. | D57: 200 OK - list of 3 comments ordered by createdAt asc | E57: - Can connect with server - User is MANAGER of workspace - Task exists in workspace - Task has 3 comments | F57: Pending | I57: Pending | L57: Pending | O57: Feature not implemented yet
A58: FR3.6.3-09 | B58: [Normal] Add Comments On Task with taskId = valid task | C58: 1. Prepare the state listed in Pre-conditions. 2. Call TaskCommentServiceImpl.addComment with: taskId = valid task. 3. Check the response / error and the log. | D58: 200 OK - empty list | E58: - Can connect with server - User is MANAGER of workspace - Task exists in workspace - Task has no comments | F58: Pending | I58: Pending | L58: Pending | O58: Feature not implemented yet
A59: FR3.6.3-10 | B59: [Boundary] Add Comments On Task with content = 1 char | C59: 1. Prepare the state listed in Pre-conditions. 2. Call TaskCommentServiceImpl.addComment with: content = 1 char. 3. Check the response / error and the log. | D59: 201 Created - CommentResponse | E59: - Can connect with server - User is MANAGER of workspace - Task exists in workspace | F59: Pending | I59: Pending | L59: Pending | O59: Feature not implemented yet
A60: FR3.6.3-11 | B60: [Boundary] Add Comments On Task with content = max length text | C60: 1. Prepare the state listed in Pre-conditions. 2. Call TaskCommentServiceImpl.addComment with: content = max length text. 3. Check the response / error and the log. | D60: 201 Created - CommentResponse | E60: - Can connect with server - User is MANAGER of workspace - Task exists in workspace | F60: Pending | I60: Pending | L60: Pending | O60: Feature not implemented yet
A61: FR3.6.3-12 | B61: [Boundary] Add Comments On Task with content = max length + 1 chars | C61: 1. Prepare the state listed in Pre-conditions. 2. Call TaskCommentServiceImpl.addComment with: content = max length + 1 chars. 3. Check the response / error and the log. | D61: Error: 400 VALIDATION_ERROR - Request validation failed | E61: - Can connect with server - User is MANAGER of workspace - Task exists in workspace | F61: Pending | I61: Pending | L61: Pending | O61: Feature not implemented yet
... A68: FR3.6.3-19 | B68: [Abnormal] Add Comments On Task with content = valid text | C68: 1. Prepare the state listed in Pre-conditions. 2. Call TaskCommentServiceImpl.addComment with: content = valid text. 3. Check the response / error and the log. | D68: Error: 404 TASK_NOT_FOUND - Task not found | E68: - Can connect with server - User is MANAGER of workspace - Task belongs to another workspace | F68: Pending | I68: Pending | L68: Pending | O68: Feature not implemented yet
A69: 3.6.4 List Task View
A70: FR3.6.4-01 | B70: [Normal] List Task View with view = list, sort = dueDate, order = asc | C70: 1. Prepare the state listed in Pre-conditions. 2. Call TaskServiceImpl.listTasks with: view = list; sort = dueDate; order = asc; page = 0; size = 20. 3. Check the response / error and the log. | D70: 200 OK - tasks sorted by dueDate asc | E70: - Can connect with server - User is MANAGER of workspace - Workspace has tasks | F70: Pending | I70: Pending | L70: Pending | O70: Feature not implemented yet
A71: FR3.6.4-02 | B71: [Normal] List Task View with view = list, sort = dueDate, order = desc | C71: 1. Prepare the state listed in Pre-conditions. 2. Call TaskServiceImpl.listTasks with: view = list; sort = dueDate; order = desc; page = 0; size = 20. 3. Check the response / error and the log. | D71: 200 OK - tasks sorted by dueDate desc | E71: - Can connect with server - User is CREATOR of workspace - Workspace has tasks | F71: Pending | I71: Pending | L71: Pending | O71: Feature not implemented yet
A72: FR3.6.4-03 | B72: [Normal] List Task View with view = list, page = 0, size = 20 | C72: 1. Prepare the state listed in Pre-conditions. 2. Call TaskServiceImpl.listTasks with: view = list; page = 0; size = 20. 3. Check the response / error and the log. | D72: 200 OK - rows(id,title,type,assigneeName,status,dueDate) | E72: - Can connect with server - User is CLIENT of workspace - Workspace has tasks | F72: Pending | I72: Pending | L72: Pending | O72: Feature not implemented yet
A73: FR3.6.4-04 | B73: [Normal] List Task View with view = list, sort = title, order = asc | C73: 1. Prepare the state listed in Pre-conditions. 2. Call TaskServiceImpl.listTasks with: view = list; sort = title; order = asc; page = 0; size = 20. 3. Check the response / error and the log. | D73: 200 OK - sorted by title | E73: - Can connect with server - User is MANAGER of workspace - Workspace has tasks | F73: Pending | I73: Pending | L73: Pending | O73: Feature not implemented yet
A74: FR3.6.4-05 | B74: [Normal] List Task View with view = list, sort = status, order = asc | C74: 1. Prepare the state listed in Pre-conditions. 2. Call TaskServiceImpl.listTasks with: view = list; sort = status; order = asc; page = 0; size = 20. 3. Check the response / error and the log. | D74: 200 OK - sorted by status | E74: - Can connect with server - User is MANAGER of workspace - Workspace has tasks | F74: Pending | I74: Pending | L74: Pending | O74: Feature not implemented yet
A75: FR3.6.4-06 | B75: [Normal] List Task View with view = list, page = 0, size = 20 | C75: 1. Prepare the state listed in Pre-conditions. 2. Call TaskServiceImpl.listTasks with: view = list; page = 0; size = 20. 3. Check the response / error and the log. | D75: 200 OK - assigneeName null for backlog task | E75: - Can connect with server - User is MANAGER of workspace - Workspace has tasks - Task has no assignee | F75: Pending | I75: Pending | L75: Pending | O75: Feature not implemented yet
A76: FR3.6.4-07 | B76: [Normal] List Task View with view = list, page = 1, size = 20 | C76: 1. Prepare the state listed in Pre-conditions. 2. Call TaskServiceImpl.listTasks with: view = list; page = 1; size = 20. 3. Check the response / error and the log. | D76: 200 OK - second page with 5 tasks | E76: - Can connect with server - User is MANAGER of workspace - Workspace has tasks - 25 tasks in workspace | F76: Pending | I76: Pending | L76: Pending | O76: Feature not implemented yet
A77: FR3.6.4-08 | B77: [Boundary] List Task View with view = list, page = 0, size = 20 | C77: 1. Prepare the state listed in Pre-conditions. 2. Call TaskServiceImpl.listTasks with: view = list; page = 0; size = 20. 3. Check the response / error and the log. | D77: 200 OK - 20 tasks, totalElements=25 | E77: - Can connect with server - User is MANAGER of workspace - Workspace has tasks - 25 tasks in workspace | F77: Pending | I77: Pending | L77: Pending | O77: Feature not implemented yet
A78: FR3.6.4-09 | B78: [Boundary] List Task View with view = list, page = 0, size = 20 | C78: 1. Prepare the state listed in Pre-conditions. 2. Call TaskServiceImpl.listTasks with: view = list; page = 0; size = 20. 3. Check the response / error and the log. | D78: 200 OK - 20 tasks, 1 page | E78: - Can connect with server - User is MANAGER of workspace - Workspace has tasks - Exactly 20 tasks in workspace | F78: Pending | I78: Pending | L78: Pending | O78: Feature not implemented yet
A79: FR3.6.4-10 | B79: [Boundary] List Task View with view = list, page = 0, size = 1 | C79: 1. Prepare the state listed in Pre-conditions. 2. Call TaskServiceImpl.listTasks with: view = list; page = 0; size = 1. 3. Check the response / error and the log. | D79: 200 OK - 1 task | E79: - Can connect with server - User is MANAGER of workspace - Workspace has tasks | F79: Pending | I79: Pending | L79: Pending | O79: Feature not implemented yet
